/*       */ package utils.plugins.PluginManager;
/*       */ import com.a.a.a.g;
/*       */ import com.a.a.a.i;
/*       */ import com.a.a.c.R;
/*       */ import com.a.a.c.h;
/*       */ import com.a.a.d.g;
/*       */ import com.a.a.d.k;
/*       */ import com.a.a.d.l;
/*       */ import com.a.a.d.q;
/*       */ import com.rs.lO;
/*       */ import com.rs.lZ;
/*       */ import com.rs.mO;
/*       */ import com.rs.mP;
/*       */ import com.rs.mi;
/*       */ import com.rs.nZ;
/*       */ import com.rs.oj;
/*       */ import java.awt.Dimension;
/*       */ import java.awt.Point;
/*       */ import java.awt.Rectangle;
/*       */ import java.awt.event.KeyEvent;
/*       */ import java.io.InputStream;
/*       */ import java.io.OutputStream;
/*       */ import java.lang.reflect.Field;
/*       */ import java.lang.reflect.Method;
/*       */ import java.lang.reflect.ParameterizedType;
/*       */ import java.lang.reflect.Type;
/*       */ import java.util.ArrayList;
/*       */ import java.util.Iterator;
/*       */ import java.util.List;
/*       */ import java.util.Optional;
/*       */ import java.util.Set;
/*       */ import java.util.stream.Collectors;
/*       */ import javax.swing.SwingUtilities;
/*       */ import utils.ConfigChanged;
/*       */ import utils.WorldPoint;
/*       */ import utils.plugins.Plugin;
/*       */ import utils.plugins.PluginDependency;
/*       */ import utils.plugins.impl.NpcIndicatorsPlugin;
/*       */ import utils.plugins.impl.groundmarkers.TileIndicatorsPlugin;
/*       */ import utils.plugins.settings.config.Alpha;
/*       */ import utils.plugins.settings.config.Config;
/*       */ import utils.plugins.settings.config.ConfigGroup;
/*       */ import utils.plugins.settings.config.ConfigItem;
/*       */ import utils.plugins.settings.config.ConfigItemDescriptor;
/*       */ import utils.plugins.settings.config.ConfigSection;
/*       */ import utils.plugins.settings.config.ConfigSectionDescriptor;
/*       */ import utils.plugins.settings.config.Keybind;
/*       */ import utils.plugins.settings.config.ModifierlessKeybind;
/*       */ import utils.plugins.settings.config.Range;
/*       */ import utils.plugins.settings.config.Units;
/*       */ 
/*       */ public class PluginManager {
/*    53 */   private static final b log = c.j(PluginManager.class);
/*       */ 
/*       */ 
/*       */   
/*       */   private static final String PLUGIN_PACKAGE = "utils.plugins.impl";
/*       */ 
/*       */ 
/*       */   
/*    61 */   public static final File PLUGINS_CONFIG_FILE = new File(oE.cmz, "plugin configurations.txt");
/*       */   
/*    63 */   private static final c gson = new c();
/*       */   
/*       */   private final boolean developerMode;
/*       */   
/*       */   private final boolean safeMode;
/*    68 */   private final List<Plugin> plugins = new CopyOnWriteArrayList<>();
/*    69 */   private final List<Plugin> activePlugins = new CopyOnWriteArrayList<>();
/*       */   
/*    71 */   private static final Properties properties = new Properties();
/*       */ 
/*       */ 
/*       */ 
/*       */   
/*    76 */   ArrayList<Plugin> upperLeftOverlays = new ArrayList<>();
/*       */   
/*       */   public static boolean initialized = false;
/*       */   
/*       */   public static void saveConfig(boolean force) {
/*    81 */     if (!force && !initialized) {
/*       */       return;
/*       */     }
/*       */     
/*    85 */     oE.cmz.mkdirs();
/*       */     
/*    87 */     properties.put("tile-indicators", TileIndicatorsPlugin.save());
/*    88 */     properties.put("obj-indicators", ObjectIndicatorsPlugin.save());
/*    89 */     properties.put("npc-indicators", NpcIndicatorsPlugin.save());
/*    90 */     properties.put("inventory-tags", InventoryTagsPlugin.save());
/*       */     
/*    92 */     try { OutputStream output = new FileOutputStream(PLUGINS_CONFIG_FILE); 
/*    93 */       try { properties.store(output, (String)null);
/*    94 */         output.close(); return; } catch (Throwable throwable) { try { output.close(); } catch (Throwable throwable1) { throwable.addSuppressed(throwable1); }  throw throwable; }  }
/*    95 */     catch (Throwable throwable) { null.printStackTrace();
/*       */       return; }
/*       */   
/*       */   }
/*       */   public static void loadConfig() {
/*   100 */     if (!PLUGINS_CONFIG_FILE.exists()) {
/*   101 */       saveConfig(true);
/*       */     }
/*       */     
/*   104 */     try { InputStream input = new FileInputStream(PLUGINS_CONFIG_FILE); 
/*   105 */       try { properties.load(input);
/*   106 */         TileIndicatorsPlugin.load(properties.getProperty("tile-indicators"));
/*   107 */         ObjectIndicatorsPlugin.load(properties.getProperty("obj-indicators"));
/*   108 */         NpcIndicatorsPlugin.load(properties.getProperty("npc-indicators"));
/*   109 */         InventoryTagsPlugin.load(properties.getProperty("inventory-tags"));
/*       */         
/*       */         String val;
/*       */         
/*   113 */         WorldSwitcherPanel.updateSelectedWorld(((val = getSingleton().getConfiguration("WorldSelector", "worldId")) == null) ? 1 : Integer.parseInt(val));
/*   114 */         input.close(); } catch (Throwable throwable) { try { input.close(); } catch (Throwable worldId) { Throwable throwable1; throwable.addSuppressed(throwable1); }  throw throwable; }  }
/*   115 */     catch (IOException iOException) { null.printStackTrace(); }
/*       */     
/*   117 */     initialized = true;
/*       */   }
/*       */ 
/*       */ 
/*       */ 
/*       */ 
/*       */ 
/*       */   
/*       */   public static boolean isUsingOsrsHitmarkers() {
/*   126 */     return !RshdHitMarksPlugin.active;
/*       */   }
/*       */   
/*       */   public static void entityDrawHook(mi entity, int screenX, int screenY) {
/*   130 */     if (singleton == null || singleton.getPlugins() == null) {
/*       */       return;
/*       */     }
/*   133 */     for (Plugin plugin : getSingleton().getPlugins()) {
/*   134 */       if (singleton.isPluginEnabled(plugin)) {
/*       */         
/*   136 */         plugin.drawAfterEntities();
/*   137 */         plugin.drawEntityOverlay(entity, screenX, screenY);
/*       */       } 
/*       */     } 
/*       */   }
/*       */   public static void resetItemsDrawnAtTile() {
/*   142 */     GroundItemsPlugin.resetItemsAtTile();
/*   143 */     NpcIndicatorsPlugin.reset();
/*       */   }
/*       */   
/*   146 */   public static HashMap<String, Boolean> pluginEnabled = new HashMap<>();
/*       */   
/*       */   public static boolean isEnabled(Class<? extends Plugin> clazz) {
/*       */     Boolean enabled;
/*   150 */     if ((enabled = pluginEnabled.get(clazz.getName())) != null)
/*   151 */       return enabled.booleanValue(); 
/*       */     Plugin p;
/*   153 */     if ((p = getPlugin(clazz.getName())) != null)
/*   154 */       return p.getDefaultValue(); 
/*   155 */     return false;
/*       */   }
/*       */   
/*       */   public static Plugin getPlugin(String s) {
/*   159 */     for (Iterator<Plugin> iterator = getSingleton().getPlugins().iterator(); iterator.hasNext();) {
/*   160 */       if ((plugin = iterator.next()).getClass().getSimpleName().equalsIgnoreCase(s))
/*   161 */         return plugin; 
/*       */     } 
/*   163 */     return null;
/*       */   }
/*       */   
/*       */   public static Plugin getPlugin(Class<?> clazz) {
/*   167 */     for (Iterator<Plugin> iterator = getSingleton().getPlugins().iterator(); iterator.hasNext();) {
/*   168 */       if ((plugin = iterator.next()).getClass() == clazz)
/*   169 */         return plugin; 
/*       */     } 
/*   171 */     return null;
/*       */   }
/*       */   
/*   174 */   private static final PluginManager singleton = new PluginManager(true, false); private static boolean initConfig;
/*       */   
/*       */   public static PluginManager getSingleton() {
/*   177 */     return singleton;
/*       */   }
/*       */ 
/*       */ 
/*       */   
/*       */   public static void handleLoginEvents() {
/*   183 */     SwingUtilities.invokeLater(() -> {
/*       */           if (!initConfig) {
/*       */             if (lO.tS() == 2) {
/*       */               PluginListPanel.configListPanel.rebuildPluginList();
/*       */               AdminPanel.createPlugin(Loader.clientUI);
/*       */             } 
/*       */             initConfig = true;
/*       */           } 
/*       */         });
/*       */   }
/*       */   
/*   194 */   private final ConfigInvocationHandler handler = new ConfigInvocationHandler(); private static final int OVERLAY_PADDING = 4; boolean isOutdated;
/*       */   
/*       */   public static void onInteractingEntityChange(mi entity) {
/*   197 */     mi newInteractingEntity = getEntity(entity);
/*       */     
/*   199 */     for (Iterator<Plugin> iterator = getSingleton().getPlugins().iterator(); iterator.hasNext();) ((Plugin)iterator.next())
/*   200 */         .onInteractingEntityChange(entity, newInteractingEntity);
/*       */   
/*       */   }
/*       */   
/*       */   public static mi getEntity(mi entity) {
/*   205 */     if (entity.btq * 1433412323 != -1) {
/*   206 */       oj oj; mi interactingEntity = null;
/*   207 */       if (entity.btq * 1433412323 < 32768) {
/*       */         nZ class298_sub29;
/*   209 */         if ((class298_sub29 = (nZ)lO.bkM.H((1433412323 * entity.btq))) != null)
/*   210 */           interactingEntity = (mi)class298_sub29.value; 
/*   211 */       } else if (entity.btq * 1433412323 >= 32768) {
/*   212 */         oj = lO.bmG[1433412323 * entity.btq - 32768];
/*   213 */       }  return (mi)oj;
/*       */     } 
/*   215 */     return null;
/*       */   }
/*       */ 
/*       */ 
/*       */   
/*       */   public static void drawAfterInterfaces() {}
/*       */ 
/*       */ 
/*       */   
/*       */   private static int countPMs() {
/*   225 */     int count = 0;
/*   226 */     for (int i = 1; i < 6; i++) {
/*       */       mP def;
/*   228 */       if ((def = jR.ei(0x2F20000 | i)) != null && def.text != null && !def.text.isEmpty()) {
/*   229 */         count++;
/*       */       }
/*       */     } 
/*   232 */     return count;
/*       */   }
/*       */ 
/*       */ 
/*       */ 
/*       */ 
/*       */   
/*       */   public static Point getSouthOverlayDrawPoint() {
/*       */     Point southPoint;
/*   241 */     if ((southPoint = getChatboxNorthBorder()) != null) {
/*   242 */       boolean fixed = (aT.ic() < 2);
/*   243 */       int x = southPoint.x;
/*   244 */       int y = southPoint.y - 40 - countPMs() * 14 + (!fixed ? -22 : 0);
/*   245 */       if (fixed) {
/*       */         mP pmFixedComponent;
/*       */         
/*   248 */         if ((pmFixedComponent = jR.ei(35913753)) != null) {
/*   249 */           y -= pmFixedComponent.getY();
/*       */         }
/*       */       } else {
/*       */         
/*   253 */         y = (int)southPoint.getY() - 8 - ((BroadcastPlugin.currentBroadcast == null) ? 0 : (BroadcastPlugin.currentBroadcast.length * 14)) - 40 - countPMs() * 14;
/*       */       } 
/*   255 */       return new Point(x, y);
/*       */     } 
/*   257 */     return null;
/*       */   }
/*       */ 
/*       */ 
/*       */   
/*       */   public static Point getChatboxNorthBorder() {
/*       */     mO chatInterface;
/*       */     mP[] widgets;
/*   265 */     if ((chatInterface = mA.bxh[752]) != null && (
/*       */       
/*   267 */       widgets = chatInterface.vH()) != null) {
/*   268 */       int x = -2093041337 * (widgets[0]).bAN;
/*   269 */       int y = (int)((-1111710645 * eV.afy) / ((aT.ic() < 2) ? 1.0D : oE.BG()) - ((widgets[0]).bAS * 457937409) - 20.0D);
/*   270 */       return new Point(x, y);
/*       */     } 
/*       */ 
/*       */     
/*   274 */     return null;
/*       */   }
/*       */ 
/*       */ 
/*       */ 
/*       */ 
/*       */   
/*       */   public static boolean buildContextMenuActions(int mouseX, int mouseY) {
/*   282 */     for (Iterator<Plugin> iterator = getSingleton().getPlugins().iterator(); iterator.hasNext();) {
/*   283 */       if (!((Plugin)iterator.next()).buildContextMenuActions(mouseX, mouseY)) {
/*   284 */         return false;
/*       */       }
/*       */     } 
/*   287 */     return true;
/*       */   }
/*       */ 
/*       */ 
/*       */ 
/*       */ 
/*       */   
/*       */   public static boolean buildEntityContextMenuActions(mi entity, boolean top) {
/*   295 */     for (Iterator<Plugin> iterator = getSingleton().getPlugins().iterator(); iterator.hasNext();) {
/*   296 */       if (!((Plugin)iterator.next()).buildEntityContextMenuActions(entity, top)) {
/*   297 */         return false;
/*       */       }
/*       */     } 
/*   300 */     return true;
/*       */   }
/*       */   
/*       */   public static void onRendererDispose() {
/*   304 */     OpponentInfoPlugin.reset();
/*   305 */     InfoBoxManagerPlugin.reset();
/*   306 */     FishingPlugin.reset();
/*       */   }
/*       */   
/*       */   public static void handleLogoutEvents() {
/*   310 */     TileIndicatorsPlugin.dynamicTileIndicators.clear();
/*       */   }
/*       */   
/*       */   public static void updatePluginEnabled(Plugin plugin) {
/*   314 */     pluginEnabled.put(plugin.getClass().getName(), Boolean.valueOf(plugin.isEnabled()));
/*       */   }
/*       */   
/*       */   public static boolean keyPressed(KeyEvent evt) {
/*   318 */     for (Iterator<Plugin> iterator = getSingleton().getPlugins().iterator(); iterator.hasNext();) {
/*   319 */       if (isEnabled((Class)(plugin = iterator.next()).getClass()))
/*       */       {
/*       */         
/*   322 */         if (plugin.keyPressed(evt))
/*   323 */           return true;  } 
/*       */     } 
/*   325 */     return false;
/*       */   }
/*       */   public static boolean keyReleased(KeyEvent evt) {
/*   328 */     for (Iterator<Plugin> iterator = getSingleton().getPlugins().iterator(); iterator.hasNext();) {
/*   329 */       if (isEnabled((Class)(plugin = iterator.next()).getClass()))
/*       */       {
/*   331 */         if (plugin.keyReleased(evt))
/*   332 */           return true;  } 
/*       */     } 
/*   334 */     return false;
/*       */   }
/*       */   
/*       */   public static void onMapLoad() {
/*   338 */     for (Iterator<Plugin> iterator = getSingleton().getPlugins().iterator(); iterator.hasNext();) {
/*   339 */       if (isEnabled((Class)(plugin = iterator.next()).getClass()))
/*       */       {
/*   341 */         plugin.onMapLoad(); } 
/*       */     } 
/*       */   }
/*       */   
/*       */   public static void preGameRenderHook() {
/*   346 */     for (Iterator<Plugin> iterator = getSingleton().getPlugins().iterator(); iterator.hasNext();) {
/*   347 */       if (isEnabled((Class)(plugin = iterator.next()).getClass()))
/*       */       {
/*   349 */         plugin.preGameRenderHook(); } 
/*       */     } 
/*       */   }
/*       */   
/*       */   public static void itemContainerUpdate(long key, nf container) {
/*   354 */     for (Iterator<Plugin> iterator = getSingleton().getPlugins().iterator(); iterator.hasNext();) {
/*   355 */       if (isEnabled((Class)(plugin = iterator.next()).getClass()))
/*       */       {
/*   357 */         plugin.onItemContainerUpdate(key, container); } 
/*       */     } 
/*       */   }
/*       */   
/*       */   public void registerUpperLeftOverlay(Plugin plugin) {
/*   362 */     this.upperLeftOverlays.add(plugin);
/*   363 */     this.upperLeftOverlays.sort(Comparator.comparingInt(Plugin::getRenderPriority));
/*       */   }
/*       */   
/*       */   public ArrayList<Plugin> getUpperLeftOverlays() {
/*   367 */     return this.upperLeftOverlays;
/*       */   }
/*       */ 
/*       */ 
/*       */ 
/*       */ 
/*       */ 
/*       */   
/*       */   public static void drawOverlayUnderInterfaces() {
/*   376 */     int offsetY = 24;
/*       */ 
/*       */     
/*   379 */     if (R.aY(3322)) {
/*   380 */       offsetY += 105;
/*       */     }
/*   382 */     else if (R.aY(3317)) {
/*   383 */       offsetY += 178;
/*       */     } 
/*   385 */     boolean hasCentralInterface = R.dy();
/*       */ 
/*       */     
/*   388 */     for (Plugin plugin : getSingleton().getUpperLeftOverlays()) {
/*   389 */       if (!hasCentralInterface || plugin.drawsWhileCentralInterfaceOpen())
/*       */       {
/*       */ 
/*       */         
/*   393 */         if (singleton.isPluginEnabled(plugin)) {
/*       */           int overlayHeight;
/*       */ 
/*       */ 
/*       */ 
/*       */ 
/*       */           
/*   400 */           if ((overlayHeight = plugin.draw(6, offsetY)) > 0)
/*   401 */             offsetY += overlayHeight + 4; 
/*       */         } 
/*       */       }
/*       */     } 
/*   405 */     for (Plugin plugin : getSingleton().getPlugins()) {
/*   406 */       if (singleton.isPluginEnabled(plugin))
/*       */       {
/*   408 */         if (!hasCentralInterface || plugin.drawsWhileCentralInterfaceOpen()) {
/*   409 */           plugin.drawOverlayUnderInterfaces();
/*   410 */           plugin.drawAfterInterfaces();
/*       */         }  } 
/*       */     } 
/*       */   }
/*       */   
/*       */   public static void drawOverlayAlwaysOnTop() {
/*   416 */     boolean hasCentralInterface = R.dy();
/*       */     
/*   418 */     for (Iterator<Plugin> iterator = getSingleton().getUpperLeftOverlays().iterator(); iterator.hasNext();) {
/*   419 */       if (isEnabled((Class)(plugin = iterator.next()).getClass()))
/*       */       {
/*       */         
/*   422 */         if (!hasCentralInterface || plugin.drawsWhileCentralInterfaceOpen())
/*       */         {
/*       */           
/*   425 */           plugin.drawOverlayAlwaysOnTop(); } 
/*       */       }
/*       */     } 
/*   428 */     if (Tooltips.tooltip != null) {
/*   429 */       Tooltips.drawTooltip();
/*   430 */       Tooltips.reset();
/*       */     } 
/*       */   }
/*       */ 
/*       */   
/*       */   public <T extends Config> T getConfig(Class<T> clazz) {
/*   436 */     if (clazz == null)
/*   437 */       return null; 
/*   438 */     if (!Modifier.isPublic(clazz.getModifiers()))
/*       */     {
/*   440 */       throw new RuntimeException("Non-public configuration classes can't have default methods invoked");
/*       */     }
/*       */     
/*   443 */     return (T)Proxy.newProxyInstance(clazz.getClassLoader(), new Class[] { clazz }, (InvocationHandler)this.handler);
/*       */   }
/*       */ 
/*       */ 
/*       */ 
/*       */ 
/*       */ 
/*       */ 
/*       */   
/*       */   public ConfigDescriptor getConfigDescriptor(Config configurationProxy) {
/*   453 */     if (configurationProxy == null) {
/*   454 */       return null;
/*       */     }
/*       */     Class<?> inter;
/*       */     ConfigGroup group;
/*   458 */     if ((group = (inter = configurationProxy.getClass().getInterfaces()[0]).<Annotation>getAnnotation(ConfigGroup.class)) == null)
/*       */     {
/*   460 */       throw new IllegalArgumentException("Not a config group");
/*       */     }
/*       */ 
/*       */ 
/*       */ 
/*       */ 
/*       */ 
/*       */ 
/*       */ 
/*       */ 
/*       */ 
/*       */ 
/*       */ 
/*       */ 
/*       */ 
/*       */ 
/*       */ 
/*       */ 
/*       */ 
/*       */ 
/*       */ 
/*       */ 
/*       */ 
/*       */ 
/*       */     
/*   485 */     List<ConfigSectionDescriptor> sections = (List<ConfigSectionDescriptor>)Arrays.<Field>stream(inter.getDeclaredFields()).filter(m -> (m.isAnnotationPresent((Class)ConfigSection.class) && m.getType() == String.class)).map(m -> { try { return new ConfigSectionDescriptor(String.valueOf(m.get(inter)), m.<ConfigSection>getDeclaredAnnotation(ConfigSection.class)); } catch (IllegalAccessException illegalAccessException) { System.out.println("Unable to load section " + inter.getSimpleName() + "::" + m.getName()); return null; }  }).filter(Objects::nonNull).sorted((a, configSectionDescriptor1) -> h.cn().B(a.getSection().position(), configSectionDescriptor1.getSection().position()).a(a.getSection().name(), configSectionDescriptor1.getSection().name()).co()).collect(Collectors.toList());
/*       */ 
/*       */ 
/*       */ 
/*       */ 
/*       */ 
/*       */ 
/*       */ 
/*       */ 
/*       */ 
/*       */ 
/*       */ 
/*       */ 
/*       */ 
/*       */     
/*   500 */     List<ConfigItemDescriptor> items = (List<ConfigItemDescriptor>)Arrays.<Method>stream(inter.getMethods()).filter(m -> (m.getParameterCount() == 0 && m.isAnnotationPresent((Class)ConfigItem.class))).map(m -> new ConfigItemDescriptor(m.<ConfigItem>getDeclaredAnnotation(ConfigItem.class), m.getGenericReturnType(), m.<Range>getDeclaredAnnotation(Range.class), m.<Alpha>getDeclaredAnnotation(Alpha.class), m.<Units>getDeclaredAnnotation(Units.class))).sorted((a, configItemDescriptor1) -> h.cn().B(a.getItem().position(), configItemDescriptor1.getItem().position()).a(a.getItem().name(), configItemDescriptor1.getItem().name()).co()).collect(Collectors.toList());
/*       */     
/*   502 */     return new ConfigDescriptor(group, sections, items);
/*       */   }
/*       */ 
/*       */ 
/*       */   
/*       */   public static boolean interceptContextMenuClick(lZ contextMenuOption, int clickX, int clickY, int dstX, int dstY, int optionIndex, int interactionTypeIndex, long interactionHash) {
/*   508 */     int interfaceHash, interfaceId = (interfaceHash = 1262526353 * hw.aww) >> 16;
/*   509 */     int componentId = interfaceHash - (interfaceId << 16);
/*       */ 
/*       */ 
/*       */ 
/*       */ 
/*       */ 
/*       */ 
/*       */ 
/*       */ 
/*       */ 
/*       */ 
/*       */ 
/*       */     
/*   522 */     if (contextMenuOption == null)
/*   523 */       return false; 
/*   524 */     if (contextMenuOption.brH == null)
/*   525 */       contextMenuOption.brH = ""; 
/*   526 */     if (contextMenuOption.brR == null)
/*   527 */       contextMenuOption.brR = ""; 
/*   528 */     for (Iterator<Plugin> iterator = singleton.getPlugins().iterator(); iterator.hasNext();) {
/*   529 */       if ((plugin = iterator.next()).isEnabled() && plugin.interceptButtonClick(contextMenuOption, clickX, clickY, dstX, dstY, optionIndex, interactionTypeIndex, interactionHash, interfaceId, componentId)) {
/*   530 */         return true;
/*       */       }
/*       */     } 
/*   533 */     return false;
/*       */   }
/*       */   
/*       */   public static void drawSceneOverlay(int screenX, int screenY) {
/*   537 */     for (Plugin plugin : getSingleton().getPlugins()) {
/*   538 */       if (singleton.isPluginEnabled(plugin))
/*       */       {
/*   540 */         plugin.drawSceneOverlay(screenX, screenY); } 
/*       */     } 
/*       */   }
/*       */   
/*       */   public void setEnabled(String className, boolean enabled) {
/*       */     Plugin plugin;
/*   546 */     if ((plugin = getPlugin(className)) == null) {
/*   547 */       System.out.println("Could not find a plugin with class name \"" + className + "\""); return;
/*       */     } 
/*   549 */     setEnabled(plugin, enabled);
/*       */   }
/*       */ 
/*       */   
/*       */   public static void setEnabled(Class clazz, boolean enabled) {
/*   554 */     System.out.println("Setting " + clazz.getSimpleName() + " " + enabled);
/*       */     
/*   556 */     setEnabled(getPlugin(clazz), enabled);
/*       */   }
/*       */   
/*       */   public static void setEnabled(Plugin plugin, boolean enabled) {
/*   560 */     boolean oldValue = getSingleton().isPluginEnabled(plugin);
/*   561 */     plugin.setEnabled(enabled);
/*       */     
/*       */     ConfigChanged configChanged;
/*   564 */     (configChanged = new ConfigChanged()).setGroup(plugin.getClass().getSimpleName());
/*   565 */     configChanged.setProfile("none");
/*   566 */     configChanged.setKey("plugin");
/*   567 */     configChanged.setOldValue(String.valueOf(oldValue));
/*   568 */     configChanged.setNewValue(String.valueOf(enabled));
/*   569 */     configChangedEvent(configChanged);
/*       */   }
/*       */ 
/*       */   
/*       */   public void setOutdated(boolean outdated) {
/*   574 */     this.isOutdated = outdated;
/*       */   }
/*       */ 
/*       */ 
/*       */ 
/*       */ 
/*       */ 
/*       */ 
/*       */   
/*       */   public PluginManager(boolean developerMode, boolean safeMode) {
/*   584 */     this.developerMode = developerMode;
/*   585 */     this.safeMode = safeMode;
/*   586 */     onStartup();
/*       */   }
/*       */   
/*       */   private void onStartup() {
/*   590 */     (new Thread(ItemPrices::loadItemPrices)).start();
/*       */   }
/*       */ 
/*       */   
/*       */   public void refreshPlugins() {
/*   595 */     SwingUtilities.invokeLater(() -> {
/*       */           for (Plugin plugin : getPlugins()) {
/*       */             try {
/*       */               if (isPluginEnabled(plugin) != this.activePlugins.contains(plugin)) {
/*       */                 if (this.activePlugins.contains(plugin)) {
/*       */                   stopPlugin(plugin);
/*       */ 
/*       */ 
/*       */ 
/*       */                   
/*       */                   continue;
/*       */                 } 
/*       */ 
/*       */ 
/*       */ 
/*       */                 
/*       */                 startPlugin(plugin);
/*       */               } 
/*   613 */             } catch (Exception e) {
/*       */               System.out.printf("Error during starting/stopping plugin {}", new Object[] { plugin.getClass().getSimpleName(), e });
/*       */             } 
/*       */           } 
/*       */         });
/*       */   }
/*       */ 
/*       */ 
/*       */ 
/*       */ 
/*       */ 
/*       */   
/*       */   public void startPlugins() {
/*   626 */     for (Iterator<?> iterator = (new ArrayList(this.plugins)).iterator(); iterator.hasNext(); ) { Plugin plugin = (Plugin)iterator.next();
/*       */ 
/*       */       
/*       */       try {
/*   630 */         SwingUtilities.invokeAndWait(() -> {
/*       */               try {
/*       */                 startPlugin(plugin);
/*       */ 
/*       */                 
/*       */                 return;
/*   636 */               } catch (Exception ex) {
/*       */                 System.out.printf("Unable to start plugin {}", new Object[] { plugin.getClass().getSimpleName(), ex });
/*       */                 
/*       */                 this.plugins.remove(plugin);
/*       */                 return;
/*       */               } 
/*       */             });
/*   643 */       } catch (InterruptedException|java.lang.reflect.InvocationTargetException e) {
/*       */         
/*   645 */         throw new RuntimeException(e);
/*       */       }  }
/*       */   
/*       */   }
/*       */ 
/*       */ 
/*       */   
/*       */   private static boolean corePluginsLoaded = false;
/*       */ 
/*       */   
/*       */   public void loadCorePlugins() throws IOException, Exception {
/*   656 */     if (corePluginsLoaded)
/*       */       return; 
/*   658 */     corePluginsLoaded = true;
/*       */ 
/*       */ 
/*       */ 
/*       */     
/*   663 */     List<Class<?>> plugins = (List<Class<?>>)a.a(getClass().getClassLoader()).l("utils.plugins.impl").stream().map(a.a::eb).collect(Collectors.toList());
/*       */     
/*   665 */     loadPlugins(plugins, null);
/*       */   }
/*       */   
/*   668 */   private static final ArrayList<Plugin> hiddenPlugins = new ArrayList<>();
/*       */ 
/*       */ 
/*       */ 
/*       */ 
/*       */ 
/*       */ 
/*       */ 
/*       */ 
/*       */ 
/*       */ 
/*       */ 
/*       */ 
/*       */ 
/*       */ 
/*       */ 
/*       */ 
/*       */ 
/*       */ 
/*       */ 
/*       */ 
/*       */ 
/*       */ 
/*       */ 
/*       */ 
/*       */ 
/*       */ 
/*       */ 
/*       */ 
/*       */ 
/*       */ 
/*       */ 
/*       */ 
/*       */ 
/*       */ 
/*       */ 
/*       */ 
/*       */ 
/*       */ 
/*       */ 
/*       */ 
/*       */ 
/*       */ 
/*       */ 
/*       */ 
/*       */ 
/*       */ 
/*       */ 
/*       */ 
/*       */ 
/*       */ 
/*       */ 
/*       */ 
/*       */ 
/*       */ 
/*       */ 
/*       */ 
/*       */ 
/*       */ 
/*       */ 
/*       */ 
/*       */ 
/*       */ 
/*       */ 
/*       */ 
/*       */ 
/*       */ 
/*       */ 
/*       */ 
/*       */ 
/*       */ 
/*       */ 
/*       */ 
/*       */ 
/*       */ 
/*       */ 
/*       */ 
/*       */ 
/*       */ 
/*       */ 
/*       */ 
/*       */ 
/*       */ 
/*       */ 
/*       */ 
/*       */ 
/*       */ 
/*       */ 
/*       */ 
/*       */ 
/*       */ 
/*       */ 
/*       */ 
/*       */ 
/*       */ 
/*       */ 
/*       */ 
/*       */   
/*       */   public boolean startPlugin(Plugin plugin) throws Exception {
/*   767 */     assert SwingUtilities.isEventDispatchThread();
/*       */     
/*   769 */     if (this.activePlugins.contains(plugin) || !isPluginEnabled(plugin))
/*       */     {
/*   771 */       return false;
/*       */     }
/*       */     
/*   774 */     this.activePlugins.add(plugin);
/*       */ 
/*       */     
/*       */     try {
/*   778 */       plugin.startUp();
/*       */ 
/*       */     
/*       */     }
/*   782 */     catch (ThreadDeath threadDeath) {
/*       */       throw null;
/*   784 */     } catch (Throwable ex) {
/*       */       ThreadDeath e;
/*   786 */       throw new Exception(e);
/*       */     } 
/*       */     
/*   789 */     return true;
/*       */   }
/*       */ 
/*       */ 
/*       */   
/*       */   public boolean stopPlugin(Plugin plugin) throws Exception {
/*   795 */     assert SwingUtilities.isEventDispatchThread();
/*       */     
/*   797 */     if (!this.activePlugins.remove(plugin))
/*       */     {
/*   799 */       return false;
/*       */     }
/*       */ 
/*       */     
/*       */     try {
/*   804 */       plugin.shutDown();
/*       */       
/*   806 */       System.out.printf("Plugin {} is now stopped", new Object[] { plugin.getClass().getSimpleName() });
/*       */     }
/*   808 */     catch (Exception ex) {
/*       */       
/*   810 */       throw new Exception(ex);
/*       */     } 
/*       */     
/*   813 */     return true;
/*       */   }
/*       */ 
/*       */ 
/*       */ 
/*       */   
/*       */   public void setPluginEnabled(Plugin plugin, boolean enabled) {
/*   820 */     plugin.setEnabled(enabled);
/*       */   }
/*       */ 
/*       */   
/*       */   public boolean isPluginEnabled(Plugin plugin) {
/*   825 */     return ((Boolean)pluginEnabled.getOrDefault(plugin.getClass().getName(), Boolean.FALSE)).booleanValue();
/*       */   }
/*       */   
/*       */   private Plugin instantiate(List<Plugin> scannedPlugins, Class<Plugin> clazz) throws Exception {
/*       */     Plugin plugin;
/*   830 */     PluginDependency[] pluginDependencies = clazz.<PluginDependency>getAnnotationsByType(PluginDependency.class);
/*   831 */     List<Plugin> deps = new ArrayList<>(); PluginDependency[] arrayOfPluginDependency1; int i; byte b1;
/*   832 */     for (i = (arrayOfPluginDependency1 = pluginDependencies).length, b1 = 0; b1 < i; ) { PluginDependency pluginDependency = arrayOfPluginDependency1[b1];
/*       */       
/*       */       Optional<Plugin> dependency;
/*   835 */       if (!(dependency = scannedPlugins.stream().filter(p -> (p.getClass() == pluginDependency.value())).findFirst()).isPresent())
/*       */       {
/*   837 */         throw new Exception("Unmet dependency for " + clazz.getSimpleName() + ": " + pluginDependency.value().getSimpleName());
/*       */       }
/*   839 */       deps.add(dependency.get());
/*       */       
/*       */       b1++; }
/*       */ 
/*       */     
/*       */     try {
/*   845 */       plugin = clazz.getDeclaredConstructor(new Class[0]).newInstance(new Object[0]);
/*       */ 
/*       */     
/*       */     }
/*   849 */     catch (ThreadDeath threadDeath) {
/*       */       throw null;
/*   851 */     } catch (Throwable ex) {
/*       */       ThreadDeath e;
/*   853 */       throw new Exception(e);
/*       */     } 
/*       */ 
/*       */     
/*   857 */     return plugin;
/*       */   }
/*       */ 
/*       */   
/*       */   public void add(Plugin plugin) {
/*   862 */     this.plugins.add(plugin);
/*       */   }
/*       */ 
/*       */   
/*       */   public void remove(Plugin plugin) {
/*   867 */     this.plugins.remove(plugin);
/*       */   }
/*       */ 
/*       */   
/*       */   public Collection<Plugin> getPlugins() {
/*   872 */     return this.plugins;
/*       */   }
/*       */ 
/*       */ 
/*       */ 
/*       */ 
/*       */ 
/*       */ 
/*       */ 
/*       */ 
/*       */ 
/*       */ 
/*       */ 
/*       */ 
/*       */ 
/*       */ 
/*       */ 
/*       */ 
/*       */ 
/*       */ 
/*       */ 
/*       */ 
/*       */ 
/*       */ 
/*       */ 
/*       */ 
/*       */ 
/*       */ 
/*       */ 
/*       */ 
/*       */ 
/*       */ 
/*       */ 
/*       */ 
/*       */ 
/*       */ 
/*       */ 
/*       */ 
/*       */ 
/*       */ 
/*       */ 
/*       */ 
/*       */ 
/*       */ 
/*       */ 
/*       */ 
/*       */ 
/*       */ 
/*       */ 
/*       */ 
/*       */ 
/*       */ 
/*       */ 
/*       */ 
/*       */ 
/*       */ 
/*       */ 
/*       */ 
/*       */ 
/*       */ 
/*       */ 
/*       */ 
/*       */ 
/*       */ 
/*       */ 
/*       */ 
/*       */ 
/*       */ 
/*       */ 
/*       */ 
/*       */ 
/*       */ 
/*       */ 
/*       */ 
/*       */ 
/*       */ 
/*       */ 
/*       */ 
/*       */ 
/*       */ 
/*       */ 
/*       */ 
/*       */ 
/*       */ 
/*       */ 
/*       */ 
/*       */ 
/*       */ 
/*       */ 
/*       */ 
/*       */ 
/*       */ 
/*       */ 
/*       */ 
/*       */ 
/*       */ 
/*       */ 
/*       */ 
/*       */ 
/*       */ 
/*       */ 
/*       */ 
/*       */ 
/*       */ 
/*       */ 
/*       */ 
/*       */ 
/*       */ 
/*       */ 
/*       */ 
/*       */ 
/*       */ 
/*       */ 
/*       */ 
/*       */ 
/*       */ 
/*       */ 
/*       */ 
/*       */ 
/*       */ 
/*       */ 
/*       */ 
/*       */ 
/*       */ 
/*       */ 
/*       */ 
/*       */ 
/*       */ 
/*       */ 
/*       */ 
/*       */ 
/*       */ 
/*       */ 
/*       */ 
/*       */ 
/*       */ 
/*       */ 
/*       */ 
/*       */ 
/*       */ 
/*       */ 
/*       */ 
/*       */ 
/*       */ 
/*       */ 
/*       */ 
/*       */ 
/*       */ 
/*       */ 
/*       */ 
/*       */ 
/*       */ 
/*       */ 
/*       */ 
/*       */ 
/*       */ 
/*       */ 
/*       */ 
/*       */ 
/*       */ 
/*       */ 
/*       */ 
/*       */ 
/*       */ 
/*       */ 
/*       */ 
/*       */ 
/*       */ 
/*       */ 
/*       */ 
/*       */ 
/*       */ 
/*       */ 
/*       */ 
/*       */ 
/*       */ 
/*       */ 
/*       */ 
/*       */ 
/*       */ 
/*       */ 
/*       */ 
/*       */ 
/*       */ 
/*       */ 
/*       */ 
/*       */ 
/*       */ 
/*       */ 
/*       */ 
/*       */ 
/*       */ 
/*       */ 
/*       */ 
/*       */ 
/*       */ 
/*       */ 
/*       */ 
/*       */ 
/*       */ 
/*       */ 
/*       */ 
/*       */ 
/*       */ 
/*       */ 
/*       */ 
/*       */ 
/*       */ 
/*       */ 
/*       */ 
/*       */ 
/*       */ 
/*       */ 
/*       */ 
/*       */ 
/*       */ 
/*       */ 
/*       */ 
/*       */ 
/*       */ 
/*       */ 
/*       */ 
/*       */ 
/*       */ 
/*       */ 
/*       */ 
/*       */ 
/*       */ 
/*       */ 
/*       */ 
/*       */ 
/*       */ 
/*       */ 
/*       */ 
/*       */ 
/*       */ 
/*       */ 
/*       */ 
/*       */ 
/*       */ 
/*       */ 
/*       */ 
/*       */ 
/*       */ 
/*       */ 
/*       */ 
/*       */ 
/*       */ 
/*       */ 
/*       */ 
/*       */ 
/*       */ 
/*       */ 
/*       */ 
/*       */ 
/*       */ 
/*       */ 
/*       */ 
/*       */ 
/*       */ 
/*       */ 
/*       */ 
/*       */ 
/*       */ 
/*       */ 
/*       */ 
/*       */ 
/*       */ 
/*       */ 
/*       */ 
/*       */ 
/*       */ 
/*       */ 
/*       */ 
/*       */ 
/*       */ 
/*       */ 
/*       */ 
/*       */ 
/*       */ 
/*       */ 
/*       */ 
/*       */ 
/*       */ 
/*       */ 
/*       */ 
/*       */ 
/*       */ 
/*       */ 
/*       */ 
/*       */ 
/*       */ 
/*       */ 
/*       */ 
/*       */ 
/*       */ 
/*       */ 
/*       */ 
/*       */ 
/*       */ 
/*       */ 
/*       */ 
/*       */ 
/*       */ 
/*       */ 
/*       */ 
/*       */ 
/*       */ 
/*       */ 
/*       */ 
/*       */ 
/*       */ 
/*       */ 
/*       */ 
/*       */ 
/*       */ 
/*       */ 
/*       */ 
/*       */ 
/*       */ 
/*       */ 
/*       */ 
/*       */ 
/*       */ 
/*       */ 
/*       */ 
/*       */ 
/*       */ 
/*       */ 
/*       */ 
/*       */ 
/*       */ 
/*       */ 
/*       */ 
/*       */ 
/*       */ 
/*       */ 
/*       */ 
/*       */ 
/*       */ 
/*       */ 
/*       */ 
/*       */ 
/*       */ 
/*       */ 
/*       */ 
/*       */ 
/*       */ 
/*       */ 
/*       */ 
/*       */ 
/*       */ 
/*       */ 
/*       */ 
/*       */ 
/*       */ 
/*       */ 
/*       */ 
/*       */ 
/*       */ 
/*       */ 
/*       */ 
/*       */ 
/*       */ 
/*       */ 
/*       */ 
/*       */ 
/*       */ 
/*       */ 
/*       */ 
/*       */ 
/*       */ 
/*       */ 
/*       */ 
/*       */ 
/*       */ 
/*       */ 
/*       */ 
/*       */ 
/*       */ 
/*       */ 
/*       */ 
/*       */ 
/*       */ 
/*       */ 
/*       */ 
/*       */ 
/*       */ 
/*       */ 
/*       */ 
/*       */ 
/*       */ 
/*       */ 
/*       */ 
/*       */ 
/*       */ 
/*       */ 
/*       */ 
/*       */ 
/*       */ 
/*       */ 
/*       */ 
/*       */ 
/*       */ 
/*       */ 
/*       */ 
/*       */ 
/*       */ 
/*       */ 
/*       */ 
/*       */ 
/*       */ 
/*       */ 
/*       */ 
/*       */ 
/*       */ 
/*       */ 
/*       */ 
/*       */ 
/*       */ 
/*       */ 
/*       */ 
/*       */ 
/*       */ 
/*       */ 
/*       */ 
/*       */ 
/*       */ 
/*       */ 
/*       */ 
/*       */ 
/*       */ 
/*       */ 
/*       */ 
/*       */ 
/*       */ 
/*       */ 
/*       */ 
/*       */ 
/*       */ 
/*       */ 
/*       */ 
/*       */ 
/*       */ 
/*       */ 
/*       */ 
/*       */ 
/*       */ 
/*       */ 
/*       */ 
/*       */ 
/*       */ 
/*       */ 
/*       */ 
/*       */ 
/*       */ 
/*       */ 
/*       */ 
/*       */ 
/*       */ 
/*       */ 
/*       */ 
/*       */ 
/*       */ 
/*       */ 
/*       */ 
/*       */ 
/*       */ 
/*       */ 
/*       */ 
/*       */ 
/*       */ 
/*       */ 
/*       */ 
/*       */ 
/*       */ 
/*       */ 
/*       */ 
/*       */ 
/*       */ 
/*       */ 
/*       */ 
/*       */ 
/*       */ 
/*       */ 
/*       */ 
/*       */ 
/*       */ 
/*       */ 
/*       */ 
/*       */ 
/*       */ 
/*       */ 
/*       */ 
/*       */ 
/*       */ 
/*       */ 
/*       */ 
/*       */ 
/*       */ 
/*       */ 
/*       */ 
/*       */ 
/*       */ 
/*       */ 
/*       */ 
/*       */ 
/*       */ 
/*       */ 
/*       */ 
/*       */ 
/*       */ 
/*       */ 
/*       */ 
/*       */ 
/*       */ 
/*       */ 
/*       */ 
/*       */ 
/*       */ 
/*       */ 
/*       */ 
/*       */ 
/*       */ 
/*       */ 
/*       */ 
/*       */ 
/*       */ 
/*       */ 
/*       */ 
/*       */ 
/*       */ 
/*       */ 
/*       */ 
/*       */ 
/*       */ 
/*       */ 
/*       */ 
/*       */ 
/*       */ 
/*       */ 
/*       */ 
/*       */ 
/*       */ 
/*       */ 
/*       */ 
/*       */ 
/*       */ 
/*       */ 
/*       */ 
/*       */ 
/*       */ 
/*       */ 
/*       */ 
/*       */ 
/*       */ 
/*       */ 
/*       */ 
/*       */ 
/*       */ 
/*       */ 
/*       */ 
/*       */ 
/*       */ 
/*       */ 
/*       */ 
/*       */ 
/*       */ 
/*       */ 
/*       */ 
/*       */ 
/*       */ 
/*       */ 
/*       */ 
/*       */ 
/*       */ 
/*       */ 
/*       */ 
/*       */ 
/*       */ 
/*       */ 
/*       */ 
/*       */ 
/*       */ 
/*       */ 
/*       */ 
/*       */ 
/*       */ 
/*       */ 
/*       */ 
/*       */ 
/*       */ 
/*       */ 
/*       */ 
/*       */ 
/*       */ 
/*       */ 
/*       */ 
/*       */ 
/*       */ 
/*       */ 
/*       */ 
/*       */ 
/*       */ 
/*       */ 
/*       */ 
/*       */ 
/*       */ 
/*       */ 
/*       */ 
/*       */ 
/*       */ 
/*       */ 
/*       */ 
/*       */ 
/*       */ 
/*       */ 
/*       */ 
/*       */ 
/*       */ 
/*       */ 
/*       */ 
/*       */ 
/*       */ 
/*       */ 
/*       */ 
/*       */ 
/*       */ 
/*       */ 
/*       */ 
/*       */ 
/*       */ 
/*       */ 
/*       */ 
/*       */ 
/*       */ 
/*       */ 
/*       */ 
/*       */ 
/*       */ 
/*       */ 
/*       */ 
/*       */ 
/*       */ 
/*       */ 
/*       */ 
/*       */ 
/*       */ 
/*       */ 
/*       */ 
/*       */ 
/*       */ 
/*       */ 
/*       */ 
/*       */ 
/*       */ 
/*       */ 
/*       */ 
/*       */ 
/*       */ 
/*       */ 
/*       */ 
/*       */ 
/*       */ 
/*       */ 
/*       */ 
/*       */ 
/*       */ 
/*       */ 
/*       */ 
/*       */ 
/*       */ 
/*       */ 
/*       */ 
/*       */ 
/*       */ 
/*       */ 
/*       */ 
/*       */ 
/*       */ 
/*       */ 
/*       */ 
/*       */ 
/*       */ 
/*       */ 
/*       */ 
/*       */ 
/*       */ 
/*       */ 
/*       */ 
/*       */ 
/*       */ 
/*       */ 
/*       */ 
/*       */ 
/*       */ 
/*       */ 
/*       */ 
/*       */ 
/*       */ 
/*       */ 
/*       */ 
/*       */ 
/*       */ 
/*       */ 
/*       */ 
/*       */ 
/*       */ 
/*       */ 
/*       */ 
/*       */ 
/*       */ 
/*       */ 
/*       */ 
/*       */ 
/*       */ 
/*       */ 
/*       */ 
/*       */ 
/*       */ 
/*       */ 
/*       */ 
/*       */ 
/*       */ 
/*       */ 
/*       */ 
/*       */ 
/*       */ 
/*       */ 
/*       */ 
/*       */ 
/*       */ 
/*       */ 
/*       */ 
/*       */ 
/*       */ 
/*       */ 
/*       */ 
/*       */ 
/*       */ 
/*       */ 
/*       */ 
/*       */ 
/*       */ 
/*       */ 
/*       */ 
/*       */ 
/*       */ 
/*       */ 
/*       */ 
/*       */ 
/*       */ 
/*       */ 
/*       */ 
/*       */ 
/*       */ 
/*       */ 
/*       */ 
/*       */ 
/*       */ 
/*       */ 
/*       */ 
/*       */ 
/*       */ 
/*       */ 
/*       */ 
/*       */ 
/*       */ 
/*       */ 
/*       */ 
/*       */ 
/*       */ 
/*       */ 
/*       */ 
/*       */ 
/*       */ 
/*       */ 
/*       */ 
/*       */ 
/*       */ 
/*       */ 
/*       */ 
/*       */ 
/*       */ 
/*       */ 
/*       */ 
/*       */ 
/*       */ 
/*       */ 
/*       */ 
/*       */ 
/*       */ 
/*       */ 
/*       */ 
/*       */ 
/*       */ 
/*       */ 
/*       */ 
/*       */ 
/*       */ 
/*       */ 
/*       */ 
/*       */ 
/*       */ 
/*       */ 
/*       */ 
/*       */ 
/*       */ 
/*       */ 
/*       */ 
/*       */ 
/*       */ 
/*       */ 
/*       */ 
/*       */ 
/*       */ 
/*       */ 
/*       */ 
/*       */ 
/*       */ 
/*       */ 
/*       */ 
/*       */ 
/*       */ 
/*       */ 
/*       */ 
/*       */ 
/*       */ 
/*       */ 
/*       */ 
/*       */ 
/*       */ 
/*       */ 
/*       */ 
/*       */ 
/*       */ 
/*       */ 
/*       */ 
/*       */ 
/*       */ 
/*       */ 
/*       */ 
/*       */ 
/*       */ 
/*       */ 
/*       */ 
/*       */ 
/*       */ 
/*       */ 
/*       */ 
/*       */ 
/*       */ 
/*       */ 
/*       */ 
/*       */ 
/*       */ 
/*       */ 
/*       */ 
/*       */ 
/*       */ 
/*       */ 
/*       */ 
/*       */ 
/*       */ 
/*       */ 
/*       */ 
/*       */ 
/*       */ 
/*       */ 
/*       */ 
/*       */ 
/*       */ 
/*       */ 
/*       */ 
/*       */ 
/*       */ 
/*       */ 
/*       */ 
/*       */ 
/*       */ 
/*       */ 
/*       */ 
/*       */ 
/*       */ 
/*       */ 
/*       */ 
/*       */ 
/*       */ 
/*       */ 
/*       */ 
/*       */ 
/*       */ 
/*       */ 
/*       */ 
/*       */ 
/*       */ 
/*       */ 
/*       */ 
/*       */ 
/*       */ 
/*       */ 
/*       */ 
/*       */ 
/*       */ 
/*       */ 
/*       */ 
/*       */ 
/*       */ 
/*       */ 
/*       */ 
/*       */ 
/*       */ 
/*       */ 
/*       */ 
/*       */ 
/*       */ 
/*       */ 
/*       */ 
/*       */ 
/*       */ 
/*       */ 
/*       */ 
/*       */ 
/*       */ 
/*       */ 
/*       */ 
/*       */ 
/*       */ 
/*       */ 
/*       */ 
/*       */ 
/*       */ 
/*       */ 
/*       */ 
/*       */ 
/*       */ 
/*       */ 
/*       */ 
/*       */ 
/*       */ 
/*       */ 
/*       */ 
/*       */ 
/*       */ 
/*       */ 
/*       */ 
/*       */ 
/*       */ 
/*       */ 
/*       */ 
/*       */ 
/*       */ 
/*       */ 
/*       */ 
/*       */ 
/*       */ 
/*       */ 
/*       */ 
/*       */ 
/*       */ 
/*       */ 
/*       */ 
/*       */ 
/*       */ 
/*       */ 
/*       */ 
/*       */ 
/*       */ 
/*       */ 
/*       */ 
/*       */ 
/*       */ 
/*       */ 
/*       */ 
/*       */ 
/*       */ 
/*       */ 
/*       */ 
/*       */ 
/*       */ 
/*       */ 
/*       */ 
/*       */ 
/*       */ 
/*       */ 
/*       */ 
/*       */ 
/*       */ 
/*       */ 
/*       */ 
/*       */ 
/*       */ 
/*       */ 
/*       */ 
/*       */ 
/*       */ 
/*       */ 
/*       */ 
/*       */ 
/*       */ 
/*       */ 
/*       */ 
/*       */ 
/*       */ 
/*       */ 
/*       */ 
/*       */ 
/*       */ 
/*       */ 
/*       */ 
/*       */ 
/*       */ 
/*       */ 
/*       */ 
/*       */ 
/*       */ 
/*       */ 
/*       */ 
/*       */ 
/*       */ 
/*       */ 
/*       */ 
/*       */ 
/*       */ 
/*       */ 
/*       */ 
/*       */ 
/*       */ 
/*       */ 
/*       */ 
/*       */ 
/*       */ 
/*       */ 
/*       */ 
/*       */ 
/*       */ 
/*       */ 
/*       */ 
/*       */ 
/*       */ 
/*       */ 
/*       */ 
/*       */ 
/*       */ 
/*       */ 
/*       */ 
/*       */ 
/*       */ 
/*       */ 
/*       */ 
/*       */ 
/*       */ 
/*       */ 
/*       */ 
/*       */ 
/*       */ 
/*       */ 
/*       */ 
/*       */ 
/*       */ 
/*       */ 
/*       */ 
/*       */ 
/*       */ 
/*       */ 
/*       */ 
/*       */ 
/*       */ 
/*       */ 
/*       */ 
/*       */ 
/*       */ 
/*       */ 
/*       */ 
/*       */ 
/*       */ 
/*       */ 
/*       */ 
/*       */ 
/*       */ 
/*       */ 
/*       */ 
/*       */ 
/*       */ 
/*       */ 
/*       */ 
/*       */ 
/*       */ 
/*       */ 
/*       */ 
/*       */ 
/*       */ 
/*       */ 
/*       */ 
/*       */ 
/*       */ 
/*       */ 
/*       */ 
/*       */ 
/*       */ 
/*       */ 
/*       */ 
/*       */ 
/*       */ 
/*       */ 
/*       */ 
/*       */ 
/*       */ 
/*       */ 
/*       */ 
/*       */ 
/*       */ 
/*       */ 
/*       */ 
/*       */ 
/*       */ 
/*       */ 
/*       */ 
/*       */ 
/*       */ 
/*       */ 
/*       */ 
/*       */ 
/*       */ 
/*       */ 
/*       */ 
/*       */ 
/*       */ 
/*       */ 
/*       */ 
/*       */ 
/*       */ 
/*       */ 
/*       */ 
/*       */ 
/*       */ 
/*       */ 
/*       */ 
/*       */ 
/*       */ 
/*       */ 
/*       */ 
/*       */ 
/*       */ 
/*       */ 
/*       */ 
/*       */ 
/*       */ 
/*       */ 
/*       */ 
/*       */ 
/*       */ 
/*       */ 
/*       */ 
/*       */ 
/*       */ 
/*       */ 
/*       */ 
/*       */ 
/*       */ 
/*       */ 
/*       */ 
/*       */ 
/*       */ 
/*       */ 
/*       */ 
/*       */ 
/*       */ 
/*       */ 
/*       */ 
/*       */ 
/*       */ 
/*       */ 
/*       */ 
/*       */ 
/*       */ 
/*       */ 
/*       */ 
/*       */ 
/*       */ 
/*       */ 
/*       */ 
/*       */ 
/*       */ 
/*       */ 
/*       */ 
/*       */ 
/*       */ 
/*       */ 
/*       */ 
/*       */ 
/*       */ 
/*       */ 
/*       */ 
/*       */ 
/*       */ 
/*       */ 
/*       */ 
/*       */ 
/*       */ 
/*       */ 
/*       */ 
/*       */ 
/*       */ 
/*       */ 
/*       */ 
/*       */ 
/*       */ 
/*       */ 
/*       */ 
/*       */ 
/*       */ 
/*       */ 
/*       */ 
/*       */ 
/*       */ 
/*       */ 
/*       */ 
/*       */ 
/*       */ 
/*       */ 
/*       */ 
/*       */ 
/*       */ 
/*       */ 
/*       */ 
/*       */ 
/*       */ 
/*       */ 
/*       */ 
/*       */ 
/*       */ 
/*       */ 
/*       */ 
/*       */ 
/*       */ 
/*       */ 
/*       */ 
/*       */ 
/*       */ 
/*       */ 
/*       */ 
/*       */ 
/*       */ 
/*       */ 
/*       */ 
/*       */ 
/*       */ 
/*       */ 
/*       */ 
/*       */ 
/*       */ 
/*       */ 
/*       */ 
/*       */ 
/*       */ 
/*       */ 
/*       */ 
/*       */ 
/*       */ 
/*       */ 
/*       */ 
/*       */ 
/*       */ 
/*       */ 
/*       */ 
/*       */ 
/*       */ 
/*       */ 
/*       */ 
/*       */ 
/*       */ 
/*       */ 
/*       */ 
/*       */ 
/*       */ 
/*       */ 
/*       */ 
/*       */ 
/*       */ 
/*       */ 
/*       */ 
/*       */ 
/*       */ 
/*       */ 
/*       */ 
/*       */ 
/*       */ 
/*       */ 
/*       */ 
/*       */ 
/*       */ 
/*       */ 
/*       */ 
/*       */ 
/*       */ 
/*       */ 
/*       */ 
/*       */ 
/*       */ 
/*       */ 
/*       */ 
/*       */ 
/*       */ 
/*       */ 
/*       */ 
/*       */ 
/*       */ 
/*       */ 
/*       */ 
/*       */ 
/*       */ 
/*       */ 
/*       */ 
/*       */ 
/*       */ 
/*       */ 
/*       */ 
/*       */ 
/*       */ 
/*       */ 
/*       */ 
/*       */ 
/*       */ 
/*       */ 
/*       */ 
/*       */ 
/*       */ 
/*       */ 
/*       */ 
/*       */ 
/*       */ 
/*       */ 
/*       */ 
/*       */ 
/*       */ 
/*       */ 
/*       */ 
/*       */ 
/*       */ 
/*       */ 
/*       */ 
/*       */ 
/*       */ 
/*       */ 
/*       */ 
/*       */ 
/*       */ 
/*       */ 
/*       */ 
/*       */ 
/*       */ 
/*       */ 
/*       */ 
/*       */ 
/*       */ 
/*       */ 
/*       */ 
/*       */ 
/*       */ 
/*       */ 
/*       */ 
/*       */ 
/*       */ 
/*       */ 
/*       */ 
/*       */ 
/*       */ 
/*       */ 
/*       */ 
/*       */ 
/*       */ 
/*       */ 
/*       */ 
/*       */ 
/*       */ 
/*       */ 
/*       */ 
/*       */ 
/*       */ 
/*       */ 
/*       */ 
/*       */ 
/*       */ 
/*       */ 
/*       */ 
/*       */ 
/*       */ 
/*       */ 
/*       */ 
/*       */ 
/*       */ 
/*       */ 
/*       */ 
/*       */ 
/*       */ 
/*       */ 
/*       */ 
/*       */ 
/*       */ 
/*       */ 
/*       */ 
/*       */ 
/*       */ 
/*       */ 
/*       */ 
/*       */ 
/*       */ 
/*       */ 
/*       */ 
/*       */ 
/*       */ 
/*       */ 
/*       */ 
/*       */ 
/*       */ 
/*       */ 
/*       */ 
/*       */ 
/*       */ 
/*       */ 
/*       */ 
/*       */ 
/*       */ 
/*       */ 
/*       */ 
/*       */ 
/*       */ 
/*       */ 
/*       */ 
/*       */ 
/*       */ 
/*       */ 
/*       */ 
/*       */ 
/*       */ 
/*       */ 
/*       */ 
/*       */ 
/*       */ 
/*       */ 
/*       */ 
/*       */ 
/*       */ 
/*       */ 
/*       */ 
/*       */ 
/*       */ 
/*       */ 
/*       */ 
/*       */ 
/*       */ 
/*       */ 
/*       */ 
/*       */ 
/*       */ 
/*       */ 
/*       */ 
/*       */ 
/*       */ 
/*       */ 
/*       */ 
/*       */ 
/*       */ 
/*       */ 
/*       */ 
/*       */ 
/*       */ 
/*       */ 
/*       */ 
/*       */ 
/*       */ 
/*       */ 
/*       */ 
/*       */ 
/*       */ 
/*       */ 
/*       */ 
/*       */ 
/*       */ 
/*       */ 
/*       */ 
/*       */ 
/*       */ 
/*       */ 
/*       */ 
/*       */ 
/*       */ 
/*       */ 
/*       */ 
/*       */ 
/*       */ 
/*       */ 
/*       */ 
/*       */ 
/*       */ 
/*       */ 
/*       */ 
/*       */ 
/*       */ 
/*       */ 
/*       */ 
/*       */ 
/*       */ 
/*       */ 
/*       */ 
/*       */ 
/*       */ 
/*       */ 
/*       */ 
/*       */ 
/*       */ 
/*       */ 
/*       */ 
/*       */ 
/*       */ 
/*       */ 
/*       */ 
/*       */ 
/*       */ 
/*       */ 
/*       */ 
/*       */ 
/*       */ 
/*       */ 
/*       */ 
/*       */ 
/*       */ 
/*       */ 
/*       */ 
/*       */ 
/*       */ 
/*       */ 
/*       */ 
/*       */ 
/*       */ 
/*       */ 
/*       */ 
/*       */ 
/*       */ 
/*       */ 
/*       */ 
/*       */ 
/*       */ 
/*       */ 
/*       */ 
/*       */ 
/*       */ 
/*       */ 
/*       */ 
/*       */ 
/*       */ 
/*       */ 
/*       */ 
/*       */ 
/*       */ 
/*       */ 
/*       */ 
/*       */ 
/*       */ 
/*       */ 
/*       */ 
/*       */ 
/*       */ 
/*       */ 
/*       */ 
/*       */ 
/*       */ 
/*       */ 
/*       */ 
/*       */ 
/*       */ 
/*       */ 
/*       */ 
/*       */ 
/*       */ 
/*       */ 
/*       */ 
/*       */ 
/*       */ 
/*       */ 
/*       */ 
/*       */ 
/*       */ 
/*       */ 
/*       */ 
/*       */ 
/*       */ 
/*       */ 
/*       */ 
/*       */ 
/*       */ 
/*       */ 
/*       */ 
/*       */ 
/*       */ 
/*       */ 
/*       */ 
/*       */ 
/*       */ 
/*       */ 
/*       */ 
/*       */ 
/*       */ 
/*       */ 
/*       */ 
/*       */ 
/*       */ 
/*       */ 
/*       */ 
/*       */ 
/*       */ 
/*       */ 
/*       */ 
/*       */ 
/*       */ 
/*       */ 
/*       */ 
/*       */ 
/*       */ 
/*       */ 
/*       */ 
/*       */ 
/*       */ 
/*       */ 
/*       */ 
/*       */ 
/*       */ 
/*       */ 
/*       */ 
/*       */ 
/*       */ 
/*       */ 
/*       */ 
/*       */ 
/*       */ 
/*       */ 
/*       */ 
/*       */ 
/*       */ 
/*       */ 
/*       */ 
/*       */ 
/*       */ 
/*       */ 
/*       */ 
/*       */ 
/*       */ 
/*       */ 
/*       */ 
/*       */ 
/*       */ 
/*       */ 
/*       */ 
/*       */ 
/*       */ 
/*       */ 
/*       */ 
/*       */ 
/*       */ 
/*       */ 
/*       */ 
/*       */ 
/*       */ 
/*       */ 
/*       */ 
/*       */ 
/*       */ 
/*       */ 
/*       */ 
/*       */ 
/*       */ 
/*       */ 
/*       */ 
/*       */ 
/*       */ 
/*       */ 
/*       */ 
/*       */ 
/*       */ 
/*       */ 
/*       */ 
/*       */ 
/*       */ 
/*       */ 
/*       */ 
/*       */ 
/*       */ 
/*       */ 
/*       */ 
/*       */ 
/*       */ 
/*       */ 
/*       */ 
/*       */ 
/*       */ 
/*       */ 
/*       */ 
/*       */ 
/*       */ 
/*       */ 
/*       */ 
/*       */ 
/*       */ 
/*       */ 
/*       */ 
/*       */ 
/*       */ 
/*       */ 
/*       */ 
/*       */ 
/*       */ 
/*       */ 
/*       */ 
/*       */ 
/*       */ 
/*       */ 
/*       */ 
/*       */ 
/*       */ 
/*       */ 
/*       */ 
/*       */ 
/*       */ 
/*       */ 
/*       */ 
/*       */ 
/*       */ 
/*       */ 
/*       */ 
/*       */ 
/*       */ 
/*       */ 
/*       */ 
/*       */ 
/*       */ 
/*       */ 
/*       */ 
/*       */ 
/*       */ 
/*       */ 
/*       */ 
/*       */ 
/*       */ 
/*       */ 
/*       */ 
/*       */ 
/*       */ 
/*       */ 
/*       */ 
/*       */ 
/*       */ 
/*       */ 
/*       */ 
/*       */ 
/*       */ 
/*       */ 
/*       */ 
/*       */ 
/*       */ 
/*       */ 
/*       */ 
/*       */ 
/*       */ 
/*       */ 
/*       */ 
/*       */ 
/*       */ 
/*       */ 
/*       */ 
/*       */ 
/*       */ 
/*       */ 
/*       */ 
/*       */ 
/*       */ 
/*       */ 
/*       */ 
/*       */ 
/*       */ 
/*       */ 
/*       */ 
/*       */ 
/*       */ 
/*       */ 
/*       */ 
/*       */ 
/*       */ 
/*       */ 
/*       */ 
/*       */ 
/*       */ 
/*       */ 
/*       */ 
/*       */ 
/*       */ 
/*       */ 
/*       */ 
/*       */ 
/*       */ 
/*       */ 
/*       */ 
/*       */ 
/*       */ 
/*       */ 
/*       */ 
/*       */ 
/*       */ 
/*       */ 
/*       */ 
/*       */ 
/*       */ 
/*       */ 
/*       */ 
/*       */ 
/*       */ 
/*       */ 
/*       */ 
/*       */ 
/*       */ 
/*       */ 
/*       */ 
/*       */ 
/*       */ 
/*       */ 
/*       */ 
/*       */ 
/*       */ 
/*       */ 
/*       */ 
/*       */ 
/*       */ 
/*       */ 
/*       */ 
/*       */ 
/*       */ 
/*       */ 
/*       */ 
/*       */ 
/*       */ 
/*       */ 
/*       */ 
/*       */ 
/*       */ 
/*       */ 
/*       */ 
/*       */ 
/*       */ 
/*       */ 
/*       */ 
/*       */ 
/*       */ 
/*       */ 
/*       */ 
/*       */ 
/*       */ 
/*       */ 
/*       */ 
/*       */ 
/*       */ 
/*       */ 
/*       */ 
/*       */ 
/*       */ 
/*       */ 
/*       */ 
/*       */ 
/*       */ 
/*       */ 
/*       */ 
/*       */ 
/*       */ 
/*       */ 
/*       */ 
/*       */ 
/*       */ 
/*       */ 
/*       */ 
/*       */ 
/*       */ 
/*       */ 
/*       */ 
/*       */ 
/*       */ 
/*       */ 
/*       */ 
/*       */ 
/*       */ 
/*       */ 
/*       */ 
/*       */ 
/*       */ 
/*       */ 
/*       */ 
/*       */ 
/*       */ 
/*       */ 
/*       */ 
/*       */ 
/*       */ 
/*       */ 
/*       */ 
/*       */ 
/*       */ 
/*       */ 
/*       */ 
/*       */ 
/*       */ 
/*       */ 
/*       */ 
/*       */ 
/*       */ 
/*       */ 
/*       */ 
/*       */ 
/*       */ 
/*       */ 
/*       */ 
/*       */ 
/*       */ 
/*       */ 
/*       */ 
/*       */ 
/*       */ 
/*       */ 
/*       */ 
/*       */ 
/*       */ 
/*       */ 
/*       */ 
/*       */ 
/*       */ 
/*       */ 
/*       */ 
/*       */ 
/*       */ 
/*       */ 
/*       */ 
/*       */ 
/*       */ 
/*       */ 
/*       */ 
/*       */ 
/*       */ 
/*       */ 
/*       */ 
/*       */ 
/*       */ 
/*       */ 
/*       */ 
/*       */ 
/*       */ 
/*       */ 
/*       */ 
/*       */ 
/*       */ 
/*       */ 
/*       */ 
/*       */ 
/*       */ 
/*       */ 
/*       */ 
/*       */ 
/*       */ 
/*       */ 
/*       */ 
/*       */ 
/*       */ 
/*       */ 
/*       */ 
/*       */ 
/*       */ 
/*       */ 
/*       */ 
/*       */ 
/*       */ 
/*       */ 
/*       */ 
/*       */ 
/*       */ 
/*       */ 
/*       */ 
/*       */ 
/*       */ 
/*       */ 
/*       */ 
/*       */ 
/*       */ 
/*       */ 
/*       */ 
/*       */ 
/*       */ 
/*       */ 
/*       */ 
/*       */ 
/*       */ 
/*       */ 
/*       */ 
/*       */ 
/*       */ 
/*       */ 
/*       */ 
/*       */ 
/*       */ 
/*       */ 
/*       */ 
/*       */ 
/*       */ 
/*       */ 
/*       */ 
/*       */ 
/*       */ 
/*       */ 
/*       */ 
/*       */ 
/*       */ 
/*       */ 
/*       */ 
/*       */ 
/*       */ 
/*       */ 
/*       */ 
/*       */ 
/*       */ 
/*       */ 
/*       */ 
/*       */ 
/*       */ 
/*       */ 
/*       */ 
/*       */ 
/*       */ 
/*       */ 
/*       */ 
/*       */ 
/*       */ 
/*       */ 
/*       */ 
/*       */ 
/*       */ 
/*       */ 
/*       */ 
/*       */ 
/*       */ 
/*       */ 
/*       */ 
/*       */ 
/*       */ 
/*       */ 
/*       */ 
/*       */ 
/*       */ 
/*       */ 
/*       */ 
/*       */ 
/*       */ 
/*       */ 
/*       */ 
/*       */ 
/*       */ 
/*       */ 
/*       */ 
/*       */ 
/*       */ 
/*       */ 
/*       */ 
/*       */ 
/*       */ 
/*       */ 
/*       */ 
/*       */ 
/*       */ 
/*       */ 
/*       */ 
/*       */ 
/*       */ 
/*       */ 
/*       */ 
/*       */ 
/*       */ 
/*       */ 
/*       */ 
/*       */ 
/*       */ 
/*       */ 
/*       */ 
/*       */ 
/*       */ 
/*       */ 
/*       */ 
/*       */ 
/*       */ 
/*       */ 
/*       */ 
/*       */ 
/*       */ 
/*       */ 
/*       */ 
/*       */ 
/*       */ 
/*       */ 
/*       */ 
/*       */ 
/*       */ 
/*       */ 
/*       */ 
/*       */ 
/*       */ 
/*       */ 
/*       */ 
/*       */ 
/*       */ 
/*       */ 
/*       */ 
/*       */ 
/*       */ 
/*       */ 
/*       */ 
/*       */ 
/*       */ 
/*       */ 
/*       */ 
/*       */ 
/*       */ 
/*       */ 
/*       */ 
/*       */ 
/*       */ 
/*       */ 
/*       */ 
/*       */ 
/*       */ 
/*       */ 
/*       */ 
/*       */ 
/*       */ 
/*       */ 
/*       */ 
/*       */ 
/*       */ 
/*       */ 
/*       */ 
/*       */ 
/*       */ 
/*       */ 
/*       */ 
/*       */ 
/*       */ 
/*       */ 
/*       */ 
/*       */ 
/*       */ 
/*       */ 
/*       */ 
/*       */ 
/*       */ 
/*       */ 
/*       */ 
/*       */ 
/*       */ 
/*       */ 
/*       */ 
/*       */ 
/*       */ 
/*       */ 
/*       */ 
/*       */ 
/*       */ 
/*       */ 
/*       */ 
/*       */ 
/*       */ 
/*       */ 
/*       */ 
/*       */ 
/*       */ 
/*       */ 
/*       */ 
/*       */ 
/*       */ 
/*       */ 
/*       */ 
/*       */ 
/*       */ 
/*       */ 
/*       */ 
/*       */ 
/*       */ 
/*       */ 
/*       */ 
/*       */ 
/*       */ 
/*       */ 
/*       */ 
/*       */ 
/*       */ 
/*       */ 
/*       */ 
/*       */ 
/*       */ 
/*       */ 
/*       */ 
/*       */ 
/*       */ 
/*       */ 
/*       */ 
/*       */ 
/*       */ 
/*       */ 
/*       */ 
/*       */ 
/*       */ 
/*       */ 
/*       */ 
/*       */ 
/*       */ 
/*       */ 
/*       */ 
/*       */ 
/*       */ 
/*       */ 
/*       */ 
/*       */ 
/*       */ 
/*       */ 
/*       */ 
/*       */ 
/*       */ 
/*       */ 
/*       */ 
/*       */ 
/*       */ 
/*       */ 
/*       */ 
/*       */ 
/*       */ 
/*       */ 
/*       */ 
/*       */ 
/*       */ 
/*       */ 
/*       */ 
/*       */ 
/*       */ 
/*       */ 
/*       */ 
/*       */ 
/*       */ 
/*       */ 
/*       */ 
/*       */ 
/*       */ 
/*       */ 
/*       */ 
/*       */ 
/*       */ 
/*       */ 
/*       */ 
/*       */ 
/*       */ 
/*       */ 
/*       */ 
/*       */ 
/*       */ 
/*       */ 
/*       */ 
/*       */ 
/*       */ 
/*       */ 
/*       */ 
/*       */ 
/*       */ 
/*       */ 
/*       */ 
/*       */ 
/*       */ 
/*       */ 
/*       */ 
/*       */ 
/*       */ 
/*       */ 
/*       */ 
/*       */ 
/*       */ 
/*       */ 
/*       */ 
/*       */ 
/*       */ 
/*       */ 
/*       */ 
/*       */ 
/*       */ 
/*       */ 
/*       */ 
/*       */ 
/*       */ 
/*       */ 
/*       */ 
/*       */ 
/*       */ 
/*       */ 
/*       */ 
/*       */ 
/*       */ 
/*       */ 
/*       */ 
/*       */ 
/*       */ 
/*       */ 
/*       */ 
/*       */ 
/*       */ 
/*       */ 
/*       */ 
/*       */ 
/*       */ 
/*       */ 
/*       */ 
/*       */ 
/*       */ 
/*       */ 
/*       */ 
/*       */ 
/*       */ 
/*       */ 
/*       */ 
/*       */ 
/*       */ 
/*       */ 
/*       */ 
/*       */ 
/*       */ 
/*       */ 
/*       */ 
/*       */ 
/*       */ 
/*       */ 
/*       */ 
/*       */ 
/*       */ 
/*       */ 
/*       */ 
/*       */ 
/*       */ 
/*       */ 
/*       */ 
/*       */ 
/*       */ 
/*       */ 
/*       */ 
/*       */ 
/*       */ 
/*       */ 
/*       */ 
/*       */ 
/*       */ 
/*       */ 
/*       */ 
/*       */ 
/*       */ 
/*       */ 
/*       */ 
/*       */ 
/*       */ 
/*       */ 
/*       */ 
/*       */ 
/*       */ 
/*       */ 
/*       */ 
/*       */ 
/*       */ 
/*       */ 
/*       */ 
/*       */ 
/*       */ 
/*       */ 
/*       */ 
/*       */ 
/*       */ 
/*       */ 
/*       */ 
/*       */ 
/*       */ 
/*       */ 
/*       */ 
/*       */ 
/*       */ 
/*       */ 
/*       */ 
/*       */ 
/*       */ 
/*       */ 
/*       */ 
/*       */ 
/*       */ 
/*       */ 
/*       */ 
/*       */ 
/*       */ 
/*       */ 
/*       */ 
/*       */ 
/*       */ 
/*       */ 
/*       */ 
/*       */ 
/*       */ 
/*       */ 
/*       */ 
/*       */ 
/*       */ 
/*       */ 
/*       */ 
/*       */ 
/*       */ 
/*       */ 
/*       */ 
/*       */ 
/*       */ 
/*       */ 
/*       */ 
/*       */ 
/*       */ 
/*       */ 
/*       */ 
/*       */ 
/*       */ 
/*       */ 
/*       */ 
/*       */ 
/*       */ 
/*       */ 
/*       */ 
/*       */ 
/*       */ 
/*       */ 
/*       */ 
/*       */ 
/*       */ 
/*       */ 
/*       */ 
/*       */ 
/*       */ 
/*       */ 
/*       */ 
/*       */ 
/*       */ 
/*       */ 
/*       */ 
/*       */ 
/*       */ 
/*       */ 
/*       */ 
/*       */ 
/*       */ 
/*       */ 
/*       */ 
/*       */ 
/*       */ 
/*       */ 
/*       */ 
/*       */ 
/*       */ 
/*       */ 
/*       */ 
/*       */ 
/*       */ 
/*       */ 
/*       */ 
/*       */ 
/*       */ 
/*       */ 
/*       */ 
/*       */ 
/*       */ 
/*       */ 
/*       */ 
/*       */ 
/*       */ 
/*       */ 
/*       */ 
/*       */ 
/*       */ 
/*       */ 
/*       */ 
/*       */ 
/*       */ 
/*       */ 
/*       */ 
/*       */ 
/*       */ 
/*       */ 
/*       */ 
/*       */ 
/*       */ 
/*       */ 
/*       */ 
/*       */ 
/*       */ 
/*       */ 
/*       */ 
/*       */ 
/*       */ 
/*       */ 
/*       */ 
/*       */ 
/*       */ 
/*       */ 
/*       */ 
/*       */ 
/*       */ 
/*       */ 
/*       */ 
/*       */ 
/*       */ 
/*       */ 
/*       */ 
/*       */ 
/*       */ 
/*       */ 
/*       */ 
/*       */ 
/*       */ 
/*       */ 
/*       */ 
/*       */ 
/*       */ 
/*       */ 
/*       */ 
/*       */ 
/*       */ 
/*       */ 
/*       */ 
/*       */ 
/*       */ 
/*       */ 
/*       */ 
/*       */ 
/*       */ 
/*       */ 
/*       */ 
/*       */ 
/*       */ 
/*       */ 
/*       */ 
/*       */ 
/*       */ 
/*       */ 
/*       */ 
/*       */ 
/*       */ 
/*       */ 
/*       */ 
/*       */ 
/*       */ 
/*       */ 
/*       */ 
/*       */ 
/*       */ 
/*       */ 
/*       */ 
/*       */ 
/*       */ 
/*       */ 
/*       */ 
/*       */ 
/*       */ 
/*       */ 
/*       */ 
/*       */ 
/*       */ 
/*       */ 
/*       */ 
/*       */ 
/*       */ 
/*       */ 
/*       */ 
/*       */ 
/*       */ 
/*       */ 
/*       */ 
/*       */ 
/*       */ 
/*       */ 
/*       */ 
/*       */ 
/*       */ 
/*       */ 
/*       */ 
/*       */ 
/*       */ 
/*       */ 
/*       */ 
/*       */ 
/*       */ 
/*       */ 
/*       */ 
/*       */ 
/*       */ 
/*       */ 
/*       */ 
/*       */ 
/*       */ 
/*       */ 
/*       */ 
/*       */ 
/*       */ 
/*       */ 
/*       */ 
/*       */ 
/*       */ 
/*       */ 
/*       */ 
/*       */ 
/*       */ 
/*       */ 
/*       */ 
/*       */ 
/*       */ 
/*       */ 
/*       */ 
/*       */ 
/*       */ 
/*       */ 
/*       */ 
/*       */ 
/*       */ 
/*       */ 
/*       */ 
/*       */ 
/*       */ 
/*       */ 
/*       */ 
/*       */ 
/*       */ 
/*       */ 
/*       */ 
/*       */ 
/*       */ 
/*       */ 
/*       */ 
/*       */ 
/*       */ 
/*       */ 
/*       */ 
/*       */ 
/*       */ 
/*       */ 
/*       */ 
/*       */ 
/*       */ 
/*       */ 
/*       */ 
/*       */ 
/*       */ 
/*       */ 
/*       */ 
/*       */ 
/*       */ 
/*       */ 
/*       */ 
/*       */ 
/*       */ 
/*       */ 
/*       */ 
/*       */ 
/*       */ 
/*       */ 
/*       */ 
/*       */ 
/*       */ 
/*       */ 
/*       */ 
/*       */ 
/*       */ 
/*       */ 
/*       */ 
/*       */ 
/*       */ 
/*       */ 
/*       */ 
/*       */ 
/*       */ 
/*       */ 
/*       */ 
/*       */ 
/*       */ 
/*       */ 
/*       */ 
/*       */ 
/*       */ 
/*       */ 
/*       */ 
/*       */ 
/*       */   
/*       */   private <T> List<T> topologicalSort(k<T> graph) {
/*  3569 */     k<T> k1 = graph, k2 = k1;
/*       */ 
/*       */ 
/*       */ 
/*       */ 
/*       */ 
/*       */ 
/*       */ 
/*       */ 
/*       */ 
/*       */ 
/*       */ 
/*       */ 
/*       */ 
/*       */ 
/*       */ 
/*       */ 
/*       */ 
/*       */ 
/*       */ 
/*       */ 
/*       */ 
/*       */ 
/*       */ 
/*       */ 
/*       */ 
/*       */ 
/*       */ 
/*       */ 
/*       */ 
/*       */ 
/*       */ 
/*       */ 
/*       */ 
/*       */ 
/*       */ 
/*       */ 
/*       */ 
/*       */ 
/*       */ 
/*       */ 
/*       */ 
/*       */ 
/*       */ 
/*       */ 
/*       */ 
/*       */ 
/*       */ 
/*       */ 
/*       */ 
/*       */ 
/*       */ 
/*       */ 
/*       */ 
/*       */ 
/*       */ 
/*       */ 
/*       */ 
/*       */ 
/*       */ 
/*       */ 
/*       */ 
/*       */ 
/*       */ 
/*       */ 
/*       */ 
/*       */ 
/*       */ 
/*       */ 
/*       */ 
/*       */ 
/*       */ 
/*       */ 
/*       */ 
/*       */ 
/*       */ 
/*       */ 
/*       */ 
/*       */ 
/*       */ 
/*       */ 
/*       */ 
/*       */ 
/*       */ 
/*       */ 
/*       */ 
/*       */ 
/*       */ 
/*       */ 
/*       */ 
/*       */ 
/*       */ 
/*       */ 
/*       */ 
/*       */ 
/*       */ 
/*       */ 
/*       */ 
/*       */ 
/*       */ 
/*       */ 
/*       */ 
/*       */ 
/*       */ 
/*       */ 
/*       */ 
/*       */ 
/*       */ 
/*       */ 
/*       */ 
/*       */ 
/*       */ 
/*       */ 
/*       */ 
/*       */ 
/*       */ 
/*       */ 
/*       */ 
/*       */ 
/*       */ 
/*       */ 
/*       */ 
/*       */ 
/*       */ 
/*       */ 
/*       */ 
/*       */ 
/*       */ 
/*       */ 
/*       */ 
/*       */ 
/*       */ 
/*       */ 
/*       */ 
/*       */ 
/*       */ 
/*       */ 
/*       */ 
/*       */ 
/*       */ 
/*       */ 
/*       */ 
/*       */ 
/*       */ 
/*       */ 
/*       */ 
/*       */ 
/*       */ 
/*       */ 
/*       */ 
/*       */ 
/*       */ 
/*       */ 
/*       */ 
/*       */ 
/*       */ 
/*       */ 
/*       */ 
/*       */ 
/*       */ 
/*       */ 
/*       */ 
/*       */ 
/*       */ 
/*       */ 
/*       */ 
/*       */ 
/*       */ 
/*       */ 
/*       */ 
/*       */ 
/*       */ 
/*       */ 
/*       */ 
/*       */ 
/*       */ 
/*       */ 
/*       */ 
/*       */ 
/*       */ 
/*       */ 
/*       */ 
/*       */ 
/*       */ 
/*       */ 
/*       */ 
/*       */ 
/*       */ 
/*       */ 
/*       */ 
/*       */ 
/*       */ 
/*       */ 
/*       */ 
/*       */ 
/*       */ 
/*       */ 
/*       */ 
/*       */ 
/*       */ 
/*       */ 
/*       */ 
/*       */ 
/*       */ 
/*       */ 
/*       */ 
/*       */ 
/*       */ 
/*       */ 
/*       */ 
/*       */ 
/*       */ 
/*       */ 
/*       */ 
/*       */ 
/*       */ 
/*       */ 
/*       */ 
/*       */ 
/*       */ 
/*       */ 
/*       */ 
/*       */ 
/*       */ 
/*       */ 
/*       */ 
/*       */ 
/*       */ 
/*       */ 
/*       */ 
/*       */ 
/*       */ 
/*       */ 
/*       */ 
/*       */ 
/*       */ 
/*       */ 
/*       */ 
/*       */ 
/*       */ 
/*       */ 
/*       */ 
/*       */ 
/*       */ 
/*       */ 
/*       */ 
/*       */ 
/*       */ 
/*       */ 
/*       */ 
/*       */ 
/*       */ 
/*       */ 
/*       */ 
/*       */ 
/*       */ 
/*       */ 
/*       */ 
/*       */ 
/*       */ 
/*       */ 
/*       */ 
/*       */ 
/*       */ 
/*       */ 
/*       */ 
/*       */ 
/*       */ 
/*       */ 
/*       */ 
/*       */ 
/*       */ 
/*       */ 
/*       */ 
/*       */ 
/*       */ 
/*       */ 
/*       */ 
/*       */ 
/*       */ 
/*       */ 
/*       */ 
/*       */ 
/*       */ 
/*       */ 
/*       */ 
/*       */ 
/*       */ 
/*       */ 
/*       */ 
/*       */ 
/*       */ 
/*       */ 
/*       */ 
/*       */ 
/*       */ 
/*       */ 
/*       */ 
/*       */ 
/*       */ 
/*       */ 
/*       */ 
/*       */ 
/*       */ 
/*       */ 
/*       */ 
/*       */ 
/*       */ 
/*       */ 
/*       */ 
/*       */ 
/*       */ 
/*       */ 
/*       */ 
/*       */ 
/*       */ 
/*       */ 
/*       */ 
/*       */ 
/*       */ 
/*       */ 
/*       */ 
/*       */ 
/*       */ 
/*       */ 
/*       */ 
/*       */ 
/*       */ 
/*       */ 
/*       */ 
/*       */ 
/*       */ 
/*       */ 
/*       */ 
/*       */ 
/*       */ 
/*       */ 
/*       */ 
/*       */ 
/*       */ 
/*       */ 
/*       */ 
/*       */ 
/*       */ 
/*       */ 
/*       */ 
/*       */ 
/*       */ 
/*       */ 
/*       */ 
/*       */ 
/*       */ 
/*       */ 
/*       */ 
/*       */ 
/*       */ 
/*       */ 
/*       */ 
/*       */ 
/*       */ 
/*       */ 
/*       */ 
/*       */ 
/*       */ 
/*       */ 
/*       */ 
/*       */ 
/*       */ 
/*       */ 
/*       */ 
/*       */ 
/*       */ 
/*       */ 
/*       */ 
/*       */ 
/*       */ 
/*       */ 
/*       */ 
/*       */ 
/*       */ 
/*       */ 
/*       */ 
/*       */ 
/*       */ 
/*       */ 
/*       */ 
/*       */ 
/*       */ 
/*       */ 
/*       */ 
/*       */ 
/*       */ 
/*       */ 
/*       */ 
/*       */ 
/*       */ 
/*       */ 
/*       */ 
/*       */ 
/*       */ 
/*       */ 
/*       */ 
/*       */ 
/*       */ 
/*       */ 
/*       */ 
/*       */ 
/*       */ 
/*       */ 
/*       */ 
/*       */ 
/*       */ 
/*       */ 
/*       */ 
/*       */ 
/*       */ 
/*       */ 
/*       */ 
/*       */ 
/*       */ 
/*       */ 
/*       */ 
/*       */ 
/*       */ 
/*       */ 
/*       */ 
/*       */ 
/*       */ 
/*       */ 
/*       */ 
/*       */ 
/*       */ 
/*       */ 
/*       */ 
/*       */ 
/*       */ 
/*       */ 
/*       */ 
/*       */ 
/*       */ 
/*       */ 
/*       */ 
/*       */ 
/*       */ 
/*       */ 
/*       */ 
/*       */ 
/*       */ 
/*       */ 
/*       */ 
/*       */ 
/*       */ 
/*       */ 
/*       */ 
/*       */ 
/*       */ 
/*       */ 
/*       */ 
/*       */ 
/*       */ 
/*       */ 
/*       */ 
/*       */ 
/*       */ 
/*       */ 
/*       */ 
/*       */ 
/*       */ 
/*       */ 
/*       */ 
/*       */ 
/*       */ 
/*       */ 
/*       */ 
/*       */ 
/*       */ 
/*       */ 
/*       */ 
/*       */ 
/*       */ 
/*       */ 
/*       */ 
/*       */ 
/*       */ 
/*       */ 
/*       */ 
/*       */ 
/*       */ 
/*       */ 
/*       */ 
/*       */ 
/*       */ 
/*       */ 
/*       */ 
/*       */ 
/*       */ 
/*       */ 
/*       */ 
/*       */ 
/*       */ 
/*       */ 
/*       */ 
/*       */ 
/*       */ 
/*       */ 
/*       */ 
/*       */ 
/*       */ 
/*       */ 
/*       */ 
/*       */ 
/*       */ 
/*       */ 
/*       */ 
/*       */ 
/*       */ 
/*       */ 
/*       */ 
/*       */ 
/*       */ 
/*       */ 
/*       */ 
/*       */ 
/*       */ 
/*       */     
/*  4094 */     boolean bool = k2.dI();
/*       */ 
/*       */ 
/*       */ 
/*       */ 
/*       */ 
/*       */ 
/*       */ 
/*       */ 
/*       */ 
/*       */ 
/*       */ 
/*       */ 
/*       */     
/*       */     l l2;
/*       */ 
/*       */ 
/*       */ 
/*       */ 
/*       */ 
/*       */ 
/*       */ 
/*       */ 
/*       */ 
/*       */ 
/*       */ 
/*       */ 
/*       */     
/*  4122 */     (l2 = new l(k2.dH())).ml = bool;
/*       */ 
/*       */ 
/*       */ 
/*       */ 
/*       */ 
/*       */     
/*       */     g g = k2.dJ();
/*       */ 
/*       */ 
/*       */ 
/*       */ 
/*       */ 
/*       */     
/*       */     l l3;
/*       */ 
/*       */ 
/*       */ 
/*       */ 
/*       */ 
/*       */     
/*  4143 */     (l3 = l2).mm = (g)g.f(g); g = k2.dF();
/*  4144 */     l2 = l3;
/*       */ 
/*       */ 
/*       */ 
/*       */ 
/*       */ 
/*       */ 
/*       */ 
/*       */ 
/*       */ 
/*       */ 
/*       */ 
/*       */ 
/*       */ 
/*       */ 
/*       */ 
/*       */ 
/*       */ 
/*       */ 
/*       */ 
/*       */ 
/*       */ 
/*       */ 
/*       */ 
/*       */ 
/*       */ 
/*       */ 
/*       */ 
/*       */ 
/*       */ 
/*       */ 
/*       */ 
/*       */ 
/*       */ 
/*       */ 
/*       */ 
/*       */ 
/*       */ 
/*       */ 
/*       */ 
/*       */ 
/*       */ 
/*       */ 
/*       */ 
/*       */ 
/*       */ 
/*       */ 
/*       */ 
/*       */ 
/*       */ 
/*       */ 
/*       */ 
/*       */ 
/*       */ 
/*       */ 
/*       */ 
/*       */ 
/*       */ 
/*       */ 
/*       */ 
/*       */ 
/*       */ 
/*       */ 
/*       */ 
/*       */ 
/*       */ 
/*       */ 
/*       */ 
/*       */ 
/*       */ 
/*       */ 
/*       */ 
/*       */ 
/*       */ 
/*       */ 
/*       */ 
/*       */ 
/*       */ 
/*       */ 
/*       */ 
/*       */ 
/*       */ 
/*       */ 
/*       */ 
/*       */ 
/*       */ 
/*       */ 
/*       */ 
/*       */ 
/*       */ 
/*       */ 
/*       */ 
/*       */ 
/*       */ 
/*       */ 
/*       */ 
/*       */ 
/*       */ 
/*       */ 
/*       */ 
/*       */ 
/*       */ 
/*       */ 
/*       */ 
/*       */ 
/*       */ 
/*       */ 
/*       */ 
/*       */ 
/*       */ 
/*       */ 
/*       */ 
/*       */ 
/*       */ 
/*       */ 
/*       */ 
/*       */ 
/*       */ 
/*       */ 
/*       */ 
/*       */ 
/*       */ 
/*       */ 
/*       */ 
/*       */ 
/*       */ 
/*       */ 
/*       */ 
/*       */ 
/*       */ 
/*       */ 
/*       */ 
/*       */ 
/*       */ 
/*       */ 
/*       */ 
/*       */ 
/*       */ 
/*       */ 
/*       */ 
/*       */ 
/*       */ 
/*       */ 
/*       */ 
/*       */ 
/*       */ 
/*       */ 
/*       */ 
/*       */ 
/*       */ 
/*       */ 
/*       */ 
/*       */ 
/*       */ 
/*       */ 
/*       */ 
/*       */ 
/*       */ 
/*       */ 
/*       */ 
/*       */ 
/*       */ 
/*       */ 
/*       */ 
/*       */ 
/*       */ 
/*       */ 
/*       */ 
/*       */ 
/*       */ 
/*       */ 
/*       */ 
/*       */ 
/*       */ 
/*       */ 
/*       */ 
/*       */ 
/*       */ 
/*       */ 
/*       */ 
/*       */ 
/*       */ 
/*       */ 
/*       */ 
/*       */ 
/*       */ 
/*       */ 
/*       */ 
/*       */ 
/*       */ 
/*       */ 
/*       */ 
/*       */ 
/*       */ 
/*       */ 
/*       */ 
/*       */ 
/*       */ 
/*       */ 
/*       */ 
/*       */ 
/*       */ 
/*       */ 
/*       */ 
/*       */ 
/*       */ 
/*       */ 
/*       */ 
/*       */ 
/*       */ 
/*       */ 
/*       */ 
/*       */ 
/*       */ 
/*       */ 
/*       */ 
/*       */ 
/*       */ 
/*       */ 
/*       */ 
/*       */ 
/*       */ 
/*       */ 
/*       */ 
/*       */ 
/*       */ 
/*       */ 
/*       */ 
/*       */ 
/*       */ 
/*       */ 
/*       */ 
/*       */ 
/*       */ 
/*       */ 
/*       */ 
/*       */ 
/*       */ 
/*       */ 
/*       */ 
/*       */ 
/*       */ 
/*       */ 
/*       */ 
/*       */ 
/*       */ 
/*       */ 
/*       */ 
/*       */ 
/*       */ 
/*       */ 
/*       */ 
/*       */ 
/*       */ 
/*       */ 
/*       */ 
/*       */ 
/*       */ 
/*       */ 
/*       */ 
/*       */ 
/*       */ 
/*       */ 
/*       */ 
/*       */ 
/*       */ 
/*       */ 
/*       */ 
/*       */ 
/*       */ 
/*       */ 
/*       */ 
/*       */ 
/*       */ 
/*       */ 
/*       */ 
/*       */ 
/*       */ 
/*       */ 
/*       */ 
/*       */ 
/*       */ 
/*       */ 
/*       */ 
/*       */ 
/*       */ 
/*       */ 
/*       */ 
/*       */ 
/*       */ 
/*       */ 
/*       */ 
/*       */ 
/*       */ 
/*       */ 
/*       */ 
/*       */ 
/*       */ 
/*       */ 
/*       */ 
/*       */ 
/*       */ 
/*       */ 
/*       */ 
/*       */ 
/*       */ 
/*       */ 
/*       */ 
/*       */ 
/*       */ 
/*       */ 
/*       */ 
/*       */ 
/*       */ 
/*       */ 
/*       */ 
/*       */ 
/*       */ 
/*       */ 
/*       */ 
/*       */ 
/*       */ 
/*       */ 
/*       */ 
/*       */ 
/*       */ 
/*       */ 
/*       */ 
/*       */ 
/*       */ 
/*       */ 
/*       */ 
/*       */ 
/*       */ 
/*       */ 
/*       */ 
/*       */ 
/*       */ 
/*       */ 
/*       */ 
/*       */ 
/*       */ 
/*       */ 
/*       */ 
/*       */ 
/*       */ 
/*       */ 
/*       */ 
/*       */ 
/*       */ 
/*       */ 
/*       */ 
/*       */ 
/*       */ 
/*       */ 
/*       */ 
/*       */ 
/*       */ 
/*       */ 
/*       */ 
/*       */ 
/*       */ 
/*       */ 
/*       */ 
/*       */ 
/*       */ 
/*       */ 
/*       */ 
/*       */ 
/*       */ 
/*       */ 
/*       */ 
/*       */ 
/*       */ 
/*       */ 
/*       */ 
/*       */ 
/*       */ 
/*       */ 
/*       */ 
/*       */ 
/*       */ 
/*       */ 
/*       */ 
/*       */ 
/*       */ 
/*       */ 
/*       */ 
/*       */ 
/*       */ 
/*       */ 
/*       */ 
/*       */ 
/*       */ 
/*       */ 
/*       */ 
/*       */ 
/*       */ 
/*       */ 
/*       */ 
/*       */ 
/*       */ 
/*       */ 
/*       */ 
/*       */ 
/*       */ 
/*       */ 
/*       */ 
/*       */ 
/*       */ 
/*       */ 
/*       */ 
/*       */ 
/*       */ 
/*       */ 
/*       */ 
/*       */ 
/*       */ 
/*       */ 
/*       */ 
/*       */ 
/*       */ 
/*       */ 
/*       */ 
/*       */ 
/*       */ 
/*       */ 
/*       */ 
/*       */ 
/*       */ 
/*       */ 
/*       */ 
/*       */ 
/*       */ 
/*       */ 
/*       */ 
/*       */ 
/*       */ 
/*       */ 
/*       */ 
/*       */ 
/*       */ 
/*       */ 
/*       */ 
/*       */ 
/*       */ 
/*       */ 
/*       */ 
/*       */ 
/*       */ 
/*       */ 
/*       */ 
/*       */ 
/*       */ 
/*       */ 
/*       */ 
/*       */ 
/*       */ 
/*       */ 
/*       */ 
/*       */ 
/*       */ 
/*       */ 
/*       */ 
/*       */ 
/*       */ 
/*       */ 
/*       */ 
/*       */ 
/*       */ 
/*       */ 
/*       */ 
/*       */ 
/*       */ 
/*       */ 
/*       */ 
/*       */ 
/*       */ 
/*       */ 
/*       */ 
/*       */ 
/*       */ 
/*       */ 
/*       */ 
/*       */ 
/*       */ 
/*       */ 
/*       */ 
/*       */ 
/*       */ 
/*       */ 
/*       */ 
/*       */ 
/*       */ 
/*       */ 
/*       */ 
/*       */ 
/*       */ 
/*       */ 
/*       */ 
/*       */ 
/*       */ 
/*       */ 
/*       */ 
/*       */ 
/*       */ 
/*       */ 
/*       */ 
/*       */ 
/*       */ 
/*       */ 
/*       */ 
/*       */ 
/*       */ 
/*       */ 
/*       */ 
/*       */ 
/*       */ 
/*       */ 
/*       */ 
/*       */ 
/*       */ 
/*       */ 
/*       */ 
/*       */ 
/*       */ 
/*       */ 
/*       */ 
/*       */ 
/*       */ 
/*       */ 
/*       */ 
/*       */ 
/*       */ 
/*       */ 
/*       */ 
/*       */ 
/*       */ 
/*       */ 
/*       */ 
/*       */ 
/*       */ 
/*       */ 
/*       */ 
/*       */ 
/*       */ 
/*       */ 
/*       */ 
/*       */ 
/*       */ 
/*       */ 
/*       */ 
/*       */ 
/*       */ 
/*       */ 
/*       */ 
/*       */ 
/*       */ 
/*       */ 
/*       */ 
/*       */ 
/*       */ 
/*       */ 
/*       */ 
/*       */ 
/*       */ 
/*       */ 
/*       */ 
/*       */ 
/*       */ 
/*       */ 
/*       */ 
/*       */ 
/*       */ 
/*       */ 
/*       */ 
/*       */ 
/*       */ 
/*       */ 
/*       */ 
/*       */ 
/*       */ 
/*       */ 
/*       */ 
/*       */ 
/*       */ 
/*       */ 
/*       */ 
/*       */ 
/*       */ 
/*       */ 
/*       */ 
/*       */ 
/*       */ 
/*       */ 
/*       */ 
/*       */ 
/*       */ 
/*       */ 
/*       */ 
/*       */ 
/*       */ 
/*       */ 
/*       */ 
/*       */ 
/*       */ 
/*       */ 
/*       */ 
/*       */ 
/*       */ 
/*       */ 
/*       */ 
/*       */ 
/*       */ 
/*       */ 
/*       */ 
/*       */ 
/*       */ 
/*       */ 
/*       */ 
/*       */ 
/*       */ 
/*       */ 
/*       */ 
/*       */ 
/*       */ 
/*       */ 
/*       */ 
/*       */ 
/*       */ 
/*       */ 
/*       */ 
/*       */ 
/*       */ 
/*       */ 
/*       */ 
/*       */ 
/*       */ 
/*       */ 
/*       */ 
/*       */ 
/*       */ 
/*       */ 
/*       */ 
/*       */ 
/*       */ 
/*       */ 
/*       */ 
/*       */ 
/*       */ 
/*       */ 
/*       */ 
/*       */ 
/*       */ 
/*       */ 
/*       */ 
/*       */ 
/*       */ 
/*       */ 
/*       */ 
/*       */ 
/*       */ 
/*       */ 
/*       */ 
/*       */ 
/*       */ 
/*       */ 
/*       */ 
/*       */ 
/*       */ 
/*       */ 
/*       */ 
/*       */ 
/*       */ 
/*       */ 
/*       */ 
/*       */ 
/*       */ 
/*       */ 
/*       */ 
/*       */ 
/*       */ 
/*       */ 
/*       */ 
/*       */ 
/*       */ 
/*       */ 
/*       */ 
/*       */ 
/*       */ 
/*       */ 
/*       */ 
/*       */ 
/*       */ 
/*       */ 
/*       */ 
/*       */ 
/*       */ 
/*       */ 
/*       */ 
/*       */ 
/*       */ 
/*       */ 
/*       */ 
/*       */ 
/*       */ 
/*       */ 
/*       */ 
/*       */ 
/*       */ 
/*       */ 
/*       */ 
/*       */ 
/*       */ 
/*       */ 
/*       */ 
/*       */ 
/*       */ 
/*       */ 
/*       */ 
/*       */ 
/*       */ 
/*       */ 
/*       */ 
/*       */ 
/*       */ 
/*       */ 
/*       */ 
/*       */ 
/*       */ 
/*       */ 
/*       */ 
/*       */ 
/*       */ 
/*       */ 
/*       */ 
/*       */ 
/*       */ 
/*       */ 
/*       */ 
/*       */ 
/*       */ 
/*       */ 
/*       */ 
/*       */ 
/*       */ 
/*       */ 
/*       */ 
/*       */ 
/*       */ 
/*       */ 
/*       */ 
/*       */ 
/*       */ 
/*       */ 
/*       */ 
/*       */ 
/*       */ 
/*       */ 
/*       */ 
/*       */ 
/*       */ 
/*       */ 
/*       */ 
/*       */ 
/*       */ 
/*       */ 
/*       */ 
/*       */ 
/*       */ 
/*       */ 
/*       */ 
/*       */ 
/*       */ 
/*       */ 
/*       */ 
/*       */ 
/*       */ 
/*       */ 
/*       */ 
/*       */ 
/*       */ 
/*       */ 
/*       */ 
/*       */ 
/*       */ 
/*       */ 
/*       */ 
/*       */ 
/*       */ 
/*       */ 
/*       */ 
/*       */ 
/*       */ 
/*       */ 
/*       */ 
/*       */ 
/*       */ 
/*       */ 
/*       */ 
/*       */ 
/*       */ 
/*       */ 
/*       */ 
/*       */ 
/*       */ 
/*       */ 
/*       */ 
/*       */ 
/*       */ 
/*       */ 
/*       */ 
/*       */ 
/*       */ 
/*       */ 
/*       */ 
/*       */ 
/*       */ 
/*       */ 
/*       */ 
/*       */ 
/*       */ 
/*       */ 
/*       */ 
/*       */ 
/*       */ 
/*       */ 
/*       */ 
/*       */ 
/*       */ 
/*       */ 
/*       */ 
/*       */ 
/*       */ 
/*       */ 
/*       */ 
/*       */ 
/*       */ 
/*       */ 
/*       */ 
/*       */ 
/*       */ 
/*       */ 
/*       */ 
/*       */ 
/*       */ 
/*       */ 
/*       */ 
/*       */ 
/*       */ 
/*       */ 
/*       */ 
/*       */ 
/*       */ 
/*       */ 
/*       */ 
/*       */ 
/*       */ 
/*       */ 
/*       */ 
/*       */ 
/*       */ 
/*       */ 
/*       */ 
/*       */ 
/*       */ 
/*       */ 
/*       */ 
/*       */ 
/*       */ 
/*       */ 
/*       */ 
/*       */ 
/*       */ 
/*       */ 
/*       */ 
/*       */ 
/*       */ 
/*       */ 
/*       */ 
/*       */ 
/*       */ 
/*       */ 
/*       */ 
/*       */ 
/*       */ 
/*       */ 
/*       */ 
/*       */ 
/*       */ 
/*       */ 
/*       */ 
/*       */ 
/*       */ 
/*       */ 
/*       */ 
/*       */ 
/*       */ 
/*       */ 
/*       */ 
/*       */ 
/*       */ 
/*       */ 
/*       */ 
/*       */ 
/*       */ 
/*       */ 
/*       */ 
/*       */ 
/*       */ 
/*       */ 
/*       */ 
/*       */ 
/*       */ 
/*       */ 
/*       */ 
/*       */ 
/*       */ 
/*       */ 
/*       */ 
/*       */ 
/*       */ 
/*       */ 
/*       */ 
/*       */ 
/*       */ 
/*       */ 
/*       */ 
/*       */ 
/*       */ 
/*       */ 
/*       */ 
/*       */ 
/*       */ 
/*       */ 
/*       */ 
/*       */ 
/*       */ 
/*       */ 
/*       */ 
/*       */ 
/*       */ 
/*       */ 
/*       */ 
/*       */ 
/*       */ 
/*       */ 
/*       */ 
/*       */ 
/*       */ 
/*       */ 
/*       */ 
/*       */ 
/*       */ 
/*       */ 
/*       */ 
/*       */ 
/*       */ 
/*       */ 
/*       */ 
/*       */ 
/*       */ 
/*       */ 
/*       */ 
/*       */ 
/*       */ 
/*       */ 
/*       */ 
/*       */ 
/*       */ 
/*       */ 
/*       */ 
/*       */ 
/*       */ 
/*       */ 
/*       */ 
/*       */ 
/*       */ 
/*       */ 
/*       */ 
/*       */ 
/*       */ 
/*       */ 
/*       */ 
/*       */ 
/*       */ 
/*       */ 
/*       */ 
/*       */ 
/*       */ 
/*       */ 
/*       */ 
/*       */ 
/*       */ 
/*       */ 
/*       */ 
/*       */ 
/*       */ 
/*       */ 
/*       */ 
/*       */ 
/*       */ 
/*       */ 
/*       */ 
/*       */ 
/*       */ 
/*       */ 
/*       */ 
/*       */ 
/*       */ 
/*       */ 
/*       */ 
/*       */ 
/*       */ 
/*       */ 
/*       */ 
/*       */     
/*  5161 */     g.a((g
/*       */ 
/*       */ 
/*       */ 
/*       */ 
/*       */ 
/*       */ 
/*       */ 
/*       */ 
/*       */ 
/*       */ 
/*       */ 
/*       */ 
/*       */ 
/*       */ 
/*       */ 
/*       */ 
/*       */ 
/*       */ 
/*       */ 
/*       */ 
/*       */ 
/*       */ 
/*       */ 
/*       */ 
/*       */ 
/*       */ 
/*       */ 
/*       */ 
/*       */ 
/*       */ 
/*       */ 
/*       */ 
/*       */ 
/*       */ 
/*       */ 
/*       */ 
/*       */ 
/*       */ 
/*       */ 
/*       */ 
/*       */ 
/*       */ 
/*       */ 
/*       */ 
/*       */ 
/*       */ 
/*       */ 
/*       */ 
/*       */ 
/*       */ 
/*       */ 
/*       */ 
/*       */ 
/*       */ 
/*       */ 
/*       */ 
/*       */ 
/*       */ 
/*       */ 
/*       */ 
/*       */ 
/*       */ 
/*       */ 
/*       */ 
/*       */ 
/*       */ 
/*       */ 
/*       */ 
/*       */ 
/*       */ 
/*       */ 
/*       */ 
/*       */ 
/*       */ 
/*       */ 
/*       */ 
/*       */ 
/*       */ 
/*       */ 
/*       */ 
/*       */ 
/*       */ 
/*       */ 
/*       */ 
/*       */ 
/*       */ 
/*       */ 
/*       */ 
/*       */ 
/*       */ 
/*       */ 
/*       */ 
/*       */ 
/*       */ 
/*       */ 
/*       */ 
/*       */ 
/*       */ 
/*       */ 
/*       */ 
/*       */ 
/*       */ 
/*       */ 
/*       */ 
/*       */ 
/*       */ 
/*       */ 
/*       */ 
/*       */ 
/*       */ 
/*       */ 
/*       */ 
/*       */ 
/*       */ 
/*       */ 
/*       */ 
/*       */ 
/*       */ 
/*       */ 
/*       */ 
/*       */ 
/*       */ 
/*       */ 
/*       */ 
/*       */ 
/*       */ 
/*       */ 
/*       */ 
/*       */ 
/*       */ 
/*       */ 
/*       */ 
/*       */ 
/*       */ 
/*       */ 
/*       */ 
/*       */ 
/*       */ 
/*       */ 
/*       */ 
/*       */ 
/*       */ 
/*       */ 
/*       */ 
/*       */ 
/*       */ 
/*       */ 
/*       */ 
/*       */ 
/*       */ 
/*       */ 
/*       */ 
/*       */ 
/*       */ 
/*       */ 
/*       */ 
/*       */ 
/*       */ 
/*       */ 
/*       */ 
/*       */ 
/*       */ 
/*       */ 
/*       */ 
/*       */ 
/*       */ 
/*       */ 
/*       */ 
/*       */ 
/*       */ 
/*       */ 
/*       */ 
/*       */ 
/*       */ 
/*       */ 
/*       */ 
/*       */ 
/*       */ 
/*       */ 
/*       */ 
/*       */ 
/*       */ 
/*       */ 
/*       */ 
/*       */ 
/*       */ 
/*       */ 
/*       */ 
/*       */ 
/*       */ 
/*       */ 
/*       */ 
/*       */ 
/*       */ 
/*       */ 
/*       */ 
/*       */ 
/*       */ 
/*       */ 
/*       */ 
/*       */ 
/*       */ 
/*       */ 
/*       */ 
/*       */ 
/*       */ 
/*       */ 
/*       */ 
/*       */ 
/*       */ 
/*       */ 
/*       */ 
/*       */ 
/*       */ 
/*       */ 
/*       */ 
/*       */ 
/*       */ 
/*       */ 
/*       */ 
/*       */ 
/*       */ 
/*       */ 
/*       */ 
/*       */ 
/*       */ 
/*       */ 
/*       */ 
/*       */ 
/*       */ 
/*       */ 
/*       */ 
/*       */ 
/*       */ 
/*       */ 
/*       */ 
/*       */ 
/*       */ 
/*       */ 
/*       */ 
/*       */ 
/*       */ 
/*       */ 
/*       */ 
/*       */ 
/*       */ 
/*       */ 
/*       */ 
/*       */ 
/*       */ 
/*       */ 
/*       */ 
/*       */ 
/*       */ 
/*       */ 
/*       */ 
/*       */ 
/*       */ 
/*       */ 
/*       */ 
/*       */ 
/*       */ 
/*       */ 
/*       */ 
/*       */ 
/*       */ 
/*       */ 
/*       */ 
/*       */ 
/*       */ 
/*       */ 
/*       */ 
/*       */ 
/*       */ 
/*       */ 
/*       */ 
/*       */ 
/*       */ 
/*       */ 
/*       */ 
/*       */ 
/*       */ 
/*       */ 
/*       */ 
/*       */ 
/*       */ 
/*       */ 
/*       */ 
/*       */ 
/*       */ 
/*       */ 
/*       */ 
/*       */ 
/*       */ 
/*       */ 
/*       */ 
/*       */ 
/*       */ 
/*       */ 
/*       */ 
/*       */ 
/*       */ 
/*       */ 
/*       */ 
/*       */ 
/*       */ 
/*       */ 
/*       */ 
/*       */ 
/*       */ 
/*       */ 
/*       */ 
/*       */ 
/*       */ 
/*       */ 
/*       */ 
/*       */ 
/*       */ 
/*       */ 
/*       */ 
/*       */ 
/*       */ 
/*       */ 
/*       */ 
/*       */ 
/*       */ 
/*       */ 
/*       */ 
/*       */ 
/*       */ 
/*       */ 
/*       */ 
/*       */ 
/*       */ 
/*       */ 
/*       */ 
/*       */ 
/*       */ 
/*       */ 
/*       */ 
/*       */ 
/*       */ 
/*       */ 
/*       */ 
/*       */ 
/*       */ 
/*       */ 
/*       */ 
/*       */ 
/*       */ 
/*       */ 
/*       */ 
/*       */ 
/*       */ 
/*       */ 
/*       */ 
/*       */ 
/*       */ 
/*       */ 
/*       */ 
/*       */ 
/*       */ 
/*       */ 
/*       */ 
/*       */ 
/*       */ 
/*       */ 
/*       */ 
/*       */ 
/*       */ 
/*       */ 
/*       */ 
/*       */ 
/*       */ 
/*       */ 
/*       */ 
/*       */ 
/*       */ 
/*       */ 
/*       */ 
/*       */ 
/*       */ 
/*       */ 
/*       */ 
/*       */ 
/*       */ 
/*       */ 
/*       */ 
/*       */ 
/*       */ 
/*       */ 
/*       */ 
/*       */ 
/*       */ 
/*       */ 
/*       */ 
/*       */ 
/*       */ 
/*       */ 
/*       */ 
/*       */ 
/*       */ 
/*       */ 
/*       */ 
/*       */ 
/*       */ 
/*       */ 
/*       */ 
/*       */ 
/*       */ 
/*       */ 
/*       */ 
/*       */ 
/*       */ 
/*       */ 
/*       */ 
/*       */ 
/*       */ 
/*       */ 
/*       */ 
/*       */ 
/*       */ 
/*       */ 
/*       */ 
/*       */ 
/*       */ 
/*       */ 
/*       */ 
/*       */ 
/*       */ 
/*       */ 
/*       */ 
/*       */ 
/*       */ 
/*       */ 
/*       */ 
/*       */ 
/*       */ 
/*       */ 
/*       */ 
/*       */ 
/*       */ 
/*       */ 
/*       */ 
/*       */ 
/*       */ 
/*       */ 
/*       */ 
/*       */ 
/*       */ 
/*       */ 
/*       */ 
/*       */ 
/*       */ 
/*       */ 
/*       */ 
/*       */ 
/*       */ 
/*       */ 
/*       */ 
/*       */ 
/*       */ 
/*       */ 
/*       */ 
/*       */ 
/*       */ 
/*       */ 
/*       */ 
/*       */ 
/*       */ 
/*       */ 
/*       */ 
/*       */ 
/*       */ 
/*       */ 
/*       */ 
/*       */ 
/*       */ 
/*       */ 
/*       */ 
/*       */ 
/*       */ 
/*       */ 
/*       */ 
/*       */ 
/*       */ 
/*       */ 
/*       */ 
/*       */ 
/*       */ 
/*       */ 
/*       */ 
/*       */ 
/*       */ 
/*       */ 
/*       */ 
/*       */ 
/*       */ 
/*       */ 
/*       */ 
/*       */ 
/*       */ 
/*       */ 
/*       */ 
/*       */ 
/*       */ 
/*       */ 
/*       */ 
/*       */ 
/*       */ 
/*       */ 
/*       */ 
/*       */ 
/*       */ 
/*       */ 
/*       */ 
/*       */ 
/*       */ 
/*       */ 
/*       */ 
/*       */ 
/*       */ 
/*       */ 
/*       */ 
/*       */ 
/*       */ 
/*       */ 
/*       */ 
/*       */ 
/*       */ 
/*       */ 
/*       */ 
/*       */ 
/*       */ 
/*       */ 
/*       */ 
/*       */ 
/*       */ 
/*       */ 
/*       */ 
/*       */ 
/*       */ 
/*       */ 
/*       */ 
/*       */ 
/*       */ 
/*       */ 
/*       */ 
/*       */ 
/*       */ 
/*       */ 
/*       */ 
/*       */ 
/*       */ 
/*       */ 
/*       */ 
/*       */ 
/*       */ 
/*       */ 
/*       */ 
/*       */ 
/*       */ 
/*       */ 
/*       */ 
/*       */ 
/*       */ 
/*       */ 
/*       */ 
/*       */ 
/*       */ 
/*       */ 
/*       */ 
/*       */ 
/*       */ 
/*       */ 
/*       */ 
/*       */ 
/*       */ 
/*       */ 
/*       */ 
/*       */ 
/*       */ 
/*       */ 
/*       */ 
/*       */ 
/*       */ 
/*       */ 
/*       */ 
/*       */ 
/*       */ 
/*       */ 
/*       */ 
/*       */ 
/*       */ 
/*       */ 
/*       */ 
/*       */ 
/*       */ 
/*       */ 
/*       */ 
/*       */ 
/*       */ 
/*       */ 
/*       */ 
/*       */ 
/*       */ 
/*       */ 
/*       */ 
/*       */ 
/*       */ 
/*       */ 
/*       */ 
/*       */ 
/*       */ 
/*       */ 
/*       */ 
/*       */ 
/*       */ 
/*       */ 
/*       */ 
/*       */ 
/*       */ 
/*       */ 
/*       */ 
/*       */ 
/*       */ 
/*       */ 
/*       */ 
/*       */ 
/*       */ 
/*       */ 
/*       */ 
/*       */ 
/*       */ 
/*       */ 
/*       */ 
/*       */ 
/*       */ 
/*       */ 
/*       */ 
/*       */ 
/*       */ 
/*       */ 
/*       */ 
/*       */ 
/*       */ 
/*       */ 
/*       */ 
/*       */ 
/*       */ 
/*       */ 
/*       */ 
/*       */ 
/*       */ 
/*       */ 
/*       */ 
/*       */ 
/*       */ 
/*       */ 
/*       */ 
/*       */ 
/*       */ 
/*       */ 
/*       */ 
/*       */ 
/*       */ 
/*       */ 
/*       */ 
/*       */ 
/*       */ 
/*       */ 
/*       */ 
/*       */ 
/*       */ 
/*       */ 
/*       */ 
/*       */ 
/*       */ 
/*       */ 
/*       */ 
/*       */ 
/*       */ 
/*       */ 
/*       */ 
/*       */ 
/*       */ 
/*       */ 
/*       */ 
/*       */ 
/*       */ 
/*       */ 
/*       */ 
/*       */ 
/*       */ 
/*       */ 
/*       */ 
/*       */ 
/*       */ 
/*       */ 
/*       */ 
/*       */ 
/*       */ 
/*       */ 
/*       */ 
/*       */ 
/*       */ 
/*       */ 
/*       */ 
/*       */ 
/*       */ 
/*       */ 
/*       */ 
/*       */ 
/*       */ 
/*       */ 
/*       */ 
/*       */ 
/*       */ 
/*       */ 
/*       */ 
/*       */ 
/*       */ 
/*       */ 
/*       */ 
/*       */ 
/*       */ 
/*       */ 
/*       */ 
/*       */ 
/*       */ 
/*       */ 
/*       */ 
/*       */ 
/*       */ 
/*       */ 
/*       */ 
/*       */ 
/*       */ 
/*       */ 
/*       */ 
/*       */ 
/*       */ 
/*       */ 
/*       */ 
/*       */ 
/*       */ 
/*       */ 
/*       */ 
/*       */ 
/*       */ 
/*       */ 
/*       */ 
/*       */ 
/*       */ 
/*       */ 
/*       */ 
/*       */ 
/*       */ 
/*       */ 
/*       */ 
/*       */ 
/*       */ 
/*       */ 
/*       */ 
/*       */ 
/*       */ 
/*       */ 
/*       */ 
/*       */ 
/*       */ 
/*       */ 
/*       */ 
/*       */ 
/*       */ 
/*       */ 
/*       */ 
/*       */ 
/*       */ 
/*       */ 
/*       */ 
/*       */ 
/*       */ 
/*       */ 
/*       */ 
/*       */ 
/*       */ 
/*       */ 
/*       */ 
/*       */ 
/*       */ 
/*       */ 
/*       */ 
/*       */ 
/*       */ 
/*       */ 
/*       */ 
/*       */ 
/*       */ 
/*       */ 
/*       */ 
/*       */ 
/*       */ 
/*       */ 
/*       */ 
/*       */ 
/*       */ 
/*       */ 
/*       */ 
/*       */ 
/*       */ 
/*       */ 
/*       */ 
/*       */ 
/*       */ 
/*       */ 
/*       */ 
/*       */ 
/*       */ 
/*       */ 
/*       */ 
/*       */ 
/*       */ 
/*       */ 
/*       */ 
/*       */ 
/*       */ 
/*       */ 
/*       */ 
/*       */ 
/*       */ 
/*       */ 
/*       */ 
/*       */ 
/*       */ 
/*       */ 
/*       */ 
/*       */ 
/*       */ 
/*       */ 
/*       */ 
/*       */ 
/*       */ 
/*       */ 
/*       */ 
/*       */ 
/*       */ 
/*       */ 
/*       */ 
/*       */ 
/*       */ 
/*       */ 
/*       */ 
/*       */ 
/*       */ 
/*       */ 
/*       */ 
/*       */ 
/*       */ 
/*       */ 
/*       */ 
/*       */ 
/*       */ 
/*       */ 
/*       */ 
/*       */ 
/*       */ 
/*       */ 
/*       */ 
/*       */ 
/*       */ 
/*       */ 
/*       */ 
/*       */ 
/*       */ 
/*       */ 
/*       */ 
/*       */ 
/*       */ 
/*       */ 
/*       */ 
/*       */ 
/*       */ 
/*       */ 
/*       */ 
/*       */ 
/*       */ 
/*       */ 
/*       */ 
/*       */ 
/*       */ 
/*       */ 
/*       */ 
/*       */ 
/*       */ 
/*       */ 
/*       */ 
/*       */ 
/*       */ 
/*       */ 
/*       */ 
/*       */ 
/*       */ 
/*       */ 
/*       */ 
/*       */ 
/*       */ 
/*       */ 
/*       */ 
/*       */ 
/*       */ 
/*       */ 
/*       */ 
/*       */ 
/*       */ 
/*       */ 
/*       */ 
/*       */ 
/*       */ 
/*       */ 
/*       */ 
/*       */ 
/*       */ 
/*       */ 
/*       */ 
/*       */ 
/*       */ 
/*       */ 
/*       */ 
/*       */ 
/*       */ 
/*       */ 
/*       */ 
/*       */ 
/*       */ 
/*       */ 
/*       */ 
/*       */ 
/*       */ 
/*       */ 
/*       */ 
/*       */ 
/*       */ 
/*       */ 
/*       */ 
/*       */ 
/*       */ 
/*       */ 
/*       */ 
/*       */ 
/*       */ 
/*       */ 
/*       */ 
/*       */ 
/*       */ 
/*       */ 
/*       */ 
/*       */ 
/*       */ 
/*       */ 
/*       */ 
/*       */ 
/*       */ 
/*       */ 
/*       */ 
/*       */ 
/*       */ 
/*       */ 
/*       */ 
/*       */ 
/*       */ 
/*       */ 
/*       */ 
/*       */ 
/*       */ 
/*       */ 
/*       */ 
/*       */ 
/*       */ 
/*       */ 
/*       */ 
/*       */ 
/*       */ 
/*       */ 
/*       */ 
/*       */ 
/*       */         
/*  6148 */         .mC == g.a.mD || g
/*       */ 
/*       */ 
/*       */ 
/*       */ 
/*       */ 
/*       */ 
/*       */ 
/*       */ 
/*       */ 
/*       */ 
/*       */ 
/*       */ 
/*       */ 
/*       */ 
/*       */ 
/*       */ 
/*       */ 
/*       */ 
/*       */ 
/*       */ 
/*       */ 
/*       */ 
/*       */ 
/*       */ 
/*       */ 
/*       */ 
/*       */ 
/*       */ 
/*       */ 
/*       */ 
/*       */ 
/*       */ 
/*       */ 
/*       */ 
/*       */ 
/*       */ 
/*       */ 
/*       */ 
/*       */ 
/*       */ 
/*       */ 
/*       */ 
/*       */ 
/*       */ 
/*       */ 
/*       */ 
/*       */ 
/*       */ 
/*       */ 
/*       */ 
/*       */ 
/*       */ 
/*       */ 
/*       */ 
/*       */ 
/*       */ 
/*       */ 
/*       */ 
/*       */ 
/*       */ 
/*       */ 
/*       */ 
/*       */ 
/*       */ 
/*       */ 
/*       */ 
/*       */ 
/*       */ 
/*       */ 
/*       */ 
/*       */ 
/*       */ 
/*       */ 
/*       */ 
/*       */ 
/*       */ 
/*       */ 
/*       */ 
/*       */ 
/*       */ 
/*       */ 
/*       */ 
/*       */ 
/*       */ 
/*       */ 
/*       */ 
/*       */ 
/*       */ 
/*       */ 
/*       */ 
/*       */ 
/*       */ 
/*       */ 
/*       */ 
/*       */ 
/*       */ 
/*       */ 
/*       */ 
/*       */ 
/*       */ 
/*       */ 
/*       */ 
/*       */ 
/*       */ 
/*       */ 
/*       */ 
/*       */ 
/*       */ 
/*       */ 
/*       */ 
/*       */ 
/*       */ 
/*       */ 
/*       */ 
/*       */ 
/*       */ 
/*       */ 
/*       */ 
/*       */ 
/*       */ 
/*       */ 
/*       */ 
/*       */ 
/*       */ 
/*       */ 
/*       */ 
/*       */ 
/*       */ 
/*       */ 
/*       */ 
/*       */ 
/*       */ 
/*       */ 
/*       */ 
/*       */ 
/*       */ 
/*       */ 
/*       */ 
/*       */ 
/*       */ 
/*       */ 
/*       */ 
/*       */ 
/*       */ 
/*       */ 
/*       */ 
/*       */ 
/*       */ 
/*       */ 
/*       */ 
/*       */ 
/*       */ 
/*       */ 
/*       */ 
/*       */ 
/*       */ 
/*       */ 
/*       */ 
/*       */ 
/*       */ 
/*       */ 
/*       */ 
/*       */ 
/*       */ 
/*       */ 
/*       */ 
/*       */ 
/*       */ 
/*       */ 
/*       */ 
/*       */ 
/*       */ 
/*       */ 
/*       */ 
/*       */ 
/*       */ 
/*       */ 
/*       */ 
/*       */ 
/*       */ 
/*       */ 
/*       */ 
/*       */ 
/*       */ 
/*       */ 
/*       */ 
/*       */ 
/*       */ 
/*       */ 
/*       */ 
/*       */ 
/*       */ 
/*       */ 
/*       */ 
/*       */ 
/*       */ 
/*       */ 
/*       */ 
/*       */ 
/*       */ 
/*       */ 
/*       */ 
/*       */ 
/*       */ 
/*       */ 
/*       */ 
/*       */ 
/*       */ 
/*       */ 
/*       */ 
/*       */ 
/*       */ 
/*       */ 
/*       */ 
/*       */ 
/*       */ 
/*       */ 
/*       */ 
/*       */ 
/*       */ 
/*       */ 
/*       */ 
/*       */ 
/*       */ 
/*       */ 
/*       */ 
/*       */ 
/*       */ 
/*       */ 
/*       */ 
/*       */ 
/*       */ 
/*       */ 
/*       */ 
/*       */ 
/*       */ 
/*       */ 
/*       */ 
/*       */ 
/*       */ 
/*       */ 
/*       */ 
/*       */ 
/*       */ 
/*       */ 
/*       */ 
/*       */ 
/*       */ 
/*       */ 
/*       */ 
/*       */ 
/*       */ 
/*       */ 
/*       */ 
/*       */ 
/*       */ 
/*       */ 
/*       */ 
/*       */ 
/*       */ 
/*       */ 
/*       */ 
/*       */ 
/*       */ 
/*       */ 
/*       */ 
/*       */ 
/*       */ 
/*       */ 
/*       */ 
/*       */ 
/*       */ 
/*       */ 
/*       */ 
/*       */ 
/*       */ 
/*       */ 
/*       */ 
/*       */ 
/*       */ 
/*       */ 
/*       */ 
/*       */ 
/*       */ 
/*       */ 
/*       */ 
/*       */ 
/*       */ 
/*       */ 
/*       */ 
/*       */ 
/*       */ 
/*       */ 
/*       */ 
/*       */ 
/*       */ 
/*       */ 
/*       */ 
/*       */ 
/*       */ 
/*       */ 
/*       */ 
/*       */ 
/*       */ 
/*       */ 
/*       */ 
/*       */ 
/*       */ 
/*       */ 
/*       */ 
/*       */ 
/*       */ 
/*       */ 
/*       */ 
/*       */ 
/*       */ 
/*       */ 
/*       */ 
/*       */ 
/*       */ 
/*       */ 
/*       */ 
/*       */ 
/*       */ 
/*       */ 
/*       */ 
/*       */ 
/*       */ 
/*       */ 
/*       */ 
/*       */ 
/*       */ 
/*       */ 
/*       */ 
/*       */ 
/*       */ 
/*       */ 
/*       */ 
/*       */ 
/*       */ 
/*       */ 
/*       */ 
/*       */ 
/*       */ 
/*       */ 
/*       */ 
/*       */ 
/*       */ 
/*       */ 
/*       */ 
/*       */ 
/*       */ 
/*       */ 
/*       */ 
/*       */ 
/*       */ 
/*       */ 
/*       */ 
/*       */ 
/*       */ 
/*       */ 
/*       */ 
/*       */ 
/*       */ 
/*       */ 
/*       */ 
/*       */ 
/*       */ 
/*       */ 
/*       */ 
/*       */ 
/*       */ 
/*       */ 
/*       */ 
/*       */ 
/*       */ 
/*       */ 
/*       */ 
/*       */ 
/*       */ 
/*       */ 
/*       */ 
/*       */ 
/*       */ 
/*       */ 
/*       */ 
/*       */ 
/*       */ 
/*       */ 
/*       */ 
/*       */ 
/*       */ 
/*       */ 
/*       */ 
/*       */ 
/*       */ 
/*       */ 
/*       */ 
/*       */ 
/*       */ 
/*       */ 
/*       */ 
/*       */ 
/*       */ 
/*       */ 
/*       */ 
/*       */ 
/*       */ 
/*       */ 
/*       */ 
/*       */ 
/*       */ 
/*       */ 
/*       */ 
/*       */ 
/*       */ 
/*       */ 
/*       */ 
/*       */ 
/*       */ 
/*       */ 
/*       */ 
/*       */ 
/*       */ 
/*       */ 
/*       */ 
/*       */ 
/*       */ 
/*       */ 
/*       */ 
/*       */ 
/*       */ 
/*       */ 
/*       */ 
/*       */ 
/*       */ 
/*       */ 
/*       */ 
/*       */ 
/*       */ 
/*       */ 
/*       */ 
/*       */ 
/*       */ 
/*       */ 
/*       */ 
/*       */ 
/*       */ 
/*       */ 
/*       */ 
/*       */ 
/*       */ 
/*       */ 
/*       */ 
/*       */ 
/*       */ 
/*       */ 
/*       */ 
/*       */ 
/*       */ 
/*       */ 
/*       */ 
/*       */ 
/*       */ 
/*       */ 
/*       */ 
/*       */ 
/*       */ 
/*       */ 
/*       */ 
/*       */ 
/*       */ 
/*       */ 
/*       */ 
/*       */ 
/*       */ 
/*       */ 
/*       */ 
/*       */ 
/*       */ 
/*       */ 
/*       */ 
/*       */ 
/*       */ 
/*       */ 
/*       */ 
/*       */ 
/*       */ 
/*       */ 
/*       */ 
/*       */ 
/*       */ 
/*       */ 
/*       */ 
/*       */ 
/*       */ 
/*       */ 
/*       */ 
/*       */ 
/*       */ 
/*       */ 
/*       */ 
/*       */ 
/*       */ 
/*       */ 
/*       */ 
/*       */ 
/*       */ 
/*       */ 
/*       */ 
/*       */ 
/*       */ 
/*       */ 
/*       */ 
/*       */ 
/*       */ 
/*       */ 
/*       */ 
/*       */ 
/*       */ 
/*       */ 
/*       */ 
/*       */ 
/*       */ 
/*       */ 
/*       */ 
/*       */ 
/*       */ 
/*       */ 
/*       */ 
/*       */ 
/*       */ 
/*       */ 
/*       */ 
/*       */ 
/*       */ 
/*       */ 
/*       */ 
/*       */ 
/*       */ 
/*       */ 
/*       */ 
/*       */ 
/*       */ 
/*       */ 
/*       */ 
/*       */ 
/*       */ 
/*       */ 
/*       */ 
/*       */ 
/*       */ 
/*       */ 
/*       */ 
/*       */ 
/*       */ 
/*       */ 
/*       */ 
/*       */ 
/*       */ 
/*       */ 
/*       */ 
/*       */ 
/*       */ 
/*       */ 
/*       */ 
/*       */ 
/*       */ 
/*       */ 
/*       */ 
/*       */ 
/*       */ 
/*       */ 
/*       */ 
/*       */ 
/*       */ 
/*       */ 
/*       */ 
/*       */ 
/*       */ 
/*       */ 
/*       */ 
/*       */ 
/*       */ 
/*       */ 
/*       */ 
/*       */ 
/*       */ 
/*       */ 
/*       */ 
/*       */ 
/*       */ 
/*       */ 
/*       */ 
/*       */ 
/*       */ 
/*       */ 
/*       */ 
/*       */ 
/*       */ 
/*       */ 
/*       */ 
/*       */ 
/*       */ 
/*       */ 
/*       */ 
/*       */ 
/*       */ 
/*       */ 
/*       */ 
/*       */ 
/*       */ 
/*       */ 
/*       */ 
/*       */ 
/*       */ 
/*       */ 
/*       */ 
/*       */ 
/*       */ 
/*       */ 
/*       */ 
/*       */ 
/*       */ 
/*       */ 
/*       */ 
/*       */ 
/*       */ 
/*       */ 
/*       */ 
/*       */ 
/*       */ 
/*       */ 
/*       */ 
/*       */ 
/*       */ 
/*       */ 
/*       */ 
/*       */ 
/*       */ 
/*       */ 
/*       */ 
/*       */ 
/*       */ 
/*       */ 
/*       */ 
/*       */ 
/*       */ 
/*       */ 
/*       */ 
/*       */ 
/*       */ 
/*       */ 
/*       */ 
/*       */ 
/*       */ 
/*       */ 
/*       */ 
/*       */ 
/*       */ 
/*       */ 
/*       */ 
/*       */ 
/*       */ 
/*       */ 
/*       */ 
/*       */ 
/*       */ 
/*       */ 
/*       */ 
/*       */ 
/*       */ 
/*       */ 
/*       */ 
/*       */ 
/*       */ 
/*       */ 
/*       */ 
/*       */ 
/*       */ 
/*       */ 
/*       */ 
/*       */ 
/*       */ 
/*       */ 
/*       */ 
/*       */ 
/*       */ 
/*       */ 
/*       */ 
/*       */ 
/*       */ 
/*       */ 
/*       */ 
/*       */ 
/*       */ 
/*       */ 
/*       */ 
/*       */ 
/*       */ 
/*       */ 
/*       */ 
/*       */ 
/*       */ 
/*       */ 
/*       */ 
/*       */ 
/*       */ 
/*       */ 
/*       */ 
/*       */ 
/*       */ 
/*       */ 
/*       */ 
/*       */ 
/*       */ 
/*       */ 
/*       */ 
/*       */ 
/*       */ 
/*       */ 
/*       */ 
/*       */ 
/*       */ 
/*       */ 
/*       */ 
/*       */ 
/*       */ 
/*       */ 
/*       */ 
/*       */ 
/*       */ 
/*       */ 
/*       */ 
/*       */ 
/*       */ 
/*       */ 
/*       */ 
/*       */ 
/*       */ 
/*       */ 
/*       */ 
/*       */ 
/*       */ 
/*       */ 
/*       */ 
/*       */ 
/*       */ 
/*       */ 
/*       */ 
/*       */ 
/*       */ 
/*       */ 
/*       */ 
/*       */ 
/*       */ 
/*       */ 
/*       */ 
/*       */ 
/*       */ 
/*       */ 
/*       */ 
/*       */ 
/*       */ 
/*       */ 
/*       */ 
/*       */ 
/*       */ 
/*       */ 
/*       */ 
/*       */ 
/*       */ 
/*       */ 
/*       */ 
/*       */ 
/*       */ 
/*       */ 
/*       */ 
/*       */ 
/*       */ 
/*       */ 
/*       */ 
/*       */ 
/*       */ 
/*       */ 
/*       */ 
/*       */ 
/*       */ 
/*       */ 
/*       */ 
/*       */ 
/*       */ 
/*       */ 
/*       */ 
/*       */ 
/*       */ 
/*       */ 
/*       */ 
/*       */ 
/*       */ 
/*       */ 
/*       */ 
/*       */ 
/*       */ 
/*       */ 
/*       */ 
/*       */ 
/*       */ 
/*       */ 
/*       */ 
/*       */ 
/*       */ 
/*       */ 
/*       */ 
/*       */ 
/*       */ 
/*       */ 
/*       */ 
/*       */ 
/*       */ 
/*       */ 
/*       */ 
/*       */ 
/*       */ 
/*       */ 
/*       */ 
/*       */ 
/*       */ 
/*       */ 
/*       */ 
/*       */ 
/*       */ 
/*       */ 
/*       */ 
/*       */ 
/*       */ 
/*       */ 
/*       */ 
/*       */ 
/*       */ 
/*       */ 
/*       */ 
/*       */ 
/*       */ 
/*       */ 
/*       */ 
/*       */ 
/*       */ 
/*       */ 
/*       */ 
/*       */ 
/*       */ 
/*       */ 
/*       */ 
/*       */ 
/*       */ 
/*       */ 
/*       */ 
/*       */ 
/*       */ 
/*       */ 
/*       */ 
/*       */ 
/*       */ 
/*       */ 
/*       */ 
/*       */ 
/*       */ 
/*       */ 
/*       */ 
/*       */ 
/*       */ 
/*       */ 
/*       */ 
/*       */ 
/*       */ 
/*       */ 
/*       */ 
/*       */ 
/*       */ 
/*       */ 
/*       */ 
/*       */ 
/*       */ 
/*       */ 
/*       */ 
/*       */ 
/*       */ 
/*       */ 
/*       */ 
/*       */ 
/*       */ 
/*       */ 
/*       */ 
/*       */ 
/*       */ 
/*       */ 
/*       */ 
/*       */ 
/*       */ 
/*       */ 
/*       */ 
/*       */ 
/*       */ 
/*       */ 
/*       */ 
/*       */ 
/*       */ 
/*       */ 
/*       */ 
/*       */ 
/*       */ 
/*       */ 
/*       */ 
/*       */ 
/*       */ 
/*       */ 
/*       */ 
/*       */ 
/*       */ 
/*       */ 
/*       */ 
/*       */ 
/*       */ 
/*       */ 
/*       */ 
/*       */ 
/*       */ 
/*       */ 
/*       */ 
/*       */ 
/*       */ 
/*       */ 
/*       */ 
/*       */ 
/*       */ 
/*       */ 
/*       */ 
/*       */ 
/*       */ 
/*       */ 
/*       */ 
/*       */ 
/*       */ 
/*       */ 
/*       */ 
/*       */ 
/*       */ 
/*       */ 
/*       */ 
/*       */ 
/*       */ 
/*       */ 
/*       */ 
/*       */ 
/*       */ 
/*       */ 
/*       */ 
/*       */ 
/*       */ 
/*       */ 
/*       */ 
/*       */ 
/*       */ 
/*       */ 
/*       */ 
/*       */ 
/*       */ 
/*       */ 
/*       */ 
/*       */ 
/*       */ 
/*       */ 
/*       */ 
/*       */ 
/*       */ 
/*       */ 
/*       */ 
/*       */ 
/*       */ 
/*       */ 
/*       */ 
/*       */ 
/*       */ 
/*       */ 
/*       */ 
/*       */ 
/*       */ 
/*       */ 
/*       */ 
/*       */ 
/*       */ 
/*       */ 
/*       */ 
/*       */ 
/*       */ 
/*       */ 
/*       */ 
/*       */         
/*  7148 */         .mC == g.a.mE), "The given elementOrder (%s) is unsupported. incidentEdgeOrder() only supports ElementOrder.unordered() and ElementOrder.stable().", g);
/*       */ 
/*       */ 
/*       */ 
/*       */ 
/*       */ 
/*       */ 
/*       */ 
/*       */ 
/*       */ 
/*       */ 
/*       */ 
/*       */ 
/*       */ 
/*       */ 
/*       */ 
/*       */ 
/*       */ 
/*       */ 
/*       */ 
/*       */ 
/*       */ 
/*       */ 
/*       */ 
/*       */ 
/*       */ 
/*       */ 
/*       */ 
/*       */ 
/*       */ 
/*       */ 
/*       */ 
/*       */ 
/*       */ 
/*       */ 
/*       */ 
/*       */ 
/*       */ 
/*       */ 
/*       */ 
/*       */ 
/*       */ 
/*       */ 
/*       */ 
/*       */ 
/*       */ 
/*       */ 
/*       */ 
/*       */ 
/*       */ 
/*       */ 
/*       */ 
/*       */ 
/*       */ 
/*       */ 
/*       */ 
/*       */ 
/*       */ 
/*       */ 
/*       */ 
/*       */ 
/*       */ 
/*       */ 
/*       */ 
/*       */ 
/*       */ 
/*       */ 
/*       */ 
/*       */ 
/*       */ 
/*       */ 
/*       */ 
/*       */ 
/*       */ 
/*       */ 
/*       */ 
/*       */ 
/*       */ 
/*       */ 
/*       */ 
/*       */ 
/*       */ 
/*       */ 
/*       */ 
/*       */ 
/*       */ 
/*       */ 
/*       */ 
/*       */ 
/*       */ 
/*       */ 
/*       */ 
/*       */ 
/*       */ 
/*       */ 
/*       */ 
/*       */ 
/*       */ 
/*       */ 
/*       */ 
/*       */ 
/*       */ 
/*       */ 
/*       */ 
/*       */ 
/*       */ 
/*       */ 
/*       */ 
/*       */ 
/*       */ 
/*       */ 
/*       */ 
/*       */ 
/*       */ 
/*       */ 
/*       */ 
/*       */ 
/*       */ 
/*       */ 
/*       */ 
/*       */ 
/*       */ 
/*       */ 
/*       */ 
/*       */ 
/*       */ 
/*       */ 
/*       */ 
/*       */ 
/*       */ 
/*       */ 
/*       */ 
/*       */ 
/*       */ 
/*       */ 
/*       */ 
/*       */ 
/*       */ 
/*       */ 
/*       */ 
/*       */ 
/*       */ 
/*       */ 
/*       */ 
/*       */ 
/*       */ 
/*       */ 
/*       */ 
/*       */ 
/*       */ 
/*       */ 
/*       */ 
/*       */ 
/*       */ 
/*       */ 
/*       */ 
/*       */ 
/*       */ 
/*       */ 
/*       */ 
/*       */ 
/*       */ 
/*       */ 
/*       */ 
/*       */ 
/*       */ 
/*       */ 
/*       */ 
/*       */ 
/*       */ 
/*       */ 
/*       */ 
/*       */ 
/*       */ 
/*       */ 
/*       */ 
/*       */ 
/*       */ 
/*       */ 
/*       */ 
/*       */ 
/*       */ 
/*       */ 
/*       */ 
/*       */ 
/*       */ 
/*       */ 
/*       */ 
/*       */ 
/*       */ 
/*       */ 
/*       */ 
/*       */ 
/*       */ 
/*       */ 
/*       */ 
/*       */ 
/*       */ 
/*       */ 
/*       */ 
/*       */ 
/*       */ 
/*       */ 
/*       */ 
/*       */ 
/*       */ 
/*       */ 
/*       */ 
/*       */ 
/*       */ 
/*       */ 
/*       */ 
/*       */ 
/*       */ 
/*       */ 
/*       */ 
/*       */ 
/*       */ 
/*       */ 
/*       */ 
/*       */ 
/*       */ 
/*       */ 
/*       */ 
/*       */ 
/*       */ 
/*       */ 
/*       */ 
/*       */ 
/*       */ 
/*       */ 
/*       */ 
/*       */ 
/*       */ 
/*       */ 
/*       */ 
/*       */ 
/*       */ 
/*       */ 
/*       */ 
/*       */ 
/*       */ 
/*       */ 
/*       */ 
/*       */ 
/*       */     
/*       */     (l3 = l2).mn = (g)g.f(g);
/*       */ 
/*       */ 
/*       */ 
/*       */ 
/*       */ 
/*       */ 
/*       */ 
/*       */ 
/*       */ 
/*       */ 
/*       */ 
/*       */ 
/*       */ 
/*       */ 
/*       */ 
/*       */ 
/*       */ 
/*       */ 
/*       */ 
/*       */ 
/*       */ 
/*       */ 
/*       */ 
/*       */ 
/*       */ 
/*       */ 
/*       */ 
/*       */ 
/*       */ 
/*       */ 
/*       */ 
/*       */ 
/*       */ 
/*       */ 
/*       */ 
/*       */ 
/*       */ 
/*       */ 
/*       */ 
/*       */ 
/*       */ 
/*       */ 
/*       */ 
/*       */ 
/*       */ 
/*       */ 
/*       */ 
/*       */ 
/*       */ 
/*       */ 
/*       */ 
/*       */ 
/*       */ 
/*       */ 
/*       */ 
/*       */ 
/*       */ 
/*       */ 
/*       */ 
/*       */ 
/*       */ 
/*       */ 
/*       */ 
/*       */ 
/*       */ 
/*       */ 
/*       */ 
/*       */ 
/*       */ 
/*       */ 
/*       */ 
/*       */ 
/*       */ 
/*       */ 
/*       */ 
/*       */ 
/*       */ 
/*       */ 
/*       */ 
/*       */ 
/*       */ 
/*       */ 
/*       */ 
/*       */ 
/*       */ 
/*       */ 
/*       */ 
/*       */ 
/*       */ 
/*       */ 
/*       */ 
/*       */ 
/*       */ 
/*       */ 
/*       */ 
/*       */ 
/*       */ 
/*       */ 
/*       */ 
/*       */ 
/*       */ 
/*       */ 
/*       */ 
/*       */ 
/*       */ 
/*       */ 
/*       */ 
/*       */ 
/*       */ 
/*       */ 
/*       */ 
/*       */ 
/*       */ 
/*       */ 
/*       */ 
/*       */ 
/*       */ 
/*       */ 
/*       */ 
/*       */ 
/*       */ 
/*       */ 
/*       */ 
/*       */ 
/*       */ 
/*       */ 
/*       */ 
/*       */ 
/*       */ 
/*       */ 
/*       */ 
/*       */ 
/*       */ 
/*       */ 
/*       */ 
/*       */ 
/*       */ 
/*       */ 
/*       */ 
/*       */ 
/*       */ 
/*       */ 
/*       */ 
/*       */ 
/*       */ 
/*       */ 
/*       */ 
/*       */ 
/*       */ 
/*       */ 
/*       */ 
/*       */ 
/*       */ 
/*       */ 
/*       */ 
/*       */ 
/*       */ 
/*       */ 
/*       */ 
/*       */ 
/*       */ 
/*       */ 
/*       */ 
/*       */ 
/*       */ 
/*       */ 
/*       */ 
/*       */ 
/*       */ 
/*       */ 
/*       */ 
/*       */ 
/*       */ 
/*       */ 
/*       */ 
/*       */ 
/*       */ 
/*       */ 
/*       */ 
/*       */ 
/*       */ 
/*       */ 
/*       */ 
/*       */ 
/*       */ 
/*       */ 
/*       */ 
/*       */ 
/*       */ 
/*       */ 
/*       */ 
/*       */ 
/*       */ 
/*       */ 
/*       */ 
/*       */ 
/*       */ 
/*       */ 
/*       */ 
/*       */ 
/*       */ 
/*       */ 
/*       */ 
/*       */ 
/*       */ 
/*       */ 
/*       */ 
/*       */ 
/*       */ 
/*       */ 
/*       */ 
/*       */ 
/*       */ 
/*       */ 
/*       */ 
/*       */ 
/*       */ 
/*       */ 
/*       */ 
/*       */ 
/*       */ 
/*       */ 
/*       */ 
/*       */ 
/*       */ 
/*       */ 
/*       */ 
/*       */ 
/*       */ 
/*       */ 
/*       */ 
/*       */ 
/*       */ 
/*       */ 
/*       */ 
/*       */ 
/*       */ 
/*       */ 
/*       */ 
/*       */ 
/*       */ 
/*       */ 
/*       */ 
/*       */ 
/*       */     
/*       */     int i = k1.dG().size();
/*       */ 
/*       */ 
/*       */ 
/*       */ 
/*       */ 
/*       */ 
/*       */ 
/*       */ 
/*       */ 
/*       */ 
/*       */ 
/*       */ 
/*       */ 
/*       */ 
/*       */ 
/*       */ 
/*       */ 
/*       */ 
/*       */ 
/*       */ 
/*       */ 
/*       */ 
/*       */ 
/*       */ 
/*       */ 
/*       */ 
/*       */ 
/*       */ 
/*       */ 
/*       */ 
/*       */ 
/*       */ 
/*       */ 
/*       */ 
/*       */ 
/*       */ 
/*       */ 
/*       */ 
/*       */ 
/*       */ 
/*       */ 
/*       */ 
/*       */ 
/*       */ 
/*       */ 
/*       */ 
/*       */ 
/*       */ 
/*       */ 
/*       */ 
/*       */ 
/*       */ 
/*       */ 
/*       */ 
/*       */ 
/*       */ 
/*       */ 
/*       */ 
/*       */ 
/*       */ 
/*       */ 
/*       */ 
/*       */ 
/*       */ 
/*       */ 
/*       */ 
/*       */ 
/*       */ 
/*       */ 
/*       */ 
/*       */ 
/*       */ 
/*       */ 
/*       */ 
/*       */ 
/*       */ 
/*       */ 
/*       */ 
/*       */ 
/*       */ 
/*       */ 
/*       */ 
/*       */ 
/*       */ 
/*       */ 
/*       */ 
/*       */ 
/*       */ 
/*       */ 
/*       */ 
/*       */ 
/*       */ 
/*       */ 
/*       */ 
/*       */ 
/*       */ 
/*       */ 
/*       */ 
/*       */ 
/*       */ 
/*       */ 
/*       */ 
/*       */ 
/*       */ 
/*       */ 
/*       */ 
/*       */ 
/*       */ 
/*       */ 
/*       */ 
/*       */ 
/*       */ 
/*       */ 
/*       */ 
/*       */ 
/*       */ 
/*       */ 
/*       */ 
/*       */ 
/*       */ 
/*       */ 
/*       */ 
/*       */ 
/*       */ 
/*       */ 
/*       */ 
/*       */ 
/*       */ 
/*       */ 
/*       */ 
/*       */ 
/*       */ 
/*       */ 
/*       */ 
/*       */ 
/*       */ 
/*       */ 
/*       */ 
/*       */ 
/*       */ 
/*       */ 
/*       */ 
/*       */ 
/*       */ 
/*       */ 
/*       */ 
/*       */ 
/*       */ 
/*       */ 
/*       */ 
/*       */ 
/*       */ 
/*       */ 
/*       */ 
/*       */ 
/*       */ 
/*       */ 
/*       */ 
/*       */ 
/*       */ 
/*       */ 
/*       */ 
/*       */ 
/*       */ 
/*       */ 
/*       */ 
/*       */ 
/*       */ 
/*       */ 
/*       */ 
/*       */ 
/*       */ 
/*       */ 
/*       */ 
/*       */ 
/*       */ 
/*       */ 
/*       */ 
/*       */ 
/*       */ 
/*       */ 
/*       */ 
/*       */ 
/*       */ 
/*       */ 
/*       */ 
/*       */ 
/*       */ 
/*       */ 
/*       */ 
/*       */ 
/*       */ 
/*       */ 
/*       */ 
/*       */ 
/*       */ 
/*       */ 
/*       */ 
/*       */ 
/*       */ 
/*       */ 
/*       */ 
/*       */ 
/*       */ 
/*       */ 
/*       */ 
/*       */ 
/*       */ 
/*       */ 
/*       */ 
/*       */ 
/*       */ 
/*       */ 
/*       */ 
/*       */ 
/*       */ 
/*       */ 
/*       */ 
/*       */ 
/*       */ 
/*       */ 
/*       */ 
/*       */ 
/*       */ 
/*       */ 
/*       */ 
/*       */ 
/*       */ 
/*       */ 
/*       */ 
/*       */ 
/*       */ 
/*       */ 
/*       */ 
/*       */ 
/*       */ 
/*       */ 
/*       */ 
/*       */ 
/*       */ 
/*       */ 
/*       */ 
/*       */ 
/*       */ 
/*       */     
/*       */     l l1;
/*       */ 
/*       */ 
/*       */ 
/*       */ 
/*       */ 
/*       */ 
/*       */ 
/*       */ 
/*       */ 
/*       */ 
/*       */ 
/*       */ 
/*       */ 
/*       */ 
/*       */ 
/*       */ 
/*       */ 
/*       */ 
/*       */ 
/*       */ 
/*       */ 
/*       */ 
/*       */ 
/*       */ 
/*       */ 
/*       */ 
/*       */ 
/*       */ 
/*       */ 
/*       */ 
/*       */ 
/*       */ 
/*       */ 
/*       */ 
/*       */ 
/*       */ 
/*       */ 
/*       */ 
/*       */ 
/*       */ 
/*       */ 
/*       */ 
/*       */ 
/*       */ 
/*       */ 
/*       */ 
/*       */ 
/*       */ 
/*       */ 
/*       */ 
/*       */ 
/*       */ 
/*       */ 
/*       */ 
/*       */ 
/*       */ 
/*       */ 
/*       */ 
/*       */ 
/*       */ 
/*       */ 
/*       */ 
/*       */ 
/*       */ 
/*       */ 
/*       */ 
/*       */ 
/*       */ 
/*       */ 
/*       */ 
/*       */ 
/*       */ 
/*       */ 
/*       */ 
/*       */ 
/*       */ 
/*       */ 
/*       */ 
/*       */ 
/*       */ 
/*       */ 
/*       */ 
/*       */ 
/*       */ 
/*       */ 
/*       */ 
/*       */ 
/*       */ 
/*       */ 
/*       */ 
/*       */ 
/*       */ 
/*       */ 
/*       */ 
/*       */ 
/*       */ 
/*       */ 
/*       */ 
/*       */ 
/*       */ 
/*       */ 
/*       */ 
/*       */ 
/*       */ 
/*       */ 
/*       */ 
/*       */ 
/*       */ 
/*       */ 
/*       */ 
/*       */ 
/*       */ 
/*       */ 
/*       */ 
/*       */ 
/*       */ 
/*       */ 
/*       */ 
/*       */ 
/*       */ 
/*       */ 
/*       */ 
/*       */ 
/*       */ 
/*       */ 
/*       */ 
/*       */ 
/*       */ 
/*       */ 
/*       */ 
/*       */ 
/*       */ 
/*       */ 
/*       */ 
/*       */ 
/*       */ 
/*       */ 
/*       */ 
/*       */ 
/*       */ 
/*       */ 
/*       */ 
/*       */ 
/*       */ 
/*       */ 
/*       */ 
/*       */ 
/*       */ 
/*       */ 
/*       */ 
/*       */ 
/*       */ 
/*       */ 
/*       */ 
/*       */ 
/*       */ 
/*       */ 
/*       */ 
/*       */ 
/*       */ 
/*       */ 
/*       */ 
/*       */ 
/*       */ 
/*       */ 
/*       */ 
/*       */ 
/*       */ 
/*       */ 
/*       */ 
/*       */ 
/*       */ 
/*       */ 
/*       */ 
/*       */ 
/*       */ 
/*       */ 
/*       */ 
/*       */ 
/*       */ 
/*       */ 
/*       */ 
/*       */ 
/*       */ 
/*       */ 
/*       */ 
/*       */ 
/*       */ 
/*       */ 
/*       */ 
/*       */ 
/*       */ 
/*       */ 
/*       */ 
/*       */ 
/*       */ 
/*       */ 
/*       */ 
/*       */ 
/*       */ 
/*       */ 
/*       */ 
/*       */ 
/*       */ 
/*       */ 
/*       */ 
/*       */ 
/*       */ 
/*       */ 
/*       */ 
/*       */ 
/*       */ 
/*       */ 
/*       */ 
/*       */ 
/*       */ 
/*       */ 
/*       */ 
/*       */ 
/*       */ 
/*       */ 
/*       */ 
/*       */ 
/*       */ 
/*       */ 
/*       */ 
/*       */ 
/*       */ 
/*       */ 
/*       */ 
/*       */ 
/*       */ 
/*       */ 
/*       */ 
/*       */ 
/*       */ 
/*       */ 
/*       */ 
/*       */ 
/*       */ 
/*       */ 
/*       */ 
/*       */ 
/*       */ 
/*       */     
/*  8132 */     (l1 = l3).mo = h.h(Integer.valueOf(o.aZ(i)));
/*  8133 */     q<T> q1 = l1.dT();
/*       */ 
/*       */ 
/*       */ 
/*       */ 
/*       */ 
/*       */ 
/*       */ 
/*       */ 
/*       */ 
/*       */ 
/*       */ 
/*       */ 
/*       */ 
/*       */ 
/*       */ 
/*       */ 
/*       */ 
/*       */ 
/*       */ 
/*       */ 
/*       */ 
/*       */ 
/*       */ 
/*       */ 
/*       */ 
/*       */ 
/*       */ 
/*       */ 
/*       */ 
/*       */ 
/*       */ 
/*       */ 
/*       */ 
/*       */ 
/*       */ 
/*       */ 
/*       */ 
/*       */ 
/*       */ 
/*       */ 
/*       */ 
/*       */ 
/*       */ 
/*       */ 
/*       */ 
/*       */ 
/*       */ 
/*       */ 
/*       */ 
/*       */ 
/*       */ 
/*       */ 
/*       */ 
/*       */ 
/*       */ 
/*       */ 
/*       */ 
/*       */ 
/*       */ 
/*       */ 
/*       */ 
/*       */ 
/*       */ 
/*       */ 
/*       */ 
/*       */ 
/*       */ 
/*       */ 
/*       */ 
/*       */ 
/*       */ 
/*       */ 
/*       */ 
/*       */ 
/*       */ 
/*       */ 
/*       */ 
/*       */ 
/*       */ 
/*       */ 
/*       */ 
/*       */ 
/*       */ 
/*       */ 
/*       */ 
/*       */ 
/*       */ 
/*       */ 
/*       */ 
/*       */ 
/*       */ 
/*       */ 
/*       */ 
/*       */ 
/*       */ 
/*       */ 
/*       */ 
/*       */ 
/*       */ 
/*       */ 
/*       */ 
/*       */ 
/*       */ 
/*       */ 
/*       */ 
/*       */ 
/*       */ 
/*       */ 
/*       */ 
/*       */ 
/*       */ 
/*       */ 
/*       */ 
/*       */ 
/*       */ 
/*       */ 
/*       */ 
/*       */ 
/*       */ 
/*       */ 
/*       */ 
/*       */ 
/*       */ 
/*       */ 
/*       */ 
/*       */ 
/*       */ 
/*       */ 
/*       */ 
/*       */ 
/*       */ 
/*       */ 
/*       */ 
/*       */ 
/*       */ 
/*       */ 
/*       */ 
/*       */ 
/*       */ 
/*       */ 
/*       */ 
/*       */ 
/*       */ 
/*       */ 
/*       */ 
/*       */ 
/*       */ 
/*       */ 
/*       */ 
/*       */ 
/*       */ 
/*       */ 
/*       */ 
/*       */ 
/*       */ 
/*       */ 
/*       */ 
/*       */ 
/*       */ 
/*       */ 
/*       */ 
/*       */ 
/*       */ 
/*       */ 
/*       */ 
/*       */ 
/*       */ 
/*       */ 
/*       */ 
/*       */ 
/*       */ 
/*       */ 
/*       */ 
/*       */ 
/*       */ 
/*       */ 
/*       */ 
/*       */ 
/*       */ 
/*       */ 
/*       */ 
/*       */ 
/*       */ 
/*       */ 
/*       */ 
/*       */ 
/*       */ 
/*       */ 
/*       */ 
/*       */ 
/*       */ 
/*       */ 
/*       */ 
/*       */ 
/*       */ 
/*       */ 
/*       */ 
/*       */ 
/*       */ 
/*       */ 
/*       */ 
/*       */ 
/*       */ 
/*       */ 
/*       */ 
/*       */ 
/*       */ 
/*       */ 
/*       */ 
/*       */ 
/*       */ 
/*       */ 
/*       */ 
/*       */ 
/*       */ 
/*       */ 
/*       */ 
/*       */ 
/*       */ 
/*       */ 
/*       */ 
/*       */ 
/*       */ 
/*       */ 
/*       */ 
/*       */ 
/*       */ 
/*       */ 
/*       */ 
/*       */ 
/*       */ 
/*       */ 
/*       */ 
/*       */ 
/*       */ 
/*       */ 
/*       */ 
/*       */ 
/*       */ 
/*       */ 
/*       */ 
/*       */ 
/*       */ 
/*       */ 
/*       */ 
/*       */ 
/*       */ 
/*       */ 
/*       */ 
/*       */ 
/*       */ 
/*       */ 
/*       */ 
/*       */ 
/*       */ 
/*       */ 
/*       */ 
/*       */ 
/*       */ 
/*       */ 
/*       */ 
/*       */ 
/*       */ 
/*       */ 
/*       */ 
/*       */ 
/*       */ 
/*       */ 
/*       */ 
/*       */ 
/*       */ 
/*       */ 
/*       */ 
/*       */ 
/*       */ 
/*       */ 
/*       */ 
/*       */ 
/*       */ 
/*       */ 
/*       */ 
/*       */ 
/*       */ 
/*       */ 
/*       */ 
/*       */ 
/*       */ 
/*       */ 
/*       */ 
/*       */ 
/*       */ 
/*       */ 
/*       */ 
/*       */ 
/*       */ 
/*       */ 
/*       */ 
/*       */ 
/*       */ 
/*       */ 
/*       */ 
/*       */ 
/*       */ 
/*       */ 
/*       */ 
/*       */ 
/*       */ 
/*       */ 
/*       */ 
/*       */ 
/*       */ 
/*       */ 
/*       */ 
/*       */ 
/*       */ 
/*       */ 
/*       */ 
/*       */ 
/*       */ 
/*       */ 
/*       */ 
/*       */ 
/*       */ 
/*       */ 
/*       */ 
/*       */ 
/*       */ 
/*       */ 
/*       */ 
/*       */ 
/*       */ 
/*       */ 
/*       */ 
/*       */ 
/*       */ 
/*       */ 
/*       */ 
/*       */ 
/*       */ 
/*       */ 
/*       */ 
/*       */ 
/*       */ 
/*       */ 
/*       */ 
/*       */ 
/*       */ 
/*       */ 
/*       */ 
/*       */ 
/*       */ 
/*       */ 
/*       */ 
/*       */ 
/*       */ 
/*       */ 
/*       */ 
/*       */ 
/*       */ 
/*       */ 
/*       */ 
/*       */ 
/*       */ 
/*       */ 
/*       */ 
/*       */ 
/*       */ 
/*       */ 
/*       */ 
/*       */ 
/*       */ 
/*       */ 
/*       */ 
/*       */ 
/*       */ 
/*       */ 
/*       */ 
/*       */ 
/*       */ 
/*       */ 
/*       */ 
/*       */ 
/*       */ 
/*       */ 
/*       */ 
/*       */ 
/*       */ 
/*       */ 
/*       */ 
/*       */ 
/*       */ 
/*       */ 
/*       */ 
/*       */ 
/*       */ 
/*       */ 
/*       */ 
/*       */ 
/*       */ 
/*       */ 
/*       */ 
/*       */ 
/*       */ 
/*       */ 
/*       */ 
/*       */ 
/*       */ 
/*       */ 
/*       */ 
/*       */ 
/*       */ 
/*       */ 
/*       */ 
/*       */ 
/*       */ 
/*       */ 
/*       */ 
/*       */ 
/*       */ 
/*       */ 
/*       */ 
/*       */ 
/*       */ 
/*       */ 
/*       */ 
/*       */ 
/*       */ 
/*       */ 
/*       */ 
/*       */ 
/*       */ 
/*       */ 
/*       */ 
/*       */ 
/*       */ 
/*       */ 
/*       */ 
/*       */ 
/*       */ 
/*       */ 
/*       */ 
/*       */ 
/*       */ 
/*       */ 
/*       */ 
/*       */ 
/*       */ 
/*       */ 
/*       */ 
/*       */ 
/*       */ 
/*       */ 
/*       */ 
/*       */ 
/*       */ 
/*       */ 
/*       */ 
/*       */ 
/*       */ 
/*       */ 
/*       */ 
/*       */ 
/*       */ 
/*       */ 
/*       */ 
/*       */ 
/*       */ 
/*       */ 
/*       */ 
/*       */ 
/*       */ 
/*       */ 
/*       */ 
/*       */ 
/*       */ 
/*       */ 
/*       */     
/*       */     for (Object object : k1.dG()) {
/*       */       q1.K(object);
/*       */     }
/*       */ 
/*       */ 
/*       */ 
/*       */ 
/*       */ 
/*       */ 
/*       */ 
/*       */ 
/*       */ 
/*       */ 
/*       */ 
/*       */ 
/*       */ 
/*       */ 
/*       */ 
/*       */ 
/*       */ 
/*       */ 
/*       */ 
/*       */ 
/*       */ 
/*       */ 
/*       */ 
/*       */ 
/*       */ 
/*       */ 
/*       */ 
/*       */ 
/*       */ 
/*       */ 
/*       */ 
/*       */ 
/*       */ 
/*       */ 
/*       */ 
/*       */ 
/*       */ 
/*       */ 
/*       */ 
/*       */ 
/*       */ 
/*       */ 
/*       */ 
/*       */ 
/*       */ 
/*       */ 
/*       */ 
/*       */ 
/*       */ 
/*       */ 
/*       */ 
/*       */ 
/*       */ 
/*       */ 
/*       */ 
/*       */ 
/*       */ 
/*       */ 
/*       */ 
/*       */ 
/*       */ 
/*       */ 
/*       */ 
/*       */ 
/*       */ 
/*       */ 
/*       */ 
/*       */ 
/*       */ 
/*       */ 
/*       */ 
/*       */ 
/*       */ 
/*       */ 
/*       */ 
/*       */ 
/*       */ 
/*       */ 
/*       */ 
/*       */ 
/*       */ 
/*       */ 
/*       */ 
/*       */ 
/*       */ 
/*       */ 
/*       */ 
/*       */ 
/*       */ 
/*       */ 
/*       */ 
/*       */ 
/*       */ 
/*       */ 
/*       */ 
/*       */ 
/*       */ 
/*       */ 
/*       */ 
/*       */ 
/*       */ 
/*       */ 
/*       */ 
/*       */ 
/*       */ 
/*       */ 
/*       */ 
/*       */ 
/*       */ 
/*       */ 
/*       */ 
/*       */ 
/*       */ 
/*       */ 
/*       */ 
/*       */ 
/*       */ 
/*       */ 
/*       */ 
/*       */ 
/*       */ 
/*       */ 
/*       */ 
/*       */ 
/*       */ 
/*       */ 
/*       */ 
/*       */ 
/*       */ 
/*       */ 
/*       */ 
/*       */ 
/*       */ 
/*       */ 
/*       */ 
/*       */ 
/*       */ 
/*       */ 
/*       */ 
/*       */ 
/*       */ 
/*       */ 
/*       */ 
/*       */ 
/*       */ 
/*       */ 
/*       */ 
/*       */ 
/*       */ 
/*       */ 
/*       */ 
/*       */ 
/*       */ 
/*       */ 
/*       */ 
/*       */ 
/*       */ 
/*       */ 
/*       */ 
/*       */ 
/*       */ 
/*       */ 
/*       */ 
/*       */ 
/*       */ 
/*       */ 
/*       */ 
/*       */ 
/*       */ 
/*       */ 
/*       */ 
/*       */ 
/*       */ 
/*       */ 
/*       */ 
/*       */ 
/*       */ 
/*       */ 
/*       */ 
/*       */ 
/*       */ 
/*       */ 
/*       */ 
/*       */ 
/*       */ 
/*       */ 
/*       */ 
/*       */ 
/*       */ 
/*       */ 
/*       */ 
/*       */ 
/*       */ 
/*       */ 
/*       */ 
/*       */ 
/*       */ 
/*       */ 
/*       */ 
/*       */ 
/*       */ 
/*       */ 
/*       */ 
/*       */ 
/*       */ 
/*       */ 
/*       */ 
/*       */ 
/*       */ 
/*       */ 
/*       */ 
/*       */ 
/*       */ 
/*       */ 
/*       */ 
/*       */ 
/*       */ 
/*       */ 
/*       */ 
/*       */ 
/*       */ 
/*       */ 
/*       */ 
/*       */ 
/*       */ 
/*       */ 
/*       */ 
/*       */ 
/*       */ 
/*       */ 
/*       */ 
/*       */ 
/*       */ 
/*       */ 
/*       */ 
/*       */ 
/*       */ 
/*       */ 
/*       */ 
/*       */ 
/*       */ 
/*       */ 
/*       */ 
/*       */ 
/*       */ 
/*       */ 
/*       */ 
/*       */ 
/*       */ 
/*       */ 
/*       */ 
/*       */ 
/*       */ 
/*       */ 
/*       */ 
/*       */ 
/*       */ 
/*       */ 
/*       */ 
/*       */ 
/*       */ 
/*       */ 
/*       */ 
/*       */ 
/*       */ 
/*       */ 
/*       */ 
/*       */ 
/*       */ 
/*       */ 
/*       */ 
/*       */ 
/*       */ 
/*       */ 
/*       */ 
/*       */ 
/*       */ 
/*       */ 
/*       */ 
/*       */ 
/*       */ 
/*       */ 
/*       */ 
/*       */ 
/*       */ 
/*       */ 
/*       */ 
/*       */ 
/*       */ 
/*       */ 
/*       */ 
/*       */ 
/*       */ 
/*       */ 
/*       */ 
/*       */ 
/*       */ 
/*       */ 
/*       */ 
/*       */ 
/*       */ 
/*       */ 
/*       */ 
/*       */ 
/*       */ 
/*       */ 
/*       */ 
/*       */ 
/*       */ 
/*       */ 
/*       */ 
/*       */ 
/*       */ 
/*       */ 
/*       */ 
/*       */ 
/*       */ 
/*       */ 
/*       */ 
/*       */ 
/*       */ 
/*       */ 
/*       */ 
/*       */ 
/*       */ 
/*       */ 
/*       */ 
/*       */ 
/*       */ 
/*       */ 
/*       */ 
/*       */ 
/*       */ 
/*       */ 
/*       */ 
/*       */ 
/*       */ 
/*       */ 
/*       */ 
/*       */ 
/*       */ 
/*       */ 
/*       */ 
/*       */ 
/*       */ 
/*       */ 
/*       */ 
/*       */ 
/*       */ 
/*       */ 
/*       */ 
/*       */ 
/*       */ 
/*       */ 
/*       */ 
/*       */ 
/*       */ 
/*       */ 
/*       */ 
/*       */ 
/*       */ 
/*       */ 
/*       */ 
/*       */ 
/*       */ 
/*       */ 
/*       */ 
/*       */ 
/*       */ 
/*       */ 
/*       */ 
/*       */ 
/*       */ 
/*       */ 
/*       */ 
/*       */ 
/*       */ 
/*       */ 
/*       */ 
/*       */ 
/*       */ 
/*       */ 
/*       */ 
/*       */ 
/*       */ 
/*       */ 
/*       */ 
/*       */ 
/*       */ 
/*       */ 
/*       */ 
/*       */ 
/*       */ 
/*       */ 
/*       */ 
/*       */ 
/*       */ 
/*       */ 
/*       */ 
/*       */ 
/*       */ 
/*       */ 
/*       */ 
/*       */ 
/*       */ 
/*       */ 
/*       */ 
/*       */ 
/*       */ 
/*       */ 
/*       */ 
/*       */ 
/*       */ 
/*       */ 
/*       */ 
/*       */ 
/*       */ 
/*       */ 
/*       */ 
/*       */ 
/*       */ 
/*       */ 
/*       */ 
/*       */ 
/*       */ 
/*       */ 
/*       */ 
/*       */ 
/*       */ 
/*       */ 
/*       */ 
/*       */ 
/*       */ 
/*       */ 
/*       */ 
/*       */ 
/*       */ 
/*       */ 
/*       */ 
/*       */ 
/*       */ 
/*       */ 
/*       */ 
/*       */ 
/*       */ 
/*       */ 
/*       */ 
/*       */ 
/*       */ 
/*       */ 
/*       */ 
/*       */ 
/*       */ 
/*       */ 
/*       */ 
/*       */ 
/*       */ 
/*       */ 
/*       */ 
/*       */ 
/*       */ 
/*       */ 
/*       */ 
/*       */ 
/*       */ 
/*       */ 
/*       */ 
/*       */ 
/*       */ 
/*       */ 
/*       */ 
/*       */ 
/*       */ 
/*       */ 
/*       */ 
/*       */ 
/*       */     
/*       */     for (h h : k1.dE()) {
/*  9092 */       q1.q(h.mI, h
/*       */ 
/*       */ 
/*       */ 
/*       */ 
/*       */ 
/*       */ 
/*       */           
/*  9100 */           .mJ);
/*       */     }
/*       */     q<T> graphCopy = q1;
/*       */     List<T> l = new ArrayList<>();
/*       */     Set<T> s = (Set<T>)graphCopy.dG().stream().filter(node -> (graphCopy.A(node) == 0)).collect(Collectors.toSet());
/*       */     while (!s.isEmpty()) {
/*       */       Iterator<T> it;
/*       */       T n = (it = s.iterator()).next();
/*       */       it.remove();
/*       */       l.add(n);
/*       */       for (T m : graphCopy.D(n)) {
/*       */         graphCopy.r(n, m);
/*       */         if (graphCopy.A(m) == 0) {
/*       */           s.add(m);
/*       */         }
/*       */       } 
/*       */     } 
/*       */     if (!graphCopy.dE().isEmpty()) {
/*       */       throw new RuntimeException("Graph has at least one cycle");
/*       */     }
/*       */     return l;
/*       */   }
/*       */ 
/*       */ 
/*       */ 
/*       */ 
/*       */ 
/*       */ 
/*       */ 
/*       */ 
/*       */ 
/*       */ 
/*       */ 
/*       */ 
/*       */ 
/*       */ 
/*       */ 
/*       */ 
/*       */ 
/*       */ 
/*       */ 
/*       */ 
/*       */ 
/*       */ 
/*       */ 
/*       */ 
/*       */ 
/*       */ 
/*       */ 
/*       */ 
/*       */ 
/*       */ 
/*       */ 
/*       */ 
/*       */ 
/*       */ 
/*       */ 
/*       */ 
/*       */ 
/*       */ 
/*       */ 
/*       */ 
/*       */ 
/*       */ 
/*       */ 
/*       */ 
/*       */ 
/*       */ 
/*       */ 
/*       */ 
/*       */ 
/*       */ 
/*       */ 
/*       */ 
/*       */ 
/*       */ 
/*       */ 
/*       */ 
/*       */ 
/*       */ 
/*       */ 
/*       */ 
/*       */ 
/*       */ 
/*       */ 
/*       */ 
/*       */ 
/*       */ 
/*       */ 
/*       */ 
/*       */ 
/*       */ 
/*       */ 
/*       */ 
/*       */ 
/*       */ 
/*       */ 
/*       */ 
/*       */ 
/*       */ 
/*       */ 
/*       */ 
/*       */ 
/*       */ 
/*       */ 
/*       */ 
/*       */ 
/*       */ 
/*       */ 
/*       */ 
/*       */ 
/*       */ 
/*       */ 
/*       */ 
/*       */ 
/*       */ 
/*       */ 
/*       */ 
/*       */ 
/*       */ 
/*       */ 
/*       */ 
/*       */ 
/*       */ 
/*       */ 
/*       */ 
/*       */ 
/*       */ 
/*       */ 
/*       */ 
/*       */ 
/*       */ 
/*       */ 
/*       */ 
/*       */ 
/*       */ 
/*       */ 
/*       */ 
/*       */ 
/*       */ 
/*       */ 
/*       */ 
/*       */ 
/*       */ 
/*       */ 
/*       */ 
/*       */ 
/*       */ 
/*       */ 
/*       */ 
/*       */ 
/*       */ 
/*       */ 
/*       */ 
/*       */ 
/*       */ 
/*       */ 
/*       */ 
/*       */ 
/*       */   
/*       */   public String getConfiguration(String groupName, String key) {
/*       */     return getConfiguration(groupName, (String)null, key);
/*       */   }
/*       */ 
/*       */ 
/*       */ 
/*       */ 
/*       */ 
/*       */ 
/*       */ 
/*       */ 
/*       */ 
/*       */ 
/*       */ 
/*       */ 
/*       */ 
/*       */ 
/*       */ 
/*       */ 
/*       */ 
/*       */ 
/*       */ 
/*       */ 
/*       */ 
/*       */ 
/*       */ 
/*       */ 
/*       */ 
/*       */ 
/*       */ 
/*       */ 
/*       */ 
/*       */ 
/*       */ 
/*       */ 
/*       */ 
/*       */ 
/*       */ 
/*       */ 
/*       */ 
/*       */ 
/*       */ 
/*       */ 
/*       */ 
/*       */ 
/*       */ 
/*       */ 
/*       */ 
/*       */ 
/*       */ 
/*       */ 
/*       */ 
/*       */ 
/*       */ 
/*       */ 
/*       */ 
/*       */ 
/*       */ 
/*       */ 
/*       */ 
/*       */ 
/*       */ 
/*       */ 
/*       */ 
/*       */ 
/*       */ 
/*       */ 
/*       */ 
/*       */ 
/*       */ 
/*       */ 
/*       */ 
/*       */ 
/*       */ 
/*       */ 
/*       */ 
/*       */ 
/*       */ 
/*       */ 
/*       */ 
/*       */ 
/*       */ 
/*       */ 
/*       */ 
/*       */ 
/*       */ 
/*       */ 
/*       */ 
/*       */ 
/*       */ 
/*       */ 
/*       */ 
/*       */ 
/*       */ 
/*       */ 
/*       */ 
/*       */ 
/*       */ 
/*       */ 
/*       */ 
/*       */ 
/*       */ 
/*       */ 
/*       */ 
/*       */ 
/*       */ 
/*       */ 
/*       */ 
/*       */ 
/*       */ 
/*       */ 
/*       */ 
/*       */ 
/*       */ 
/*       */ 
/*       */ 
/*       */ 
/*       */ 
/*       */ 
/*       */ 
/*       */ 
/*       */ 
/*       */ 
/*       */ 
/*       */ 
/*       */ 
/*       */ 
/*       */ 
/*       */ 
/*       */ 
/*       */ 
/*       */ 
/*       */ 
/*       */ 
/*       */ 
/*       */ 
/*       */ 
/*       */ 
/*       */ 
/*       */ 
/*       */   
/*       */   public String getConfiguration(String groupName, String profile, String key) {
/*       */     String wholeKey = getWholeKey(groupName, profile, key);
/*       */     return properties.getProperty(wholeKey);
/*       */   }
/*       */ 
/*       */ 
/*       */ 
/*       */ 
/*       */ 
/*       */ 
/*       */ 
/*       */ 
/*       */ 
/*       */ 
/*       */ 
/*       */ 
/*       */ 
/*       */ 
/*       */ 
/*       */ 
/*       */ 
/*       */ 
/*       */ 
/*       */ 
/*       */ 
/*       */ 
/*       */ 
/*       */ 
/*       */ 
/*       */ 
/*       */ 
/*       */ 
/*       */ 
/*       */ 
/*       */ 
/*       */ 
/*       */ 
/*       */ 
/*       */ 
/*       */ 
/*       */ 
/*       */ 
/*       */ 
/*       */ 
/*       */ 
/*       */ 
/*       */ 
/*       */ 
/*       */ 
/*       */ 
/*       */ 
/*       */ 
/*       */ 
/*       */ 
/*       */ 
/*       */ 
/*       */ 
/*       */ 
/*       */ 
/*       */ 
/*       */ 
/*       */ 
/*       */ 
/*       */ 
/*       */ 
/*       */ 
/*       */ 
/*       */ 
/*       */ 
/*       */ 
/*       */ 
/*       */ 
/*       */ 
/*       */ 
/*       */ 
/*       */ 
/*       */ 
/*       */ 
/*       */ 
/*       */ 
/*       */ 
/*       */ 
/*       */ 
/*       */ 
/*       */ 
/*       */ 
/*       */ 
/*       */ 
/*       */ 
/*       */ 
/*       */ 
/*       */ 
/*       */ 
/*       */ 
/*       */ 
/*       */ 
/*       */ 
/*       */ 
/*       */ 
/*       */ 
/*       */ 
/*       */ 
/*       */ 
/*       */ 
/*       */ 
/*       */ 
/*       */ 
/*       */ 
/*       */ 
/*       */ 
/*       */ 
/*       */ 
/*       */ 
/*       */ 
/*       */ 
/*       */ 
/*       */ 
/*       */ 
/*       */ 
/*       */ 
/*       */ 
/*       */ 
/*       */ 
/*       */ 
/*       */ 
/*       */ 
/*       */ 
/*       */ 
/*       */ 
/*       */ 
/*       */ 
/*       */ 
/*       */ 
/*       */ 
/*       */ 
/*       */ 
/*       */ 
/*       */ 
/*       */ 
/*       */ 
/*       */ 
/*       */   
/*       */   public <T> T getConfiguration(String groupName, String key, Type clazz) {
/*       */     return getConfiguration(groupName, null, key, clazz);
/*       */   }
/*       */ 
/*       */ 
/*       */ 
/*       */ 
/*       */ 
/*       */ 
/*       */ 
/*       */ 
/*       */ 
/*       */ 
/*       */ 
/*       */ 
/*       */ 
/*       */ 
/*       */ 
/*       */ 
/*       */ 
/*       */ 
/*       */ 
/*       */ 
/*       */ 
/*       */ 
/*       */ 
/*       */ 
/*       */ 
/*       */ 
/*       */ 
/*       */ 
/*       */ 
/*       */ 
/*       */ 
/*       */ 
/*       */ 
/*       */ 
/*       */ 
/*       */ 
/*       */ 
/*       */ 
/*       */ 
/*       */ 
/*       */ 
/*       */ 
/*       */ 
/*       */ 
/*       */ 
/*       */ 
/*       */ 
/*       */ 
/*       */ 
/*       */ 
/*       */ 
/*       */ 
/*       */ 
/*       */ 
/*       */ 
/*       */ 
/*       */ 
/*       */ 
/*       */ 
/*       */ 
/*       */ 
/*       */ 
/*       */ 
/*       */ 
/*       */ 
/*       */ 
/*       */ 
/*       */ 
/*       */ 
/*       */ 
/*       */ 
/*       */ 
/*       */ 
/*       */ 
/*       */ 
/*       */ 
/*       */ 
/*       */ 
/*       */ 
/*       */ 
/*       */ 
/*       */ 
/*       */ 
/*       */ 
/*       */ 
/*       */ 
/*       */ 
/*       */ 
/*       */ 
/*       */ 
/*       */ 
/*       */ 
/*       */ 
/*       */ 
/*       */ 
/*       */ 
/*       */ 
/*       */ 
/*       */ 
/*       */ 
/*       */ 
/*       */ 
/*       */ 
/*       */ 
/*       */ 
/*       */ 
/*       */ 
/*       */ 
/*       */ 
/*       */ 
/*       */ 
/*       */ 
/*       */ 
/*       */ 
/*       */ 
/*       */ 
/*       */ 
/*       */ 
/*       */ 
/*       */ 
/*       */ 
/*       */ 
/*       */ 
/*       */ 
/*       */ 
/*       */ 
/*       */ 
/*       */ 
/*       */ 
/*       */ 
/*       */ 
/*       */ 
/*       */ 
/*       */ 
/*       */ 
/*       */ 
/*       */ 
/*       */   
/*       */   public Object stringToObject(String str, Type type) {
/*       */     if (type == boolean.class || type == Boolean.class) {
/*       */       return Boolean.valueOf(Boolean.parseBoolean(str));
/*       */     }
/*       */     if (type == int.class || type == Integer.class) {
/*       */       return Integer.valueOf(Integer.parseInt(str));
/*       */     }
/*       */     if (type == double.class || type == Double.class) {
/*       */       return Double.valueOf(Double.parseDouble(str));
/*       */     }
/*       */     if (type == Color.class) {
/*       */       return ColorUtil.fromString(str);
/*       */     }
/*       */     if (type == Dimension.class) {
/*       */       String[] splitStr;
/*       */       int width = Integer.parseInt((splitStr = str.split("x"))[0]);
/*       */       int height = Integer.parseInt(splitStr[1]);
/*       */       return new Dimension(width, height);
/*       */     } 
/*       */     if (type == Point.class) {
/*       */       String[] splitStr;
/*       */       int width = Integer.parseInt((splitStr = str.split(":"))[0]);
/*       */       int height = Integer.parseInt(splitStr[1]);
/*       */       return new Point(width, height);
/*       */     } 
/*       */     if (type == Rectangle.class) {
/*       */       String[] splitStr;
/*       */       int x = Integer.parseInt((splitStr = str.split(":"))[0]);
/*       */       int y = Integer.parseInt(splitStr[1]);
/*       */       int width = Integer.parseInt(splitStr[2]);
/*       */       int height = Integer.parseInt(splitStr[3]);
/*       */       return new Rectangle(x, y, width, height);
/*       */     } 
/*       */     if (type instanceof Class && ((Class)type).isEnum()) {
/*       */       return Enum.valueOf((Class<Enum>)type, str);
/*       */     }
/*       */     if (type == Instant.class) {
/*       */       return Instant.parse(str);
/*       */     }
/*       */     if (type == Keybind.class || type == ModifierlessKeybind.class) {
/*       */       String[] splitStr;
/*       */       int code = Integer.parseInt((splitStr = str.split(":"))[0]);
/*       */       int mods = Integer.parseInt(splitStr[1]);
/*       */       if (type == ModifierlessKeybind.class) {
/*       */         return new ModifierlessKeybind(code, mods);
/*       */       }
/*       */       return new Keybind(code, mods);
/*       */     } 
/*       */     if (type == WorldPoint.class) {
/*       */       String[] splitStr;
/*       */       int x = Integer.parseInt((splitStr = str.split(":"))[0]);
/*       */       int y = Integer.parseInt(splitStr[1]);
/*       */       int plane = Integer.parseInt(splitStr[2]);
/*       */       return new WorldPoint(x, y, plane);
/*       */     } 
/*       */     if (type == Duration.class) {
/*       */       return Duration.ofMillis(Long.parseLong(str));
/*       */     }
/*       */     if (type == byte[].class) {
/*       */       return Base64.getUrlDecoder().decode(str);
/*       */     }
/*       */     if (type instanceof ParameterizedType) {
/*       */       ParameterizedType parameterizedType;
/*       */       if ((parameterizedType = (ParameterizedType)type).getRawType() == Set.class) {
/*       */         return gson.a(str, parameterizedType);
/*       */       }
/*       */     } 
/*       */     return str;
/*       */   }
/*       */ 
/*       */ 
/*       */ 
/*       */ 
/*       */ 
/*       */ 
/*       */ 
/*       */ 
/*       */ 
/*       */ 
/*       */ 
/*       */ 
/*       */ 
/*       */ 
/*       */ 
/*       */ 
/*       */ 
/*       */ 
/*       */ 
/*       */ 
/*       */ 
/*       */ 
/*       */ 
/*       */ 
/*       */ 
/*       */ 
/*       */ 
/*       */ 
/*       */ 
/*       */ 
/*       */ 
/*       */ 
/*       */ 
/*       */ 
/*       */ 
/*       */ 
/*       */ 
/*       */ 
/*       */ 
/*       */ 
/*       */ 
/*       */ 
/*       */ 
/*       */ 
/*       */ 
/*       */ 
/*       */ 
/*       */ 
/*       */ 
/*       */ 
/*       */ 
/*       */ 
/*       */ 
/*       */ 
/*       */ 
/*       */ 
/*       */ 
/*       */ 
/*       */ 
/*       */ 
/*       */ 
/*       */ 
/*       */ 
/*       */ 
/*       */ 
/*       */ 
/*       */ 
/*       */ 
/*       */ 
/*       */ 
/*       */ 
/*       */ 
/*       */ 
/*       */ 
/*       */ 
/*       */ 
/*       */ 
/*       */ 
/*       */ 
/*       */ 
/*       */ 
/*       */ 
/*       */ 
/*       */ 
/*       */ 
/*       */ 
/*       */ 
/*       */ 
/*       */ 
/*       */ 
/*       */ 
/*       */ 
/*       */ 
/*       */ 
/*       */ 
/*       */ 
/*       */ 
/*       */ 
/*       */ 
/*       */ 
/*       */ 
/*       */ 
/*       */ 
/*       */ 
/*       */ 
/*       */ 
/*       */ 
/*       */ 
/*       */ 
/*       */ 
/*       */ 
/*       */ 
/*       */ 
/*       */ 
/*       */ 
/*       */ 
/*       */ 
/*       */ 
/*       */ 
/*       */ 
/*       */ 
/*       */ 
/*       */ 
/*       */ 
/*       */ 
/*       */ 
/*       */ 
/*       */ 
/*       */ 
/*       */ 
/*       */ 
/*       */ 
/*       */ 
/*       */ 
/*       */ 
/*       */ 
/*       */ 
/*       */   
/*       */   @Nullable
/*       */   public String objectToString(Object object) {
/*       */     if (object instanceof Color) {
/*       */       return String.valueOf(((Color)object).getRGB());
/*       */     }
/*       */     if (object instanceof Enum) {
/*       */       return ((Enum)object).name();
/*       */     }
/*       */     if (object instanceof Dimension) {
/*       */       Dimension d = (Dimension)object;
/*       */       return d.width + "x" + d.height;
/*       */     } 
/*       */     if (object instanceof Point) {
/*       */       Point p = (Point)object;
/*       */       return p.x + ":" + p.y;
/*       */     } 
/*       */     if (object instanceof Rectangle) {
/*       */       Rectangle r = (Rectangle)object;
/*       */       return r.x + ":" + r.y + ":" + r.width + ":" + r.height;
/*       */     } 
/*       */     if (object instanceof Instant) {
/*       */       return ((Instant)object).toString();
/*       */     }
/*       */     if (object instanceof Keybind) {
/*       */       Keybind k = (Keybind)object;
/*       */       return k.getKeyCode() + ":" + k.getModifiers();
/*       */     } 
/*       */     if (object instanceof WorldPoint) {
/*       */       WorldPoint wp = (WorldPoint)object;
/*       */       return wp.getX() + ":" + wp.getY() + ":" + wp.getPlane();
/*       */     } 
/*       */     if (object instanceof Duration) {
/*       */       return Long.toString(((Duration)object).toMillis());
/*       */     }
/*       */     if (object instanceof byte[]) {
/*       */       return Base64.getUrlEncoder().encodeToString((byte[])object);
/*       */     }
/*       */     if (object instanceof Set) {
/*       */       return gson.a(object, Set.class);
/*       */     }
/*       */     return (object == null) ? null : object.toString();
/*       */   }
/*       */ 
/*       */ 
/*       */ 
/*       */ 
/*       */ 
/*       */ 
/*       */ 
/*       */ 
/*       */ 
/*       */ 
/*       */ 
/*       */ 
/*       */ 
/*       */ 
/*       */ 
/*       */ 
/*       */ 
/*       */ 
/*       */ 
/*       */ 
/*       */ 
/*       */ 
/*       */ 
/*       */ 
/*       */ 
/*       */ 
/*       */ 
/*       */ 
/*       */ 
/*       */ 
/*       */ 
/*       */ 
/*       */ 
/*       */ 
/*       */ 
/*       */ 
/*       */ 
/*       */ 
/*       */ 
/*       */ 
/*       */ 
/*       */ 
/*       */ 
/*       */ 
/*       */ 
/*       */ 
/*       */ 
/*       */ 
/*       */ 
/*       */ 
/*       */ 
/*       */ 
/*       */ 
/*       */ 
/*       */ 
/*       */ 
/*       */ 
/*       */ 
/*       */ 
/*       */ 
/*       */ 
/*       */ 
/*       */ 
/*       */ 
/*       */ 
/*       */ 
/*       */ 
/*       */ 
/*       */ 
/*       */ 
/*       */ 
/*       */ 
/*       */ 
/*       */ 
/*       */ 
/*       */ 
/*       */ 
/*       */ 
/*       */ 
/*       */ 
/*       */ 
/*       */ 
/*       */ 
/*       */ 
/*       */ 
/*       */ 
/*       */ 
/*       */ 
/*       */ 
/*       */ 
/*       */ 
/*       */ 
/*       */ 
/*       */ 
/*       */ 
/*       */ 
/*       */ 
/*       */ 
/*       */ 
/*       */ 
/*       */ 
/*       */ 
/*       */ 
/*       */ 
/*       */ 
/*       */ 
/*       */ 
/*       */ 
/*       */ 
/*       */ 
/*       */ 
/*       */ 
/*       */ 
/*       */ 
/*       */ 
/*       */ 
/*       */ 
/*       */ 
/*       */ 
/*       */ 
/*       */ 
/*       */ 
/*       */ 
/*       */ 
/*       */ 
/*       */ 
/*       */ 
/*       */ 
/*       */ 
/*       */ 
/*       */ 
/*       */ 
/*       */ 
/*       */ 
/*       */ 
/*       */ 
/*       */ 
/*       */   
/*       */   public <T> T getConfiguration(String groupName, String profile, String key, Type type) {
/*       */     String value;
/* 10073 */     if (!i.d(value = getConfiguration(groupName, profile, key))) {
/*       */       try {
/*       */         return (T)stringToObject(value, type);
/*       */       } catch (Exception e) {
/*       */         System.err.println("Unable to unmarshal " + getWholeKey(groupName, profile, key) + " " + e);
/*       */       } 
/*       */     }
/*       */     return null;
/*       */   }
/*       */ 
/*       */ 
/*       */ 
/*       */ 
/*       */ 
/*       */ 
/*       */ 
/*       */ 
/*       */ 
/*       */ 
/*       */ 
/*       */ 
/*       */ 
/*       */ 
/*       */ 
/*       */ 
/*       */ 
/*       */ 
/*       */ 
/*       */ 
/*       */ 
/*       */ 
/*       */ 
/*       */ 
/*       */ 
/*       */ 
/*       */ 
/*       */ 
/*       */ 
/*       */ 
/*       */ 
/*       */ 
/*       */ 
/*       */ 
/*       */ 
/*       */ 
/*       */ 
/*       */ 
/*       */ 
/*       */ 
/*       */ 
/*       */ 
/*       */ 
/*       */ 
/*       */ 
/*       */ 
/*       */ 
/*       */ 
/*       */ 
/*       */ 
/*       */ 
/*       */ 
/*       */ 
/*       */ 
/*       */ 
/*       */ 
/*       */ 
/*       */ 
/*       */ 
/*       */ 
/*       */ 
/*       */ 
/*       */ 
/*       */ 
/*       */ 
/*       */ 
/*       */ 
/*       */ 
/*       */ 
/*       */ 
/*       */ 
/*       */ 
/*       */ 
/*       */ 
/*       */ 
/*       */ 
/*       */ 
/*       */ 
/*       */ 
/*       */ 
/*       */ 
/*       */ 
/*       */ 
/*       */ 
/*       */ 
/*       */ 
/*       */ 
/*       */ 
/*       */ 
/*       */ 
/*       */ 
/*       */ 
/*       */ 
/*       */ 
/*       */ 
/*       */ 
/*       */ 
/*       */ 
/*       */ 
/*       */ 
/*       */ 
/*       */ 
/*       */ 
/*       */ 
/*       */ 
/*       */ 
/*       */ 
/*       */ 
/*       */ 
/*       */ 
/*       */ 
/*       */ 
/*       */ 
/*       */ 
/*       */ 
/*       */ 
/*       */ 
/*       */ 
/*       */ 
/*       */ 
/*       */ 
/*       */ 
/*       */ 
/*       */ 
/*       */ 
/*       */ 
/*       */ 
/*       */ 
/*       */ 
/*       */ 
/*       */ 
/*       */ 
/*       */ 
/*       */ 
/*       */ 
/*       */ 
/*       */ 
/*       */ 
/*       */ 
/*       */ 
/*       */ 
/*       */ 
/*       */ 
/*       */ 
/*       */ 
/*       */ 
/*       */ 
/*       */ 
/*       */ 
/*       */ 
/*       */ 
/*       */ 
/*       */ 
/*       */ 
/*       */ 
/*       */ 
/*       */ 
/*       */ 
/*       */ 
/*       */ 
/*       */ 
/*       */ 
/*       */ 
/*       */ 
/*       */ 
/*       */ 
/*       */ 
/*       */ 
/*       */ 
/*       */ 
/*       */ 
/*       */ 
/*       */ 
/*       */ 
/*       */ 
/*       */ 
/*       */ 
/*       */ 
/*       */ 
/*       */ 
/*       */ 
/*       */ 
/*       */ 
/*       */ 
/*       */ 
/*       */ 
/*       */ 
/*       */ 
/*       */ 
/*       */ 
/*       */ 
/*       */ 
/*       */ 
/*       */ 
/*       */ 
/*       */ 
/*       */ 
/*       */ 
/*       */ 
/*       */ 
/*       */ 
/*       */ 
/*       */ 
/*       */ 
/*       */ 
/*       */ 
/*       */ 
/*       */ 
/*       */ 
/*       */ 
/*       */ 
/*       */ 
/*       */ 
/*       */ 
/*       */ 
/*       */ 
/*       */ 
/*       */ 
/*       */ 
/*       */ 
/*       */ 
/*       */ 
/*       */ 
/*       */ 
/*       */ 
/*       */ 
/*       */ 
/*       */ 
/*       */ 
/*       */ 
/*       */ 
/*       */ 
/*       */ 
/*       */ 
/*       */ 
/*       */ 
/*       */ 
/*       */ 
/*       */ 
/*       */ 
/*       */ 
/*       */ 
/*       */ 
/*       */ 
/*       */ 
/*       */ 
/*       */ 
/*       */ 
/*       */ 
/*       */ 
/*       */ 
/*       */ 
/*       */ 
/*       */ 
/*       */ 
/*       */ 
/*       */ 
/*       */ 
/*       */ 
/*       */ 
/*       */ 
/*       */ 
/*       */ 
/*       */ 
/*       */ 
/*       */ 
/*       */ 
/*       */ 
/*       */ 
/*       */ 
/*       */ 
/*       */ 
/*       */ 
/*       */ 
/*       */ 
/*       */ 
/*       */ 
/*       */ 
/*       */ 
/*       */ 
/*       */ 
/*       */ 
/*       */ 
/*       */ 
/*       */ 
/*       */ 
/*       */ 
/*       */ 
/*       */ 
/*       */ 
/*       */ 
/*       */ 
/*       */ 
/*       */ 
/*       */ 
/*       */ 
/*       */ 
/*       */ 
/*       */ 
/*       */ 
/*       */ 
/*       */ 
/*       */ 
/*       */ 
/*       */ 
/*       */ 
/*       */ 
/*       */ 
/*       */ 
/*       */ 
/*       */ 
/*       */ 
/*       */ 
/*       */ 
/*       */ 
/*       */ 
/*       */ 
/*       */ 
/*       */ 
/*       */ 
/*       */ 
/*       */ 
/*       */ 
/*       */ 
/*       */ 
/*       */ 
/*       */   
/*       */   public static String getWholeKey(String groupName, String profile, String key) {
/*       */     return groupName + "." + key;
/*       */   }
/*       */ 
/*       */ 
/*       */ 
/*       */ 
/*       */ 
/*       */ 
/*       */ 
/*       */ 
/*       */ 
/*       */ 
/*       */ 
/*       */ 
/*       */ 
/*       */ 
/*       */ 
/*       */ 
/*       */ 
/*       */ 
/*       */ 
/*       */ 
/*       */ 
/*       */ 
/*       */ 
/*       */ 
/*       */ 
/*       */ 
/*       */ 
/*       */ 
/*       */ 
/*       */ 
/*       */ 
/*       */ 
/*       */ 
/*       */ 
/*       */ 
/*       */ 
/*       */ 
/*       */ 
/*       */ 
/*       */ 
/*       */ 
/*       */ 
/*       */ 
/*       */ 
/*       */ 
/*       */ 
/*       */ 
/*       */ 
/*       */ 
/*       */ 
/*       */ 
/*       */ 
/*       */ 
/*       */ 
/*       */ 
/*       */ 
/*       */ 
/*       */ 
/*       */ 
/*       */ 
/*       */ 
/*       */ 
/*       */ 
/*       */ 
/*       */ 
/*       */ 
/*       */ 
/*       */ 
/*       */ 
/*       */ 
/*       */ 
/*       */ 
/*       */ 
/*       */ 
/*       */ 
/*       */ 
/*       */ 
/*       */ 
/*       */ 
/*       */ 
/*       */ 
/*       */ 
/*       */ 
/*       */ 
/*       */ 
/*       */ 
/*       */ 
/*       */ 
/*       */ 
/*       */ 
/*       */ 
/*       */ 
/*       */ 
/*       */ 
/*       */ 
/*       */ 
/*       */ 
/*       */ 
/*       */ 
/*       */ 
/*       */ 
/*       */ 
/*       */ 
/*       */ 
/*       */ 
/*       */ 
/*       */ 
/*       */ 
/*       */ 
/*       */ 
/*       */ 
/*       */ 
/*       */ 
/*       */ 
/*       */ 
/*       */ 
/*       */ 
/*       */ 
/*       */ 
/*       */ 
/*       */ 
/*       */ 
/*       */ 
/*       */ 
/*       */ 
/*       */ 
/*       */ 
/*       */ 
/*       */ 
/*       */ 
/*       */ 
/*       */ 
/*       */ 
/*       */ 
/*       */ 
/*       */ 
/*       */ 
/*       */ 
/*       */ 
/*       */ 
/*       */ 
/*       */ 
/*       */ 
/*       */ 
/*       */ 
/*       */ 
/*       */ 
/*       */ 
/*       */ 
/*       */ 
/*       */ 
/*       */ 
/*       */ 
/*       */ 
/*       */ 
/*       */ 
/*       */ 
/*       */ 
/*       */ 
/*       */ 
/*       */ 
/*       */ 
/*       */ 
/*       */ 
/*       */ 
/*       */ 
/*       */ 
/*       */ 
/*       */ 
/*       */ 
/*       */ 
/*       */ 
/*       */ 
/*       */ 
/*       */ 
/*       */ 
/*       */ 
/*       */ 
/*       */ 
/*       */ 
/*       */ 
/*       */ 
/*       */ 
/*       */ 
/*       */ 
/*       */ 
/*       */ 
/*       */ 
/*       */ 
/*       */ 
/*       */ 
/*       */ 
/*       */ 
/*       */ 
/*       */ 
/*       */ 
/*       */ 
/*       */ 
/*       */ 
/*       */ 
/*       */ 
/*       */ 
/*       */ 
/*       */ 
/*       */ 
/*       */ 
/*       */ 
/*       */ 
/*       */ 
/*       */ 
/*       */ 
/*       */ 
/*       */ 
/*       */ 
/*       */ 
/*       */ 
/*       */ 
/*       */ 
/*       */ 
/*       */ 
/*       */ 
/*       */ 
/*       */ 
/*       */ 
/*       */ 
/*       */ 
/*       */ 
/*       */ 
/*       */ 
/*       */ 
/*       */ 
/*       */ 
/*       */ 
/*       */ 
/*       */ 
/*       */ 
/*       */ 
/*       */ 
/*       */ 
/*       */ 
/*       */ 
/*       */ 
/*       */ 
/*       */ 
/*       */ 
/*       */ 
/*       */ 
/*       */ 
/*       */ 
/*       */ 
/*       */ 
/*       */ 
/*       */ 
/*       */ 
/*       */ 
/*       */ 
/*       */ 
/*       */ 
/*       */ 
/*       */ 
/*       */ 
/*       */ 
/*       */ 
/*       */ 
/*       */ 
/*       */ 
/*       */ 
/*       */ 
/*       */ 
/*       */ 
/*       */ 
/*       */ 
/*       */ 
/*       */ 
/*       */ 
/*       */ 
/*       */ 
/*       */ 
/*       */ 
/*       */ 
/*       */ 
/*       */ 
/*       */ 
/*       */ 
/*       */ 
/*       */ 
/*       */ 
/*       */ 
/*       */ 
/*       */ 
/*       */ 
/*       */ 
/*       */ 
/*       */ 
/*       */ 
/*       */ 
/*       */ 
/*       */ 
/*       */ 
/*       */ 
/*       */ 
/*       */ 
/*       */ 
/*       */ 
/*       */ 
/*       */ 
/*       */ 
/*       */ 
/*       */ 
/*       */ 
/*       */ 
/*       */ 
/*       */ 
/*       */ 
/*       */ 
/*       */ 
/*       */ 
/*       */ 
/*       */ 
/*       */ 
/*       */ 
/*       */ 
/*       */ 
/*       */ 
/*       */ 
/*       */ 
/*       */   
/*       */   public void setConfiguration(String groupName, String key, String value) {
/*       */     setConfiguration(groupName, (String)null, key, value);
/*       */   }
/*       */ 
/*       */ 
/*       */ 
/*       */ 
/*       */ 
/*       */ 
/*       */ 
/*       */ 
/*       */ 
/*       */ 
/*       */ 
/*       */ 
/*       */ 
/*       */ 
/*       */ 
/*       */ 
/*       */ 
/*       */ 
/*       */ 
/*       */ 
/*       */ 
/*       */ 
/*       */ 
/*       */ 
/*       */ 
/*       */ 
/*       */ 
/*       */ 
/*       */ 
/*       */ 
/*       */ 
/*       */ 
/*       */ 
/*       */ 
/*       */ 
/*       */ 
/*       */ 
/*       */ 
/*       */ 
/*       */ 
/*       */ 
/*       */ 
/*       */ 
/*       */ 
/*       */ 
/*       */ 
/*       */ 
/*       */ 
/*       */ 
/*       */ 
/*       */ 
/*       */ 
/*       */ 
/*       */ 
/*       */ 
/*       */ 
/*       */ 
/*       */ 
/*       */ 
/*       */ 
/*       */ 
/*       */ 
/*       */ 
/*       */ 
/*       */ 
/*       */ 
/*       */ 
/*       */ 
/*       */ 
/*       */ 
/*       */ 
/*       */ 
/*       */ 
/*       */ 
/*       */ 
/*       */ 
/*       */ 
/*       */ 
/*       */ 
/*       */ 
/*       */ 
/*       */ 
/*       */ 
/*       */ 
/*       */ 
/*       */ 
/*       */ 
/*       */ 
/*       */ 
/*       */ 
/*       */ 
/*       */ 
/*       */ 
/*       */ 
/*       */ 
/*       */ 
/*       */ 
/*       */ 
/*       */ 
/*       */ 
/*       */ 
/*       */ 
/*       */ 
/*       */ 
/*       */ 
/*       */ 
/*       */ 
/*       */ 
/*       */ 
/*       */ 
/*       */ 
/*       */ 
/*       */ 
/*       */ 
/*       */ 
/*       */ 
/*       */ 
/*       */ 
/*       */ 
/*       */ 
/*       */ 
/*       */ 
/*       */ 
/*       */ 
/*       */ 
/*       */ 
/*       */ 
/*       */ 
/*       */ 
/*       */ 
/*       */ 
/*       */ 
/*       */ 
/*       */ 
/*       */ 
/*       */ 
/*       */ 
/*       */ 
/*       */ 
/*       */ 
/*       */ 
/*       */ 
/*       */ 
/*       */ 
/*       */ 
/*       */ 
/*       */ 
/*       */ 
/*       */ 
/*       */ 
/*       */ 
/*       */ 
/*       */ 
/*       */ 
/*       */ 
/*       */ 
/*       */ 
/*       */ 
/*       */ 
/*       */ 
/*       */ 
/*       */ 
/*       */ 
/*       */ 
/*       */ 
/*       */ 
/*       */ 
/*       */ 
/*       */ 
/*       */ 
/*       */ 
/*       */ 
/*       */ 
/*       */ 
/*       */ 
/*       */ 
/*       */ 
/*       */ 
/*       */ 
/*       */ 
/*       */ 
/*       */ 
/*       */ 
/*       */ 
/*       */ 
/*       */ 
/*       */ 
/*       */ 
/*       */ 
/*       */ 
/*       */ 
/*       */ 
/*       */ 
/*       */ 
/*       */ 
/*       */ 
/*       */ 
/*       */ 
/*       */ 
/*       */ 
/*       */ 
/*       */ 
/*       */ 
/*       */ 
/*       */ 
/*       */ 
/*       */ 
/*       */ 
/*       */ 
/*       */ 
/*       */ 
/*       */ 
/*       */ 
/*       */ 
/*       */ 
/*       */ 
/*       */ 
/*       */ 
/*       */ 
/*       */ 
/*       */ 
/*       */ 
/*       */ 
/*       */ 
/*       */ 
/*       */ 
/*       */ 
/*       */ 
/*       */ 
/*       */ 
/*       */ 
/*       */ 
/*       */ 
/*       */ 
/*       */ 
/*       */ 
/*       */ 
/*       */ 
/*       */ 
/*       */ 
/*       */ 
/*       */ 
/*       */ 
/*       */ 
/*       */ 
/*       */ 
/*       */ 
/*       */ 
/*       */ 
/*       */ 
/*       */ 
/*       */ 
/*       */ 
/*       */ 
/*       */ 
/*       */ 
/*       */ 
/*       */ 
/*       */ 
/*       */ 
/*       */ 
/*       */ 
/*       */ 
/*       */ 
/*       */ 
/*       */ 
/*       */ 
/*       */ 
/*       */ 
/*       */ 
/*       */ 
/*       */ 
/*       */ 
/*       */ 
/*       */ 
/*       */ 
/*       */ 
/*       */ 
/*       */ 
/*       */ 
/*       */ 
/*       */ 
/*       */ 
/*       */ 
/*       */ 
/*       */ 
/*       */ 
/*       */ 
/*       */ 
/*       */ 
/*       */ 
/*       */ 
/*       */ 
/*       */ 
/*       */ 
/*       */ 
/*       */ 
/*       */ 
/*       */ 
/*       */ 
/*       */ 
/*       */ 
/*       */ 
/*       */ 
/*       */ 
/*       */ 
/*       */ 
/*       */ 
/*       */ 
/*       */ 
/*       */ 
/*       */ 
/*       */ 
/*       */ 
/*       */ 
/*       */ 
/*       */ 
/*       */ 
/*       */ 
/*       */ 
/*       */ 
/*       */ 
/*       */ 
/*       */ 
/*       */ 
/*       */   
/*       */   public void setConfiguration(String groupName, String profile, String key, String value) {
/*       */     String oldValue;
/*       */     if (value == null) {
/*       */       throw new NullPointerException("value is marked non-null but is null");
/*       */     }
/* 11073 */     if (i.d(groupName) || 
/*       */ 
/*       */ 
/*       */ 
/*       */ 
/*       */ 
/*       */ 
/*       */ 
/*       */ 
/*       */ 
/*       */ 
/*       */ 
/*       */ 
/*       */ 
/*       */ 
/*       */ 
/*       */ 
/*       */ 
/*       */ 
/*       */ 
/*       */ 
/*       */ 
/*       */ 
/*       */ 
/*       */ 
/*       */ 
/*       */ 
/*       */ 
/*       */ 
/*       */ 
/*       */ 
/*       */ 
/*       */ 
/*       */ 
/*       */ 
/*       */ 
/*       */ 
/*       */ 
/*       */ 
/*       */ 
/*       */ 
/*       */ 
/*       */ 
/*       */ 
/*       */ 
/*       */ 
/*       */ 
/*       */ 
/*       */ 
/*       */ 
/*       */ 
/*       */ 
/*       */ 
/*       */ 
/*       */ 
/*       */ 
/*       */ 
/*       */ 
/*       */ 
/*       */ 
/*       */ 
/*       */ 
/*       */ 
/*       */ 
/*       */ 
/*       */ 
/*       */ 
/*       */ 
/*       */ 
/*       */ 
/*       */ 
/*       */ 
/*       */ 
/*       */ 
/*       */ 
/*       */ 
/*       */ 
/*       */ 
/*       */ 
/*       */ 
/*       */ 
/*       */ 
/*       */ 
/*       */ 
/*       */ 
/*       */ 
/*       */ 
/*       */ 
/*       */ 
/*       */ 
/*       */ 
/*       */ 
/*       */ 
/*       */ 
/*       */ 
/*       */ 
/*       */ 
/*       */ 
/*       */ 
/*       */ 
/*       */ 
/*       */ 
/*       */ 
/*       */ 
/*       */ 
/*       */ 
/*       */ 
/*       */ 
/*       */ 
/*       */ 
/*       */ 
/*       */ 
/*       */ 
/*       */ 
/*       */ 
/*       */ 
/*       */ 
/*       */ 
/*       */ 
/*       */ 
/*       */ 
/*       */ 
/*       */ 
/*       */ 
/*       */ 
/*       */ 
/*       */ 
/*       */ 
/*       */ 
/*       */ 
/*       */ 
/*       */ 
/*       */ 
/*       */ 
/*       */ 
/*       */ 
/*       */ 
/*       */ 
/*       */ 
/*       */ 
/*       */ 
/*       */ 
/*       */ 
/*       */ 
/*       */ 
/*       */ 
/*       */ 
/*       */ 
/*       */ 
/*       */ 
/*       */ 
/*       */ 
/*       */ 
/*       */ 
/*       */ 
/*       */ 
/*       */ 
/*       */ 
/*       */ 
/*       */ 
/*       */ 
/*       */ 
/*       */ 
/*       */ 
/*       */ 
/*       */ 
/*       */ 
/*       */ 
/*       */ 
/*       */ 
/*       */ 
/*       */ 
/*       */ 
/*       */ 
/*       */ 
/*       */ 
/*       */ 
/*       */ 
/*       */ 
/*       */ 
/*       */ 
/*       */ 
/*       */ 
/*       */ 
/*       */ 
/*       */ 
/*       */ 
/*       */ 
/*       */ 
/*       */ 
/*       */ 
/*       */ 
/*       */ 
/*       */ 
/*       */ 
/*       */ 
/*       */ 
/*       */ 
/*       */ 
/*       */ 
/*       */ 
/*       */ 
/*       */ 
/*       */ 
/*       */ 
/*       */ 
/*       */ 
/*       */ 
/*       */ 
/*       */ 
/*       */ 
/*       */ 
/*       */ 
/*       */ 
/*       */ 
/*       */ 
/*       */ 
/*       */ 
/*       */ 
/*       */ 
/*       */ 
/*       */ 
/*       */ 
/*       */ 
/*       */ 
/*       */ 
/*       */ 
/*       */ 
/*       */ 
/*       */ 
/*       */ 
/*       */ 
/*       */ 
/*       */ 
/*       */ 
/*       */ 
/*       */ 
/*       */ 
/*       */ 
/*       */ 
/*       */ 
/*       */ 
/*       */ 
/*       */ 
/*       */ 
/*       */ 
/*       */ 
/*       */ 
/*       */ 
/*       */ 
/*       */ 
/*       */ 
/*       */ 
/*       */ 
/*       */ 
/*       */ 
/*       */ 
/*       */ 
/*       */ 
/*       */ 
/*       */ 
/*       */ 
/*       */ 
/*       */ 
/*       */ 
/*       */ 
/*       */ 
/*       */ 
/*       */ 
/*       */ 
/*       */ 
/*       */ 
/*       */ 
/*       */ 
/*       */ 
/*       */ 
/*       */ 
/*       */ 
/*       */ 
/*       */ 
/*       */ 
/*       */ 
/*       */ 
/*       */ 
/*       */ 
/*       */ 
/*       */ 
/*       */ 
/*       */ 
/*       */ 
/*       */ 
/*       */ 
/*       */ 
/*       */ 
/*       */ 
/*       */ 
/*       */ 
/*       */ 
/*       */ 
/*       */ 
/*       */ 
/*       */ 
/*       */ 
/*       */ 
/*       */ 
/*       */ 
/*       */ 
/*       */ 
/*       */ 
/*       */ 
/*       */ 
/*       */ 
/*       */ 
/*       */ 
/*       */ 
/*       */ 
/*       */ 
/*       */ 
/*       */ 
/*       */ 
/*       */ 
/*       */ 
/*       */ 
/*       */ 
/*       */ 
/*       */ 
/*       */ 
/*       */ 
/*       */ 
/*       */ 
/*       */ 
/*       */ 
/*       */ 
/*       */ 
/*       */ 
/*       */ 
/*       */ 
/*       */ 
/*       */ 
/*       */ 
/*       */ 
/*       */ 
/*       */ 
/*       */ 
/*       */ 
/*       */ 
/*       */ 
/*       */ 
/*       */ 
/*       */ 
/*       */ 
/*       */ 
/*       */ 
/*       */ 
/*       */ 
/*       */ 
/*       */ 
/*       */ 
/*       */ 
/*       */ 
/*       */ 
/*       */ 
/*       */ 
/*       */ 
/*       */ 
/*       */ 
/*       */ 
/*       */ 
/*       */ 
/*       */ 
/*       */ 
/*       */ 
/*       */ 
/*       */ 
/*       */ 
/*       */ 
/*       */ 
/*       */ 
/*       */ 
/*       */ 
/*       */ 
/*       */ 
/*       */ 
/*       */ 
/*       */ 
/*       */ 
/*       */ 
/*       */ 
/*       */ 
/*       */ 
/*       */ 
/*       */ 
/*       */ 
/*       */ 
/*       */ 
/*       */ 
/*       */ 
/*       */ 
/*       */ 
/*       */ 
/*       */ 
/*       */ 
/*       */ 
/*       */ 
/*       */ 
/*       */ 
/*       */ 
/*       */ 
/*       */ 
/*       */ 
/*       */ 
/*       */ 
/*       */ 
/*       */ 
/*       */ 
/*       */ 
/*       */ 
/*       */ 
/*       */ 
/*       */ 
/*       */ 
/*       */ 
/*       */ 
/*       */ 
/*       */ 
/*       */ 
/*       */ 
/*       */ 
/*       */ 
/*       */ 
/*       */ 
/*       */ 
/*       */ 
/*       */ 
/*       */ 
/*       */ 
/*       */ 
/*       */ 
/*       */ 
/*       */ 
/*       */ 
/*       */ 
/*       */ 
/*       */ 
/*       */ 
/*       */ 
/*       */ 
/*       */ 
/*       */ 
/*       */ 
/*       */ 
/*       */ 
/*       */ 
/*       */ 
/*       */ 
/*       */ 
/*       */ 
/*       */ 
/*       */ 
/*       */ 
/*       */ 
/*       */ 
/*       */ 
/*       */ 
/*       */ 
/*       */ 
/*       */ 
/*       */ 
/*       */ 
/*       */ 
/*       */ 
/*       */ 
/*       */ 
/*       */ 
/*       */ 
/*       */ 
/*       */ 
/*       */ 
/*       */ 
/*       */ 
/*       */ 
/*       */ 
/*       */ 
/*       */ 
/*       */ 
/*       */ 
/*       */ 
/*       */ 
/*       */ 
/*       */ 
/*       */ 
/*       */ 
/*       */ 
/*       */ 
/*       */ 
/*       */ 
/*       */ 
/*       */ 
/*       */ 
/*       */ 
/*       */ 
/*       */ 
/*       */ 
/*       */ 
/*       */ 
/*       */ 
/*       */ 
/*       */ 
/*       */ 
/*       */ 
/*       */ 
/*       */ 
/*       */ 
/*       */ 
/*       */ 
/*       */ 
/*       */ 
/*       */ 
/*       */ 
/*       */ 
/*       */ 
/*       */ 
/*       */ 
/*       */ 
/*       */ 
/*       */ 
/*       */ 
/*       */ 
/*       */ 
/*       */ 
/*       */ 
/*       */ 
/*       */ 
/*       */ 
/*       */ 
/*       */ 
/*       */ 
/*       */ 
/*       */ 
/*       */ 
/*       */ 
/*       */ 
/*       */ 
/*       */ 
/*       */ 
/*       */ 
/*       */ 
/*       */ 
/*       */ 
/*       */ 
/*       */ 
/*       */ 
/*       */ 
/*       */ 
/*       */ 
/*       */ 
/*       */ 
/*       */ 
/*       */ 
/*       */ 
/*       */ 
/*       */ 
/*       */ 
/*       */ 
/*       */ 
/*       */ 
/*       */ 
/*       */ 
/*       */ 
/*       */ 
/*       */ 
/*       */ 
/*       */ 
/*       */ 
/*       */ 
/*       */ 
/*       */ 
/*       */ 
/*       */ 
/*       */ 
/*       */ 
/*       */ 
/*       */ 
/*       */ 
/*       */ 
/*       */ 
/*       */ 
/*       */ 
/*       */ 
/*       */ 
/*       */ 
/*       */ 
/*       */ 
/*       */ 
/*       */ 
/*       */ 
/*       */ 
/*       */ 
/*       */ 
/*       */ 
/*       */ 
/*       */ 
/*       */ 
/*       */ 
/*       */ 
/*       */ 
/*       */ 
/*       */ 
/*       */ 
/*       */ 
/*       */ 
/*       */ 
/*       */ 
/*       */ 
/*       */ 
/*       */ 
/*       */ 
/*       */ 
/*       */ 
/*       */ 
/*       */ 
/*       */ 
/*       */ 
/*       */ 
/*       */ 
/*       */ 
/*       */ 
/*       */ 
/*       */ 
/*       */ 
/*       */ 
/*       */ 
/*       */ 
/*       */ 
/*       */ 
/*       */ 
/*       */ 
/*       */ 
/*       */ 
/*       */ 
/*       */ 
/*       */ 
/*       */ 
/*       */ 
/*       */ 
/*       */ 
/*       */ 
/*       */ 
/*       */ 
/*       */ 
/*       */ 
/*       */ 
/*       */ 
/*       */ 
/*       */ 
/*       */ 
/*       */ 
/*       */ 
/*       */ 
/*       */ 
/*       */ 
/*       */ 
/*       */ 
/*       */ 
/*       */ 
/*       */ 
/*       */ 
/*       */ 
/*       */ 
/*       */ 
/*       */ 
/*       */ 
/*       */ 
/*       */ 
/*       */ 
/*       */ 
/*       */ 
/*       */ 
/*       */ 
/*       */ 
/*       */ 
/*       */ 
/*       */ 
/*       */ 
/*       */ 
/*       */ 
/*       */ 
/*       */ 
/*       */ 
/*       */ 
/*       */ 
/*       */ 
/*       */ 
/*       */ 
/*       */ 
/*       */ 
/*       */ 
/*       */ 
/*       */ 
/*       */ 
/*       */ 
/*       */ 
/*       */ 
/*       */ 
/*       */ 
/*       */ 
/*       */ 
/*       */ 
/*       */ 
/*       */ 
/*       */ 
/*       */ 
/*       */ 
/*       */ 
/*       */ 
/*       */ 
/*       */ 
/*       */ 
/*       */ 
/*       */ 
/*       */ 
/*       */ 
/*       */ 
/*       */ 
/*       */ 
/*       */ 
/*       */ 
/*       */ 
/*       */ 
/*       */ 
/*       */ 
/*       */ 
/*       */ 
/*       */ 
/*       */ 
/*       */ 
/*       */ 
/*       */ 
/*       */ 
/*       */ 
/*       */ 
/*       */ 
/*       */ 
/*       */ 
/*       */ 
/*       */ 
/*       */ 
/*       */ 
/*       */ 
/*       */ 
/*       */ 
/*       */ 
/*       */ 
/*       */ 
/*       */ 
/*       */ 
/*       */ 
/*       */ 
/*       */ 
/*       */ 
/*       */ 
/*       */ 
/*       */ 
/*       */ 
/*       */ 
/*       */ 
/*       */ 
/*       */ 
/*       */ 
/*       */ 
/*       */ 
/*       */ 
/*       */ 
/*       */ 
/*       */ 
/*       */ 
/*       */ 
/*       */ 
/*       */ 
/*       */ 
/*       */ 
/*       */ 
/*       */ 
/*       */ 
/*       */ 
/*       */ 
/*       */ 
/*       */ 
/*       */ 
/*       */ 
/*       */ 
/*       */ 
/*       */ 
/*       */ 
/*       */ 
/*       */ 
/*       */ 
/*       */ 
/*       */ 
/*       */ 
/*       */ 
/*       */ 
/*       */ 
/*       */ 
/*       */ 
/*       */ 
/*       */ 
/*       */ 
/*       */ 
/*       */ 
/*       */ 
/*       */ 
/*       */ 
/*       */ 
/*       */ 
/*       */ 
/*       */ 
/*       */ 
/*       */ 
/*       */ 
/*       */ 
/*       */ 
/*       */ 
/*       */ 
/*       */ 
/*       */ 
/*       */ 
/*       */ 
/*       */ 
/*       */ 
/*       */ 
/*       */ 
/*       */ 
/*       */ 
/*       */ 
/*       */ 
/*       */ 
/*       */ 
/*       */ 
/*       */ 
/*       */ 
/*       */ 
/*       */ 
/*       */ 
/*       */ 
/*       */ 
/*       */ 
/*       */ 
/*       */ 
/*       */ 
/*       */ 
/*       */ 
/*       */ 
/*       */ 
/*       */ 
/*       */ 
/*       */ 
/*       */ 
/*       */ 
/*       */ 
/*       */ 
/*       */ 
/*       */ 
/*       */ 
/*       */ 
/*       */ 
/*       */ 
/*       */ 
/*       */ 
/*       */ 
/*       */ 
/*       */ 
/*       */ 
/*       */ 
/*       */ 
/*       */ 
/*       */ 
/*       */ 
/*       */ 
/*       */ 
/*       */ 
/*       */ 
/*       */ 
/*       */ 
/*       */ 
/*       */ 
/*       */ 
/*       */ 
/*       */ 
/*       */ 
/*       */ 
/*       */ 
/*       */ 
/*       */ 
/*       */ 
/*       */ 
/*       */ 
/*       */ 
/*       */ 
/*       */ 
/*       */ 
/*       */ 
/*       */ 
/*       */ 
/*       */ 
/*       */ 
/*       */ 
/*       */ 
/*       */ 
/*       */ 
/*       */ 
/*       */ 
/*       */ 
/*       */ 
/*       */ 
/*       */ 
/*       */ 
/*       */ 
/*       */ 
/*       */ 
/*       */ 
/*       */ 
/*       */ 
/*       */ 
/*       */ 
/*       */ 
/*       */ 
/*       */ 
/*       */ 
/*       */ 
/*       */ 
/*       */ 
/*       */ 
/*       */ 
/*       */ 
/*       */ 
/*       */ 
/*       */ 
/*       */ 
/*       */ 
/*       */ 
/*       */ 
/*       */ 
/*       */ 
/*       */ 
/*       */ 
/*       */ 
/*       */ 
/*       */ 
/*       */ 
/*       */ 
/*       */ 
/*       */ 
/*       */ 
/*       */ 
/*       */ 
/*       */ 
/*       */ 
/*       */ 
/*       */ 
/*       */ 
/*       */ 
/*       */ 
/*       */ 
/*       */ 
/*       */ 
/*       */ 
/*       */ 
/*       */ 
/*       */ 
/*       */ 
/*       */ 
/*       */ 
/*       */ 
/*       */ 
/*       */ 
/*       */ 
/*       */ 
/*       */ 
/*       */ 
/*       */ 
/*       */ 
/*       */ 
/*       */ 
/*       */ 
/*       */ 
/*       */ 
/*       */ 
/*       */ 
/*       */ 
/*       */ 
/*       */ 
/*       */ 
/*       */ 
/*       */ 
/*       */ 
/*       */ 
/*       */ 
/*       */ 
/*       */       
/* 12073 */       i.d(key) || key.indexOf(':') != -1)
/*       */       throw new IllegalArgumentException(); 
/*       */     String wholeKey = getWholeKey(groupName, null, key);
/*       */     synchronized (this) {
/*       */       if (Objects.equals(oldValue = (String)properties.setProperty(wholeKey, value), value))
/*       */         return; 
/*       */       properties.put(wholeKey, value);
/*       */     } 
/*       */     System.out.println("Setting configuration value for " + wholeKey + " to " + value);
/*       */     this.handler.invalidate();
/*       */     saveConfig(false);
/*       */     ConfigChanged configChanged;
/*       */     (configChanged = new ConfigChanged()).setGroup(groupName);
/*       */     configChanged.setProfile(null);
/*       */     configChanged.setKey(key);
/*       */     configChanged.setOldValue(oldValue);
/*       */     configChanged.setNewValue(value);
/*       */     configChangedEvent(configChanged);
/*       */   }
/*       */   
/*       */   public static void configChangedEvent(ConfigChanged configChanged) {
/*       */     for (Iterator<Plugin> iterator = singleton.getPlugins().iterator(); iterator.hasNext();)
/*       */       ((Plugin)iterator.next()).onConfigChanged(configChanged); 
/*       */   }
/*       */   
/*       */   public <T> void setConfiguration(String groupName, String profile, String key, T value) {
/*       */     setConfiguration(groupName, profile, key, objectToString(value));
/*       */   }
/*       */   
/*       */   public <T> void setConfiguration(String groupName, String key, T value) {
/*       */     setConfiguration(groupName, (String)null, key, value);
/*       */   }
/*       */   
/*       */   public void setDefaultConfiguration(Object proxy, boolean override) {
/*       */     // Byte code:
/*       */     //   0: aload_1
/*       */     //   1: invokevirtual getClass : ()Ljava/lang/Class;
/*       */     //   4: invokevirtual getInterfaces : ()[Ljava/lang/Class;
/*       */     //   7: iconst_0
/*       */     //   8: aaload
/*       */     //   9: dup
/*       */     //   10: astore_3
/*       */     //   11: ldc utils/plugins/settings/config/ConfigGroup
/*       */     //   13: invokevirtual getAnnotation : (Ljava/lang/Class;)Ljava/lang/annotation/Annotation;
/*       */     //   16: checkcast utils/plugins/settings/config/ConfigGroup
/*       */     //   19: dup
/*       */     //   20: astore #4
/*       */     //   22: ifnonnull -> 26
/*       */     //   25: return
/*       */     //   26: aload_3
/*       */     //   27: invokevirtual getDeclaredMethods : ()[Ljava/lang/reflect/Method;
/*       */     //   30: dup
/*       */     //   31: astore #5
/*       */     //   33: arraylength
/*       */     //   34: istore #6
/*       */     //   36: iconst_0
/*       */     //   37: istore #7
/*       */     //   39: iload #7
/*       */     //   41: iload #6
/*       */     //   43: if_icmpge -> 343
/*       */     //   46: aload #5
/*       */     //   48: iload #7
/*       */     //   50: aaload
/*       */     //   51: dup
/*       */     //   52: astore #8
/*       */     //   54: ldc utils/plugins/settings/config/ConfigItem
/*       */     //   56: invokevirtual getAnnotation : (Ljava/lang/Class;)Ljava/lang/annotation/Annotation;
/*       */     //   59: checkcast utils/plugins/settings/config/ConfigItem
/*       */     //   62: dup
/*       */     //   63: astore #9
/*       */     //   65: ifnull -> 337
/*       */     //   68: aload #8
/*       */     //   70: invokevirtual getParameterCount : ()I
/*       */     //   73: ifne -> 337
/*       */     //   76: aload #8
/*       */     //   78: invokevirtual isDefault : ()Z
/*       */     //   81: ifne -> 130
/*       */     //   84: iload_2
/*       */     //   85: ifeq -> 337
/*       */     //   88: aload_0
/*       */     //   89: aload #4
/*       */     //   91: invokeinterface value : ()Ljava/lang/String;
/*       */     //   96: aload #9
/*       */     //   98: invokeinterface keyName : ()Ljava/lang/String;
/*       */     //   103: invokevirtual getConfiguration : (Ljava/lang/String;Ljava/lang/String;)Ljava/lang/String;
/*       */     //   106: ifnull -> 127
/*       */     //   109: aload_0
/*       */     //   110: aload #4
/*       */     //   112: invokeinterface value : ()Ljava/lang/String;
/*       */     //   117: aload #9
/*       */     //   119: invokeinterface keyName : ()Ljava/lang/String;
/*       */     //   124: invokevirtual unsetConfiguration : (Ljava/lang/String;Ljava/lang/String;)V
/*       */     //   127: goto -> 337
/*       */     //   130: iload_2
/*       */     //   131: ifne -> 160
/*       */     //   134: aload_0
/*       */     //   135: aload #4
/*       */     //   137: invokeinterface value : ()Ljava/lang/String;
/*       */     //   142: aload #9
/*       */     //   144: invokeinterface keyName : ()Ljava/lang/String;
/*       */     //   149: aload #8
/*       */     //   151: invokevirtual getGenericReturnType : ()Ljava/lang/reflect/Type;
/*       */     //   154: invokevirtual getConfiguration : (Ljava/lang/String;Ljava/lang/String;Ljava/lang/reflect/Type;)Ljava/lang/Object;
/*       */     //   157: ifnonnull -> 337
/*       */     //   160: aload_1
/*       */     //   161: aload #8
/*       */     //   163: aconst_null
/*       */     //   164: invokestatic callDefaultMethod : (Ljava/lang/Object;Ljava/lang/reflect/Method;[Ljava/lang/Object;)Ljava/lang/Object;
/*       */     //   167: astore #10
/*       */     //   169: getstatic java/lang/System.out : Ljava/io/PrintStream;
/*       */     //   172: new java/lang/StringBuilder
/*       */     //   175: dup
/*       */     //   176: ldc 'found default '
/*       */     //   178: invokespecial <init> : (Ljava/lang/String;)V
/*       */     //   181: aload #8
/*       */     //   183: invokevirtual getName : ()Ljava/lang/String;
/*       */     //   186: invokevirtual append : (Ljava/lang/String;)Ljava/lang/StringBuilder;
/*       */     //   189: ldc ' '
/*       */     //   191: invokevirtual append : (Ljava/lang/String;)Ljava/lang/StringBuilder;
/*       */     //   194: aload #10
/*       */     //   196: invokevirtual append : (Ljava/lang/Object;)Ljava/lang/StringBuilder;
/*       */     //   199: invokevirtual toString : ()Ljava/lang/String;
/*       */     //   202: invokevirtual println : (Ljava/lang/String;)V
/*       */     //   205: goto -> 224
/*       */     //   208: astore #11
/*       */     //   210: getstatic utils/plugins/PluginManager/PluginManager.log : Lorg/c/b;
/*       */     //   213: aconst_null
/*       */     //   214: aload #11
/*       */     //   216: invokeinterface warn : (Ljava/lang/String;Ljava/lang/Throwable;)V
/*       */     //   221: goto -> 337
/*       */     //   224: aload_0
/*       */     //   225: aload #4
/*       */     //   227: invokeinterface value : ()Ljava/lang/String;
/*       */     //   232: aload #9
/*       */     //   234: invokeinterface keyName : ()Ljava/lang/String;
/*       */     //   239: invokevirtual getConfiguration : (Ljava/lang/String;Ljava/lang/String;)Ljava/lang/String;
/*       */     //   242: astore #11
/*       */     //   244: aload_0
/*       */     //   245: aload #10
/*       */     //   247: invokevirtual objectToString : (Ljava/lang/Object;)Ljava/lang/String;
/*       */     //   250: astore #12
/*       */     //   252: aload #11
/*       */     //   254: aload #12
/*       */     //   256: invokestatic equals : (Ljava/lang/Object;Ljava/lang/Object;)Z
/*       */     //   259: ifne -> 337
/*       */     //   262: aload #11
/*       */     //   264: invokestatic d : (Ljava/lang/String;)Z
/*       */     //   267: ifeq -> 278
/*       */     //   270: aload #12
/*       */     //   272: invokestatic d : (Ljava/lang/String;)Z
/*       */     //   275: ifne -> 337
/*       */     //   278: getstatic utils/plugins/PluginManager/PluginManager.log : Lorg/c/b;
/*       */     //   281: ldc 'Set default configuration value for {}.{} to {}'
/*       */     //   283: iconst_3
/*       */     //   284: anewarray java/lang/Object
/*       */     //   287: dup
/*       */     //   288: iconst_0
/*       */     //   289: aload #4
/*       */     //   291: invokeinterface value : ()Ljava/lang/String;
/*       */     //   296: aastore
/*       */     //   297: dup
/*       */     //   298: iconst_1
/*       */     //   299: aload #9
/*       */     //   301: invokeinterface keyName : ()Ljava/lang/String;
/*       */     //   306: aastore
/*       */     //   307: dup
/*       */     //   308: iconst_2
/*       */     //   309: aload #10
/*       */     //   311: aastore
/*       */     //   312: invokeinterface debug : (Ljava/lang/String;[Ljava/lang/Object;)V
/*       */     //   317: aload_0
/*       */     //   318: aload #4
/*       */     //   320: invokeinterface value : ()Ljava/lang/String;
/*       */     //   325: aload #9
/*       */     //   327: invokeinterface keyName : ()Ljava/lang/String;
/*       */     //   332: aload #12
/*       */     //   334: invokevirtual setConfiguration : (Ljava/lang/String;Ljava/lang/String;Ljava/lang/String;)V
/*       */     //   337: iinc #7, 1
/*       */     //   340: goto -> 39
/*       */     //   343: return
/*       */     // Line number table:
/*       */     //   Java source line number -> byte code offset
/*       */     //   #1176	-> 0
/*       */     //   #1177	-> 10
/*       */     //   #1179	-> 20
/*       */     //   #1181	-> 25
/*       */     //   #1184	-> 26
/*       */     //   #1186	-> 52
/*       */     //   #1189	-> 63
/*       */     //   #1194	-> 76
/*       */     //   #1196	-> 84
/*       */     //   #1198	-> 88
/*       */     //   #1200	-> 106
/*       */     //   #1202	-> 109
/*       */     //   #1204	-> 127
/*       */     //   #1208	-> 130
/*       */     //   #1212	-> 134
/*       */     //   #1213	-> 157
/*       */     //   #1222	-> 160
/*       */     //   #1223	-> 169
/*       */     //   #1229	-> 205
/*       */     //   #1225	-> 208
/*       */     //   #1227	-> 210
/*       */     //   #1228	-> 221
/*       */     //   #1231	-> 224
/*       */     //   #1232	-> 244
/*       */     //   #1236	-> 252
/*       */     //   #13073	-> 264
/*       */     //   #1236	-> 267
/*       */     //   #14073	-> 272
/*       */     //   #1236	-> 275
/*       */     //   #1241	-> 278
/*       */     //   #1243	-> 317
/*       */     //   #1184	-> 337
/*       */     //   #1245	-> 343
/*       */     // Local variable table:
/*       */     //   start	length	slot	name	descriptor
/*       */     //   0	344	0	this	Lutils/plugins/PluginManager/PluginManager;
/*       */     //   0	344	1	proxy	Ljava/lang/Object;
/*       */     //   0	344	2	override	Z
/*       */     //   10	334	3	clazz	Ljava/lang/Class;
/*       */     //   20	324	4	group	Lutils/plugins/settings/config/ConfigGroup;
/*       */     //   52	285	8	method	Ljava/lang/reflect/Method;
/*       */     //   63	274	9	item	Lutils/plugins/settings/config/ConfigItem;
/*       */     //   106	21	10	current	Ljava/lang/String;
/*       */     //   157	3	10	current	Ljava/lang/Object;
/*       */     //   169	39	10	defaultValue	Ljava/lang/Object;
/*       */     //   210	14	11	ex	Ljava/lang/Throwable;
/*       */     //   224	113	10	defaultValue	Ljava/lang/Object;
/*       */     //   244	93	11	current	Ljava/lang/String;
/*       */     //   252	85	12	valueString	Ljava/lang/String;
/*       */     // Local variable type table:
/*       */     //   start	length	slot	name	signature
/*       */     //   10	334	3	clazz	Ljava/lang/Class<*>;
/*       */     // Exception table:
/*       */     //   from	to	target	type
/*       */     //   160	205	208	java/lang/Throwable
/*       */   }
/*       */   
/*       */   public void unsetConfiguration(String groupName, String key) {
/*       */     unsetConfiguration(groupName, null, key);
/*       */   }
/*       */   
/*       */   public void unsetConfiguration(String groupName, String profile, String key) {
/*       */     String oldValue, wholeKey = getWholeKey(groupName, profile, key);
/*       */     synchronized (this) {
/*       */       oldValue = (String)properties.remove(wholeKey);
/*       */     } 
/*       */     if (oldValue == null)
/*       */       return; 
/*       */     log.debug("Unsetting configuration value for {}", wholeKey);
/*       */     this.handler.invalidate();
/*       */     saveConfig(false);
/*       */     ConfigChanged configChanged;
/*       */     (configChanged = new ConfigChanged()).setGroup(groupName);
/*       */     configChanged.setProfile(profile);
/*       */     configChanged.setKey(key);
/*       */     configChanged.setOldValue(oldValue);
/*       */   }
/*       */   
/*       */   public boolean drawChatboxFixedPlugins() {
/*       */     mO chatInterface;
/*       */     if ((chatInterface = mA.bxh[752]) == null)
/*       */       return false; 
/*       */     return (chatInterface.vH() != null);
/*       */   }
/*       */   
/*       */   public void skillUpdateEvent(int skillId, int xp, int currentLevel, int maxLevel) {
/*       */     for (Iterator<Plugin> iterator = getPlugins().iterator(); iterator.hasNext();)
/*       */       ((Plugin)iterator.next()).onSkillUpdate(skillId, xp, currentLevel, maxLevel); 
/*       */   }
/*       */   
/*       */   public List<Plugin> loadPlugins(List<Class<?>> plugins, BiConsumer<Integer, Integer> onPluginLoaded) throws Exception {
/*       */     // Byte code:
/*       */     //   0: new com/a/a/d/l
/*       */     //   3: dup
/*       */     //   4: iconst_1
/*       */     //   5: invokespecial <init> : (Z)V
/*       */     //   8: invokevirtual dT : ()Lcom/a/a/d/q;
/*       */     //   11: astore_3
/*       */     //   12: aload_1
/*       */     //   13: invokeinterface iterator : ()Ljava/util/Iterator;
/*       */     //   18: astore #4
/*       */     //   20: aload #4
/*       */     //   22: invokeinterface hasNext : ()Z
/*       */     //   27: ifeq -> 132
/*       */     //   30: aload #4
/*       */     //   32: invokeinterface next : ()Ljava/lang/Object;
/*       */     //   37: checkcast java/lang/Class
/*       */     //   40: dup
/*       */     //   41: astore #5
/*       */     //   43: ldc utils/plugins/PluginDescriptor
/*       */     //   45: invokevirtual getAnnotation : (Ljava/lang/Class;)Ljava/lang/annotation/Annotation;
/*       */     //   48: checkcast utils/plugins/PluginDescriptor
/*       */     //   51: ifnonnull -> 85
/*       */     //   54: aload #5
/*       */     //   56: invokevirtual getSuperclass : ()Ljava/lang/Class;
/*       */     //   59: ldc utils/plugins/Plugin
/*       */     //   61: if_acmpne -> 20
/*       */     //   64: getstatic java/lang/System.out : Ljava/io/PrintStream;
/*       */     //   67: ldc 'Class {} is a plugin, but has no plugin descriptor'
/*       */     //   69: iconst_1
/*       */     //   70: anewarray java/lang/Object
/*       */     //   73: dup
/*       */     //   74: iconst_0
/*       */     //   75: aload #5
/*       */     //   77: aastore
/*       */     //   78: invokevirtual printf : (Ljava/lang/String;[Ljava/lang/Object;)Ljava/io/PrintStream;
/*       */     //   81: pop
/*       */     //   82: goto -> 20
/*       */     //   85: aload #5
/*       */     //   87: invokevirtual getSuperclass : ()Ljava/lang/Class;
/*       */     //   90: ldc utils/plugins/Plugin
/*       */     //   92: if_acmpeq -> 116
/*       */     //   95: getstatic java/lang/System.out : Ljava/io/PrintStream;
/*       */     //   98: ldc 'Class {} has plugin descriptor, but is not a plugin'
/*       */     //   100: iconst_1
/*       */     //   101: anewarray java/lang/Object
/*       */     //   104: dup
/*       */     //   105: iconst_0
/*       */     //   106: aload #5
/*       */     //   108: aastore
/*       */     //   109: invokevirtual printf : (Ljava/lang/String;[Ljava/lang/Object;)Ljava/io/PrintStream;
/*       */     //   112: pop
/*       */     //   113: goto -> 20
/*       */     //   116: aload #5
/*       */     //   118: astore #7
/*       */     //   120: aload_3
/*       */     //   121: aload #7
/*       */     //   123: invokeinterface K : (Ljava/lang/Object;)Z
/*       */     //   128: pop
/*       */     //   129: goto -> 20
/*       */     //   132: aload_3
/*       */     //   133: invokeinterface dG : ()Ljava/util/Set;
/*       */     //   138: invokeinterface iterator : ()Ljava/util/Iterator;
/*       */     //   143: astore #4
/*       */     //   145: aload #4
/*       */     //   147: invokeinterface hasNext : ()Z
/*       */     //   152: ifeq -> 245
/*       */     //   155: aload #4
/*       */     //   157: invokeinterface next : ()Ljava/lang/Object;
/*       */     //   162: checkcast java/lang/Class
/*       */     //   165: dup
/*       */     //   166: astore #5
/*       */     //   168: ldc utils/plugins/PluginDependency
/*       */     //   170: invokevirtual getAnnotationsByType : (Ljava/lang/Class;)[Ljava/lang/annotation/Annotation;
/*       */     //   173: checkcast [Lutils/plugins/PluginDependency;
/*       */     //   176: dup
/*       */     //   177: astore #7
/*       */     //   179: arraylength
/*       */     //   180: istore #8
/*       */     //   182: iconst_0
/*       */     //   183: istore #9
/*       */     //   185: iload #9
/*       */     //   187: iload #8
/*       */     //   189: if_icmpge -> 242
/*       */     //   192: aload #7
/*       */     //   194: iload #9
/*       */     //   196: aaload
/*       */     //   197: astore #10
/*       */     //   199: aload_3
/*       */     //   200: invokeinterface dG : ()Ljava/util/Set;
/*       */     //   205: aload #10
/*       */     //   207: invokeinterface value : ()Ljava/lang/Class;
/*       */     //   212: invokeinterface contains : (Ljava/lang/Object;)Z
/*       */     //   217: ifeq -> 236
/*       */     //   220: aload_3
/*       */     //   221: aload #5
/*       */     //   223: aload #10
/*       */     //   225: invokeinterface value : ()Ljava/lang/Class;
/*       */     //   230: invokeinterface q : (Ljava/lang/Object;Ljava/lang/Object;)Z
/*       */     //   235: pop
/*       */     //   236: iinc #9, 1
/*       */     //   239: goto -> 185
/*       */     //   242: goto -> 145
/*       */     //   245: aload_3
/*       */     //   246: dup
/*       */     //   247: astore #11
/*       */     //   249: invokeinterface dE : ()Ljava/util/Set;
/*       */     //   254: invokeinterface size : ()I
/*       */     //   259: dup
/*       */     //   260: istore #12
/*       */     //   262: ifeq -> 366
/*       */     //   265: aload #11
/*       */     //   267: invokeinterface dH : ()Z
/*       */     //   272: ifne -> 296
/*       */     //   275: iload #12
/*       */     //   277: aload #11
/*       */     //   279: invokeinterface dG : ()Ljava/util/Set;
/*       */     //   284: invokeinterface size : ()I
/*       */     //   289: if_icmplt -> 296
/*       */     //   292: iconst_1
/*       */     //   293: goto -> 367
/*       */     //   296: aload #11
/*       */     //   298: invokeinterface dG : ()Ljava/util/Set;
/*       */     //   303: invokeinterface size : ()I
/*       */     //   308: invokestatic aV : (I)Ljava/util/HashMap;
/*       */     //   311: astore #13
/*       */     //   313: aload #11
/*       */     //   315: invokeinterface dG : ()Ljava/util/Set;
/*       */     //   320: invokeinterface iterator : ()Ljava/util/Iterator;
/*       */     //   325: astore #14
/*       */     //   327: aload #14
/*       */     //   329: invokeinterface hasNext : ()Z
/*       */     //   334: ifeq -> 366
/*       */     //   337: aload #14
/*       */     //   339: invokeinterface next : ()Ljava/lang/Object;
/*       */     //   344: astore #15
/*       */     //   346: aload #11
/*       */     //   348: aload #13
/*       */     //   350: aload #15
/*       */     //   352: aconst_null
/*       */     //   353: invokestatic a : (Lcom/a/a/d/k;Ljava/util/Map;Ljava/lang/Object;Ljava/lang/Object;)Z
/*       */     //   356: ifeq -> 363
/*       */     //   359: iconst_1
/*       */     //   360: goto -> 367
/*       */     //   363: goto -> 327
/*       */     //   366: iconst_0
/*       */     //   367: ifeq -> 380
/*       */     //   370: new java/lang/Exception
/*       */     //   373: dup
/*       */     //   374: ldc 'Plugin dependency graph contains a cycle!'
/*       */     //   376: invokespecial <init> : (Ljava/lang/String;)V
/*       */     //   379: athrow
/*       */     //   380: aload_0
/*       */     //   381: aload_3
/*       */     //   382: invokespecial topologicalSort : (Lcom/a/a/d/k;)Ljava/util/List;
/*       */     //   385: invokestatic a : (Ljava/util/List;)Ljava/util/List;
/*       */     //   388: astore #4
/*       */     //   390: iconst_0
/*       */     //   391: istore #5
/*       */     //   393: new java/util/ArrayList
/*       */     //   396: dup
/*       */     //   397: invokespecial <init> : ()V
/*       */     //   400: astore #6
/*       */     //   402: aload #4
/*       */     //   404: invokeinterface iterator : ()Ljava/util/Iterator;
/*       */     //   409: astore #7
/*       */     //   411: aload #7
/*       */     //   413: invokeinterface hasNext : ()Z
/*       */     //   418: ifeq -> 548
/*       */     //   421: aload #7
/*       */     //   423: invokeinterface next : ()Ljava/lang/Object;
/*       */     //   428: checkcast java/lang/Class
/*       */     //   431: astore #8
/*       */     //   433: aload_0
/*       */     //   434: dup
/*       */     //   435: getfield plugins : Ljava/util/List;
/*       */     //   438: aload #8
/*       */     //   440: invokespecial instantiate : (Ljava/util/List;Ljava/lang/Class;)Lutils/plugins/Plugin;
/*       */     //   443: astore #9
/*       */     //   445: aload #6
/*       */     //   447: aload #9
/*       */     //   449: invokeinterface add : (Ljava/lang/Object;)Z
/*       */     //   454: pop
/*       */     //   455: aload_0
/*       */     //   456: getfield plugins : Ljava/util/List;
/*       */     //   459: aload #9
/*       */     //   461: invokeinterface add : (Ljava/lang/Object;)Z
/*       */     //   466: pop
/*       */     //   467: aload #9
/*       */     //   469: instanceof utils/plugins/impl/zeah/ZeahPlugin
/*       */     //   472: ifeq -> 481
/*       */     //   475: ldc utils/plugins/impl/zeah/ZeahPlugin
/*       */     //   477: iconst_1
/*       */     //   478: invokestatic setEnabled : (Ljava/lang/Class;Z)V
/*       */     //   481: goto -> 517
/*       */     //   484: astore #10
/*       */     //   486: getstatic java/lang/System.out : Ljava/io/PrintStream;
/*       */     //   489: new java/lang/StringBuilder
/*       */     //   492: dup
/*       */     //   493: ldc 'Error initializing plugin '
/*       */     //   495: invokespecial <init> : (Ljava/lang/String;)V
/*       */     //   498: aload #8
/*       */     //   500: invokevirtual getSimpleName : ()Ljava/lang/String;
/*       */     //   503: invokevirtual append : (Ljava/lang/String;)Ljava/lang/StringBuilder;
/*       */     //   506: invokevirtual toString : ()Ljava/lang/String;
/*       */     //   509: invokevirtual println : (Ljava/lang/String;)V
/*       */     //   512: aload #10
/*       */     //   514: invokevirtual printStackTrace : ()V
/*       */     //   517: iinc #5, 1
/*       */     //   520: aload_2
/*       */     //   521: ifnull -> 545
/*       */     //   524: aload_2
/*       */     //   525: iload #5
/*       */     //   527: invokestatic valueOf : (I)Ljava/lang/Integer;
/*       */     //   530: aload #4
/*       */     //   532: invokeinterface size : ()I
/*       */     //   537: invokestatic valueOf : (I)Ljava/lang/Integer;
/*       */     //   540: invokeinterface accept : (Ljava/lang/Object;Ljava/lang/Object;)V
/*       */     //   545: goto -> 411
/*       */     //   548: aload #6
/*       */     //   550: areturn
/*       */     // Line number table:
/*       */     //   Java source line number -> byte code offset
/*       */     //   #2077	-> 0
/*       */     //   #674	-> 8
/*       */     //   #676	-> 12
/*       */     //   #678	-> 41
/*       */     //   #680	-> 51
/*       */     //   #682	-> 54
/*       */     //   #684	-> 64
/*       */     //   #689	-> 85
/*       */     //   #691	-> 95
/*       */     //   #692	-> 113
/*       */     //   #708	-> 116
/*       */     //   #709	-> 120
/*       */     //   #710	-> 129
/*       */     //   #713	-> 132
/*       */     //   #715	-> 166
/*       */     //   #717	-> 176
/*       */     //   #719	-> 199
/*       */     //   #721	-> 220
/*       */     //   #717	-> 236
/*       */     //   #724	-> 242
/*       */     //   #726	-> 245
/*       */     //   #3062	-> 247
/*       */     //   #3063	-> 260
/*       */     //   #3066	-> 265
/*       */     //   #3067	-> 292
/*       */     //   #3070	-> 296
/*       */     //   #3071	-> 298
/*       */     //   #3072	-> 313
/*       */     //   #3073	-> 346
/*       */     //   #3074	-> 359
/*       */     //   #3076	-> 363
/*       */     //   #3077	-> 366
/*       */     //   #726	-> 367
/*       */     //   #728	-> 370
/*       */     //   #731	-> 380
/*       */     //   #732	-> 385
/*       */     //   #734	-> 390
/*       */     //   #735	-> 393
/*       */     //   #736	-> 402
/*       */     //   #741	-> 433
/*       */     //   #742	-> 445
/*       */     //   #743	-> 455
/*       */     //   #744	-> 467
/*       */     //   #745	-> 475
/*       */     //   #752	-> 481
/*       */     //   #748	-> 484
/*       */     //   #750	-> 486
/*       */     //   #751	-> 512
/*       */     //   #754	-> 517
/*       */     //   #755	-> 520
/*       */     //   #757	-> 524
/*       */     //   #759	-> 545
/*       */     //   #761	-> 548
/*       */     // Local variable table:
/*       */     //   start	length	slot	name	descriptor
/*       */     //   0	551	0	this	Lutils/plugins/PluginManager/PluginManager;
/*       */     //   0	551	1	plugins	Ljava/util/List;
/*       */     //   0	551	2	onPluginLoaded	Ljava/util/function/BiConsumer;
/*       */     //   12	539	3	graph	Lcom/a/a/d/q;
/*       */     //   41	88	5	clazz	Ljava/lang/Class;
/*       */     //   51	78	6	pluginDescriptor	Lutils/plugins/PluginDescriptor;
/*       */     //   120	9	7	pluginClass	Ljava/lang/Class;
/*       */     //   166	76	5	pluginClazz	Ljava/lang/Class;
/*       */     //   176	66	6	pluginDependencies	[Lutils/plugins/PluginDependency;
/*       */     //   199	37	10	pluginDependency	Lutils/plugins/PluginDependency;
/*       */     //   385	166	4	sortedPlugins	Ljava/util/List;
/*       */     //   393	158	5	loaded	I
/*       */     //   402	149	6	newPlugins	Ljava/util/List;
/*       */     //   433	112	8	pluginClazz	Ljava/lang/Class;
/*       */     //   445	39	9	plugin	Lutils/plugins/Plugin;
/*       */     //   486	31	10	ex	Ljava/lang/Exception;
/*       */     // Local variable type table:
/*       */     //   start	length	slot	name	signature
/*       */     //   0	551	1	plugins	Ljava/util/List<Ljava/lang/Class<*>;>;
/*       */     //   0	551	2	onPluginLoaded	Ljava/util/function/BiConsumer<Ljava/lang/Integer;Ljava/lang/Integer;>;
/*       */     //   12	539	3	graph	Lcom/a/a/d/q<Ljava/lang/Class<+Lutils/plugins/Plugin;>;>;
/*       */     //   41	88	5	clazz	Ljava/lang/Class<*>;
/*       */     //   120	9	7	pluginClass	Ljava/lang/Class<Lutils/plugins/Plugin;>;
/*       */     //   166	76	5	pluginClazz	Ljava/lang/Class<+Lutils/plugins/Plugin;>;
/*       */     //   385	166	4	sortedPlugins	Ljava/util/List<Ljava/lang/Class<+Lutils/plugins/Plugin;>;>;
/*       */     //   402	149	6	newPlugins	Ljava/util/List<Lutils/plugins/Plugin;>;
/*       */     //   433	112	8	pluginClazz	Ljava/lang/Class<+Lutils/plugins/Plugin;>;
/*       */     // Exception table:
/*       */     //   from	to	target	type
/*       */     //   433	481	484	java/lang/Exception
/*       */   }
/*       */ }


/* Location:              C:\Users\brett\OneDrive\Desktop\Zeah Decompiled .java\zeah-client.jar\\utils\plugins\PluginManager\PluginManager.class
 * Java compiler version: 8 (52.0)
 * JD-Core Version:       1.1.3
 */